Workbook
Name Compute_P0: Assumptions!$G$14
Name Deal_WACC_premium: Assumptions!$G$46
Name ErrorTolerance: Checks!$C$2
Name Facility_capex_MW: Assumptions!$G$10
Name Facility_salvage_pct: Assumptions!$G$18
Name Floor_ext_high: Assumptions!$D$68
Name Floor_ext_low: Assumptions!$D$67
Name FloorTolerance: Assumptions!$D$69
Name GPU_life: Assumptions!$G$16
Name GPU_salvage_pct: Assumptions!$G$19
Name Hours_per_year: Assumptions!$F$28
Name Insurance_rate: Assumptions!$F$30
Name IT_load_MW: Assumptions!$G$21
Name List_Country: Assumptions!$B$50:$B$54
Name List_ReviewStatus: Assumptions!$B$58:$B$60
Name List_Scenario: Assumptions!$D$9:$F$9
Name OM_fixed: Assumptions!$G$17
Name Paid_occupancy: Assumptions!$G$15
Name Price_decline: Assumptions!$G$65
Name Price_floor: Assumptions!$G$66
Name Prop_tax_abatement: Assumptions!$F$31
Name Ramp_yr1: Assumptions!$F$32
Name Ramp_yr2: Assumptions!$F$33
Name Risk_free: Assumptions!$F$39
Name Shadow_carbon_price: Assumptions!$F$40
Name TTP_disp_hi: 'Interconnection Queue'!$F$4
Name TTP_disp_lo: 'Interconnection Queue'!$F$5
Name Unit_scale: Assumptions!$F$29

Sheet Cover
A1: 100 MW Data-Center Unit-Economics Model (Norway, Saudi Arabia, United States, Ireland, India) | C1: =IF(Checks!$C$4>0,"MODEL IN ERROR","checks OK") -> checks OK
A2: Finding: power is a trivial cost (~1–2% of revenue) at today's price, but it crosses to material once a long grid queue erodes the entry price to the floor.
A3: Owner: Henry Dalby · Status: PUBLISH · Periods 0–19 (annual) · Single workbook, no external links
A4: Thesis: with calendar-coupled compute-price erosion, time-to-power reorderds viability and destroys value in slow-queue geographies. Purpose: compare the viability of a 100 MW AI data center across 5 countries from an auditable per-MW asset P&L (per-period DCF).
A5: Intended users: the analyst (Henry) first; auditable by a finance professional on first open.
A6: What this IS: an indicative, comparative unit-economics model ranking five countries on AI-data-centre viability. · What it is FOR: the relative ranking and the drivers that move it (queue length, power, WACC, price erosion). · What it is NOT: a bankable, financing-grade valuation of any single project — absolute NPVs are directional. See the Limitations tab.
A7: Format key (River / FAST convention)
A8: Blue font | B8: Data origin — an input you may change, or a value linked in from another sheet
A9: Black font | B9: Calculated on this sheet
A10: Red font | B10: Output consumed elsewhere, or a check / status flag
A11: Only unlocked cells are editable | B11: Sheets are protected; blue input cells on Assumptions / Buildout / Review are the only editable cells
A12: Brackets = negative, dash = zero | B12: Standard finance display; units column on every calc row
A13: Tab colours by section | B13: Navy = structural/navigation · amber = inputs · steel-blue = calculations · green = outputs · gold = checks
A14: Contents
A15: Model map | B15: how it fits together
A16: Limitations | B16: scope qualifiation--read before the results
A17: Sources | B17: source data graded by confidence key
A18: GPU Specs | B18: primary spec data per single accelerator. B200
A19: Compute Price Data | B19: getDeploying B200 panel + Silicon Data SDB200RT index are the primary basis
A20: Interconnection Queue | B20: US data with observed dispersion calculation
A21: Power Build-up | B21: wholesale grid/firming prices
A22: WACC Build-up | B22: USD-nominal cost of capital decomposed
A23: Assumptions | B23: distilled drivers + country data Table (last in inputs)
A24: Capex Stack | B24: shell/fit-out/GPU/networking per MW
A25: Unit Economics | B25: per-MW build block + external anchor
A26: Buildout Schedule | B26: deployment records Table
... A48: Reconciliation: Calculations (active drill) = Country Engine (all countries × deals, per period) = Comparison, to the dollar; Checks!C4 = 0 with zero error cells across every scenario × deal × country state. | B48: country records Table

Sheet Model map
A1: Model map — how this workbook fits together | C1: =IF(Checks!$C$4>0,"MODEL IN ERROR","checks OK") -> checks OK
A2: Orient once, navigate anywhere. Three toggles drive everything; data flows one direction; reconciliations keep it honest.
D3: Workbook status | E3: =IF(Checks!$C$4>0,"MODEL IN ERROR","checks OK") -> checks OK
A4: 1 · The three toggles (set on Assumptions)
B5: Toggle | C5: Set on | D5: Options | E5: What it drives
B6: Scenario | C6: Assumptions!B4 | D6: Bear / Base / Bull | E6: Delivered power, time-to-power, WACC (all countries)
B7: Country | C7: Assumptions!B5 | D7: Norway/US/India/Ireland/Saudi | E7: Which country Calculations & Country detail present
B8: Deal type | C8: Assumptions!B7 | D8: Contracted / Merchant | E8: Occupancy, WACC premium
A10: 2 · Data flow — one direction, no circularity
B11: Sourcing tabs (GPU Specs, Compute Price Data, Interconnection Queue, Power/WACC Build-ups) → Assumptions (distilled drivers, last in inputs)
B12: ↓
B13: Capex Stack → Unit Economics (per-MW) → Buildout Schedule (facility-capex draw) → Calculations (per-period DCF)
B14: ↓
B15: Comparison (all 5 countries, closed-form) → Country detail → Scenario Grid → Checks
B16: Energy Security (WEC Trilemma) is a FENCED labelled-implication tab — it does NOT feed the P&L.
A19: 3 · Reconciliations (all on Checks; C4 must = 0)
B20: • Two-engine tie: Calculations per-period NPV = Comparison closed-form NPV (active country)
B21: • Roll-up tie: Unit Economics per-MW × IT load = Calculations facility + GPU capex
B22: • Buildout tie: DCF facility-capex draw (Σ per-period) reconciles to the facility capex total; draw weights sum to 1
B23: • Scenario Grid tie: active-country grid NPV = Calculations NPV
B24: • EXTERNAL ANCHORS: capex/MW in $30–50m band; revenue/MW/yr in $15–40m band (sourced)
A26: 4 · Key drivers (High materiality)
B27: • Compute price ($/GPU-hr) — largest NPV lever
B28: • GPU+IT capex & density — physically coupled across chip generations
B29: • Time-to-power (yr) — the sharpest country-varying energy lever
B30: • Cost of capital — unlevered hurdle rate (WACC proxy) — country-varying
B31: • IT load (MW) — scale
A33: 5 · Disclosed modelling choices
B34: • Country Engine net-FCF is one long row (~228 chars) — but FLAT (2 IFs, not nested) and single-purpose. Deliberate compact-engine tradeoff: the 15-block Country Engine stays readable by inlining the cash-flow aggregation into one line; the fully-decomposed, one-row-per-component version lives on Calculations.
B35: • Reference/build-up tabs (Power Build-up, WACC Build-up, GPU Specs, Compute Price Data) are RECONCILED to Assumptions by check (Checks r22/r24/r25), not live-linked. Assumptions holds the authoritative hardcodes; the build-ups show the derivation. Interconnection Queue is the live-linked source: US TTP (median/p75/p25) plus the dispersion ratios that set the other four countries’ TTP bands.

Sheet Limitations
A1: Limitations & scope — read before the results | C1: =IF(Checks!$C$4>0,"MODEL IN ERROR","checks OK") -> checks OK
A2: This is an INDICATIVE, comparative unit-economics model for ranking five countries — not a bankable, financing-grade valuation. It is deliberately simple; the limitations below are disclosed by design, not oversights. Absolute NPVs carry the uncertainty of all inputs; the country RANKING is the robust output.
A4: # | B4: Limitation | C4: Effect on the results | D4: How it is handled / disclosed
A5: 1 | B5: Indicative, not bankable | C5: Unlevered, single-hold; absolute NPV is directional, not a financing valuation. | D5: Use for cross-country ranking, not underwriting. Stated on Cover / Model map. No equity valuation or demand forecasting.
A6: 2 | B6: Compute-price decline & floor are PROJECTIONS | C6: B200 has not yet entered its decline; the 20%/yr erosion and $2.50 floor drive the economics. | D6: Calibrated to the realized H100 lifecycle; flagged as estimates in Sources (r34/r39-41) and on the Price Floor tab.
A7: 3 | B7: Single-hold liquidation framing | C7: One GPU cycle then exit; real operators may re-tenant, which would raise returns. | D7: Deliberate simplification; disclosed. Re-tenanting removed to keep the model auditable.
A8: 4 | B8: Grid carbon NOT priced | C8: A pure-$/MWh ranking would silently favour cheap-but-dirty grids. | D8: Grid carbon intensity (gCO2/kWh) shown as a second lens on Comparison (r42), explicitly NOT in the NPV.
A9: 5 | B9: Ireland CRU Large-Energy-User policy (late-2025) | C9: New DCs >10 MVA must self-generate 100% flexible + source 80% new renewables in 6 yr — a capex/feasibility burden not priced. Effect on results is unambiguously negative for Ireland: it does NOT change the Base/Bull ranking (Ireland is already last), but Ireland's Bear ‘least-bad’ rank (1st — its price is already at the floor, so it has the least erosion downside) is overstated and would fall if the CRU generation/storage capex and ~6-yr approval timing were costed. Deliberately not modelled, to avoid false precision. Source: CRU/EirGrid Dec-2025 (Sources r14/r30). | D9: Disclosed; it makes Ireland (already last on NPV) harder still. Model UNDERSTATES Ireland difficulty.
A10: 6 | B10: Water / cooling-water cost not separately modelled | C10: Material in hot climates (India, Saudi); modestly understates their opex. | D10: Disclosed caveat; folded into O&M at a country-flat rate.
A11: 7 | B11: US export controls / chip access (status as of Aug 2026) | C11: Ranking assumes lawful Blackwell (B200/GB200) procurement — presumption-of-denial by default. US/Norway/Ireland: unrestricted (domestic/allied). Saudi: conditional — approved via HUMAIN (Nov-2025) under RTE security/reporting + cap. India: licensed/capped (trusted-partner quota, ~270k H100-eq in 2026). No modelled country is blocked, but Saudi/India access is conditional. | D11: Boundary condition, NOT priced in the NPV; the ranking is conditional on access holding. Regime is transactional/volatile (Diffusion Rule rescinded May-2025). Sources: US Commerce Nov-2025; BIS/IISS 2025-26. Developed in the article.
A12: 8 | B12: Single 100 MW reference facility | C12: Per-MW unit economics; not a portfolio, staged-build, or financing model. | D12: Scale is a normalisation, not a forecast. Disclosed.
A13: 9 | B13: Networking fabric, GPU attrition, decommissioning | C13: Not separately line-itemed; minor understatement of cost. | D13: Folded into capex/O&M or omitted; disclosed. Immaterial to the ranking.
A14: 10 | B14: Delivered power is zone/market-dependent | C14: US = ERCOT basis (PJM 2–3× higher); Norway = blended NO zones. | D14: Disclosed on Power Build-up; delivered price validated vs observed industrial all-in.
A15: 11 | B15: Point-in-time sources | C15: Prices, tariffs, and queues as of ~Aug 2026 in a fast-moving market. | D15: Every input dated & graded on Sources; refresh before re-use.
... A23: 19 | B23: Time-to-power band methodology | C23: Non-US TTP dispersion is transferred from the US LBNL distribution (the only observed one); country medians are regulator-sourced. Ireland’s upper tail is likely fatter than the transferred IQR (CRU policy). | D23: US bands observed (LBNL); non-US bands = median × US IQR. Disclosed on Assumptions & Sources r51.
B25: Chip-access feasibility screen — export-control status by country (as of ~Aug 2026; verify current BIS rules before relying). Blackwell/B200 default = licence-required; named operator/end-user, supply route and basis below. Sources: [39][44][45].
B26: Country | C26: Chip-access status | D26: Named operator / end-user | E26: Supply route | F26: Basis / citation
B27: Norway | C27: Permitted — no US licence (EEA/NATO; Country Group A) | D27: nScale — Glomfjord AI data centre (hydro) | E27: NVIDIA → OEM → nScale (EEA) | F27: BIS EAR §742.6 [44]; operators/routes [45]
B28: United States | C28: Permitted — domestic (no export) | D28: US hyperscalers / neoclouds (e.g., CoreWeave) | E28: Domestic build | F28: BIS EAR [44] (no export)
B29: India | C29: Licence-required — approvals flowing (not Tier 1) | D29: Reliance (1 GW Gujarat); Tata Communications; Yotta (20,736 Blackwell Ultra) | E29: NVIDIA → OEM → Indian operator under US licence | F29: Export controls [39]; framework [44]; operators [45]; DPDP Act 2023
B30: Ireland | C30: Permitted — EU/Tier 1 (grid connection, not chips, is the binding gate) | D30: EU hyperscaler cloud (Dublin) | E30: NVIDIA → OEM → EU operator | F30: BIS EAR [44]; Ireland CRU policy [11]
B31: Saudi Arabia | C31: Licence-required — conditionally AUTHORISED Nov-2025 (end-user-specific) | D31: HUMAIN (PIF): up to 35,000 GB300 authorised; plan ~600k accelerators | E31: NVIDIA → OEM → HUMAIN; BIS security/reporting conditions | F31: US Commerce/BIS 19-Nov-2025 [39][44]
B32: Implication: “lawful chip access” is not uniform across the five. Norway/US/Ireland are unrestricted; India and Saudi require US licences (Saudi’s is conditional and specific to HUMAIN). Any country’s NPV rank is contingent on the named operator holding a valid licence/authorisation and meeting BIS security conditions — the model still holds chip access constant, so the India/Saudi ranks are conditional.

Sheet ▸ INPUTS
A1: ▸ INPUTS

Sheet Sources
A1: Sources | D1: =IF(Checks!$C$4>0,"MODEL IN ERROR","checks OK") -> checks OK
A2: High = primary/operator/regulator · Med = specialist aggregator · Low = disclosed judgment.
A3: # | B3: Input | C3: Value / note | D3: Named source | E3: Vintage | F3: Source confidence | G3: Source link
A4: 1 | B4: Facility build capex | C4: $17m/MW Base (band 13–24) | D4: AI liquid-cooled 2026 (ModulEdge/Epoch) | E4: 2026 | F4: Med | G4: https://epoch.ai/data-insights/ai-datacenter-cost-breakdown
A5: 2 | B5: GPU + IT capex | C5: $42,000/single B200 GPU deployed (band $35–56k: DGX B200 ~$35–40k/GPU; HGX B200 ~$56k; card $40–50k) | D5: Mercatus B200 server price; Silicon Analysts B200 cost breakdown; NVIDIA DGX B200 | E5: 2026 | F5: Med | G5: https://www.mercatus-ai.com/blog/b200-server-price
A6: 3 | B6: GPUs per MW | C6: ~600 GPU/MW (B200 1000W; HGX node ~13.3kW/8 → 1.667 kW/GPU) | D6: NVIDIA B200 / HGX B200 datasheet | E6: 2025-26 | F6: Med | G6: https://www.nvidia.com/en-us/data-center/hgx/
A7: 4 | B7: PUE (country-varying) | C7: NO 1.15 / IE 1.20 / US 1.30 / SA 1.45 / IN 1.50 | D7: LBNL 2024 US DC Energy Usage Report | E7: 2024-26 | F7: Med | G7: https://eta.lbl.gov/publications/2024-lbnl-data-center-energy-usage-report
A8: 5 | B8: Compute price | C8: $5.70/GPU-hr Base P0 (committed 1-yr, today); band $4.00–$9.00 Bear→Bull; erodes ~20%/yr to full-cost floor | D8: Silicon Data SDB200RT index; getDeploying B200 committed panel (45 listings, 7-Aug-2026) | E8: 2026 | F8: High | G8: https://www.silicondata.com/products/silicon-index
A9: 6 | B9: Utilization / occupancy | C9: 88% contracted / 70% merchant | D9: CBRE DC vacancy ~1.4%, ~74% pre-leased | E9: 2026 | F9: Low | G9: https://www.cbre.com/insights/reports/global-data-center-trends-2026
A10: 7 | B10: GPU economic life | C10: 5 yr (Bear 3 / Bull 6) | D10: Hyperscaler 10-K (Amazon 5yr, Meta 5.5yr) | E10: 2025-26 | F10: Med | G10: https://thecuberesearch.com/298-breaking-analysis-resetting-gpu-depreciation
A11: 8 | B11: Norway power / TTP / WACC | C11: $52/MWh · 2.0yr · 6.34% | D11: SSB; Statnett 2025; Damodaran 2026 | E11: 2025-26 | F11: Med | G11: https://www.ssb.no/en/energi-og-industri
A12: 9 | B12: US power / TTP / WACC | C12: $60/MWh · 4.5yr · 6.34% | D12: TTP=LBNL queue (uploaded, thru-2025): recent-cohort (online≥2019) median 4.5yr, p25 3.2/p75 5.8, N=1,297 operational; WACC per build-up | E12: 2025-26 | F12: High | G12: https://emp.lbl.gov/queues
A13: 10 | B13: India power / TTP / WACC | C13: $95/MWh · 3.0yr · 7.84% USD-nom | D13: GlobalPetrolPrices; Deccan Chronicle Jan-26; Damodaran | E13: 2025-26 | F13: Med | G13: https://www.deccanchronicle.com/business/latest/what-india-can-learn-from-the-us-about-data-centres-1973592
A14: 11 | B14: Ireland power / TTP / WACC | C14: $150/MWh · 6.0yr · 6.84% USD-nom | D14: CRU/EirGrid Dec-2025 policy; Damodaran | E14: 2025-26 | F14: Med | G14: https://www.cru.ie/
A15: 12 | B15: Saudi power / TTP / WACC | C15: $48/MWh · 2.0yr · 6.84% USD-nom | D15: SEC tariff; SERA framework (GT Jan-26); Damodaran | E15: 2025-26 | F15: Med | G15: https://www.gtlaw.com/en/insights/2026/1/saudi-arabias-data-centre-expansion-regulatory-framework-and-strategic-considerations
... A51: 48 | B51: GPU rental price — Azure H100 (mature-generation analog) | C51: Azure H100 SXM by tier (on-demand / reserved 1-3-5yr / spot); context analog for the B200 lifecycle — feeds no P&L. | D51: Microsoft Azure Retail Prices API | E51: 2026 | F51: High | G51: https://prices.azure.com/api/retail/prices
A54: Source-reliability grading key (col E)
A55: Grades the RELIABILITY OF THE SOURCE behind each input — NOT statistical confidence. Ordinal source-quality rating (tier × vintage × directness). Quantitative uncertainty is carried SEPARATELY by the input bands (Bear/Base/Bull) and the Sensitivity tornado.
A56: High | B56: Primary source (official statistics / regulator / grid operator / IEA / EIA / Ember / Damodaran / vendor datasheet), current vintage (2025–26), direct measure — used as published.
A57: Med-High | B57: Primary market data + a primary reference model (e.g. sovereign 10-yr yield + Damodaran country-risk premium). Stronger than Med, short of a single direct measure.
A58: Med | B58: Primary source needing adjustment/interpolation, OR a reputable specialist aggregator (SemiAnalysis / CBRE / JLL / Lazard), current vintage.
A59: Low | B59: Single secondary source, proxy, disclosed judgment residual, or definitional uncertainty. Directional and flagged as such (e.g. merchant occupancy, idle-shell holding cost, WACC project premium, power firming residual).

Sheet GPU Specs
A1: GPU Specs — per accelerator (NVIDIA datasheets) · modelled generation: NVIDIA B200 (Blackwell, HGX) | C1: =IF(Checks!$C$4>0,"MODEL IN ERROR","checks OK") -> checks OK
A2: Primary spec data per single accelerator. B200 (HGX 8-GPU) is the modelled generation; H100 and GB200 NVL72 shown for reference/continuity.
A3: REFERENCE TAB — density (col F, B200 row) reconciled to Assumptions G12 by Checks r22; not live-linked.
A4: Specs — per accelerator (NVIDIA datasheets)
A5: GPU (accelerator) | B5: Power (W) | C5: Memory (GB) | D5: Per rack/board | E5: kW/rack | F5: Implied GPU/MW | G5: Source
A6: H100 SXM5 — prior-gen reference | B6: 700 | C6: 80 | D6: 8 (HGX) | E6: — | F6: — | G6: [17]
A7: B200 (HGX) — MODELLED | B7: 1000 | C7: 192 | D7: 8 (HGX) | E7: 13.33 | F7: =ROUND(1000/(E7/8),0) -> 600 | G7: [17]
A8: GB200 (Blackwell, NVL72) — frontier reference (not modelled) | B8: 1200 | C8: 192 | D8: 72 (NVL72) | E8: 120 | F8: =ROUND(1000/(E8/72),0) -> 600 | G8: [17]
A9: B200 implied density = 1 MW ÷ (HGX node 13.3 kW ÷ 8 GPU = 1.667 kW/GPU) ≈ 600 GPU/MW → ties to Assumptions density (G12).

Sheet Compute Price Data
A1: Compute Price Data — $/GPU-hr evidence (NVIDIA B200, Blackwell) | C1: =IF(Checks!$C$4>0,"MODEL IN ERROR","checks OK") -> checks OK
A2: getDeploying B200 panel (7-Aug-2026, ~110 listings) + Silicon Data SDB200RT index are the primary basis. Azure H100 surface below is retained as the mature-generation analog (lifecycle & floor template).
A3: REFERENCE TAB — observed $/GPU-hr envelope; the P0 inputs are checked against it (Checks r35/r36); not live-linked.
A4: H100 SXM by tier — mature-generation analog (AVERAGEIFS over the raw Azure table; continuity/floor template) [48]
A5: Tier | B5: n (COUNTIFS) | C5: Mean $/GPU-hr | D5: Source
A6: On-demand | B6: =COUNTIFS(AzurePrice[Tier],"On-demand") -> 24 | C6: =AVERAGEIFS(AzurePrice[$/GPU-hr],AzurePrice[Tier],"On-demand") -> 16.053333 | D6: [48]
A7: Reserved 1yr | B7: =COUNTIFS(AzurePrice[Tier],"Reserved 1yr") -> 24 | C7: =AVERAGEIFS(AzurePrice[$/GPU-hr],AzurePrice[Tier],"Reserved 1yr") -> 10.26125 | D7: [48]
A8: Reserved 3yr | B8: =COUNTIFS(AzurePrice[Tier],"Reserved 3yr") -> 24 | C8: =AVERAGEIFS(AzurePrice[$/GPU-hr],AzurePrice[Tier],"Reserved 3yr") -> 7.0366667 | D8: [48]
A9: Reserved 5yr | B9: =COUNTIFS(AzurePrice[Tier],"Reserved 5yr") -> 24 | C9: =AVERAGEIFS(AzurePrice[$/GPU-hr],AzurePrice[Tier],"Reserved 5yr") -> 6.4125 | D9: [48]
A10: Spot | B10: =COUNTIFS(AzurePrice[Tier],"Spot") -> 24 | C10: =AVERAGEIFS(AzurePrice[$/GPU-hr],AzurePrice[Tier],"Spot") -> 2.9666667 | D10: [48]
A12: getDeploying neocloud B200 by tier (7-Aug-2026) + Silicon Data SDB200RT [19]
A13: Billing | B13: Listings | C13: Avg $/GPU-hr | D13: Source
A14: On-demand | B14: 35 | C14: 6.85 | D14: [18][19]
A15: Reserved / committed 1yr | B15: 45 | C15: 5.71 | D15: [18][19]
A16: Custom contract | B16: 7 | C16: 3.49 | D16: [18][19]
A17: Spot | B17: 20 | C17: 3.6 | D17: [18][19]
A19: Envelope for the compute-price check ($/GPU-hr) — B200
A20: Observed floor (B200 committed/spot low) | C20: 3.35 | D20: [34]
A21: Realized ceiling (B200 on-demand high) | C21: 8.2 | D21: [19]
A22: Model Base $5.70 (committed) must sit inside [floor 3.35, ceiling 8.20] Floor band source [34].
A24: Azure raw price surface (H100, region × tier) — mature-generation analog reference
A25: Region | B25: Tier | C25: $/GPU-hr
A26: australiaeast | B26: On-demand | C26: 17.82
A27: canadacentral | B27: On-demand | C27: 14.75
A28: centralus | B28: On-demand | C28: 15.12
A29: eastus | B29: On-demand | C29: 12.29
A30: eastus2 | B30: On-demand | C30: 12.29
A31: japaneast | B31: On-demand | C31: 17.82
A32: japanwest | B32: On-demand | C32: 19.05
A33: koreacentral | B33: On-demand | C33: 16.59
A34: northcentralus | B34: On-demand | C34: 14.75
A35: polandcentral | B35: On-demand | C35: 15.98
A36: southafricanorth | B36: On-demand | C36: 21.08
A37: southafricawest | B37: On-demand | C37: 23.33
... A145: westus3 | B145: Spot | C145: 2.27
A147: Source: Azure Retail Prices API (prices.azure.com/api/retail/prices), official Microsoft list pricing, no auth. Clickable link on the Sources tab. getDeploying neocloud summary retained for the realized tier.

Sheet Interconnection Queue
A1: US Interconnection Queue — LBNL, recent operational cohort (uploaded raw) | C1: =IF(Checks!$C$4>0,"MODEL IN ERROR","checks OK") -> checks OK
A2: 1297 operational US projects (online ≥2019) with a valid queue→online duration, from LBNL's 38,201-request dataset. US time-to-power (Bear/Base/Bull) is the LIVE median / p75 / p25 of the Duration column below. Source: US time-to-power [25]; dispersion transfer to non-US [46].
A3: Base = MEDIAN duration (yr) | C3: =MEDIAN(QueueTable[Duration (yr)]) -> 4.5 | E3: Dispersion transfer (US-observed IQR → applied to non-US medians):
A4: Bear = 75th pct (slower, yr) | C4: =PERCENTILE(QueueTable[Duration (yr)],0.75) -> 5.83 | E4: p75 / median (hi) | F4: =C4/C3 -> 1.2955556
A5: Bull = 25th pct (faster, yr) | C5: =PERCENTILE(QueueTable[Duration (yr)],0.25) -> 3.17 | E5: p25 / median (lo) | F5: =C5/C3 -> 0.70444444
A6: q_id | B6: State | C6: Type | D6: Queue yr | E6: Online yr | F6: Duration (yr)
A7: 1010 | B7: CA | C7: Wind | D7: 2014.2 | E7: 2022.2 | F7: 8
A8: 1016 | B8: CA | C8: Gas | D8: 2014.2 | E8: 2019.2 | F8: 5
A9: 1027 | B9: CA | C9: Battery | D9: 2014.2 | E9: 2023.7 | F9: 9.42
A10: 1036 | B10: CA | C10: Solar | D10: 2014.2 | E10: 2020.8 | F10: 6.58
A11: 1053 | B11: AZ | C11: Solar | D11: 2014.2 | E11: 2019.8 | F11: 5.5
A12: 1097 | B12: CA | C12: Battery | D12: 2015.2 | E12: 2024.5 | F12: 9.25
A13: 1103 | B13: CA | C13: Solar | D13: 2015.2 | E13: 2021.1 | F13: 5.83
A14: 1109 | B14: CA | C14: Battery | D14: 2015.2 | E14: 2023.6 | F14: 8.33
A15: 1111 | B15: CA | C15: Battery | D15: 2015.2 | E15: 2022.2 | F15: 6.92
A16: 1117 | B16: CA | C16: Solar | D16: 2015.2 | E16: 2021.9 | F16: 6.67
A17: 1136 | B17: CA | C17: Solar | D17: 2015.2 | E17: 2023.7 | F17: 8.42
A18: 1170 | B18: CA | C18: Battery | D18: 2015.2 | E18: 2025.2 | F18: 10
... A1210: 26INR0694 | B1210: TX | C1210: Oil | D1210: 2025.4 | E1210: 2025.8 | F1210: 0.42
A1211: 22INR0468 | C1211: Battery | D1211: 2021.1 | E1211: 2025.6 | F1211: 4.5
A1212: 22INR0540 | C1212: Battery | D1212: 2021.5 | E1212: 2025.8 | F1212: 4.25
A1213: 23INR0007 | C1213: Solar+Battery | D1213: 2019.9 | E1213: 2025.6 | F1213: 5.67
A1214: 23INR0287 | C1214: Battery | D1214: 2021.3 | E1214: 2025.7 | F1214: 4.33
A1215: 23INR0619 | C1215: Battery | D1215: 2023.4 | E1215: 2025.2 | F1215: 1.75
A1216: 24INR0460 | C1216: Battery | D1216: 2023 | E1216: 2025.7 | F1216: 2.67
A1217: 24INR0596 | C1217: Battery | D1217: 2023.4 | E1217: 2025.6 | F1217: 2.17
A1218: 25INR0223 | C1218: Gas | D1218: 2022.7 | E1218: 2025.6 | F1218: 2.92
A1219: 25INR0467 | C1219: Battery | D1219: 2023.4 | E1219: 2025.6 | F1219: 2.17
A1220: 25INR0777 | C1220: Other | D1220: 2025.4 | E1220: 2025.8 | F1220: 0.33
A1221: 26INR0666 | C1221: Other | D1221: 2025.4 | E1221: 2025.7 | F1221: 0.25
A1222: 26INR0674 | C1222: Other | D1222: 2025.4 | E1222: 2025.7 | F1222: 0.25
... A1241: 373 | C1241: Battery | D1241: 2019.8 | E1241: 2020.5 | F1241: 0.75
A1242: 505 | B1242: NY | C1242: Wind | D1242: 2015.4 | E1242: 2023.8 | F1242: 8.33
A1243: IC-237 | C1243: Nuclear | D1243: 2010.2 | E1243: 2024.2 | F1243: 14.08
A1244: 1 | C1244: Solar | D1244: 2016.6 | E1244: 2020.1 | F1244: 3.5
A1245: 61 | C1245: Battery | D1245: 2019.6 | E1245: 2021.9 | F1245: 2.33
A1246: 77 | C1246: Solar | D1246: 2021.4 | E1246: 2022.9 | F1246: 1.5
A1247: 10230 | C1247: Gas | D1247: 2017.2 | E1247: 2020.9 | F1247: 3.75
A1248: 17116 | C1248: Solar | D1248: 2016.8 | E1248: 2020.9 | F1248: 4.08
A1249: 9409 | C1249: Solar | D1249: 2016.8 | E1249: 2020.8 | F1249: 4
A1250: 158 | C1250: Gas | D1250: 2014.5 | E1250: 2019.4 | F1250: 4.92
A1251: 162 | C1251: Gas | D1251: 2015.1 | E1251: 2019.4 | F1251: 4.33
A1252: 181 | C1252: Solar | D1252: 2016.2 | E1252: 2019 | F1252: 2.75
A1253: 182 | C1253: Solar | D1253: 2016.2 | E1253: 2019 | F1253: 2.75
A1254: 194 | C1254: Solar | D1254: 2016.4 | E1254: 2019 | F1254: 2.58
... A1266: Q07c | C1266: Solar | D1266: 2017.4 | E1266: 2022.9 | F1266: 5.5
A1267: 1120 | B1267: CA | C1267: Solar+Battery | D1267: 2015.2 | E1267: 2023.9 | F1267: 8.67
A1268: 1139 | B1268: CA | C1268: Solar+Battery | D1268: 2015.2 | E1268: 2023.9 | F1268: 8.67
A1269: 1158 | B1269: CA | C1269: Solar+Battery | D1269: 2015.2 | E1269: 2022.2 | F1269: 6.92
A1270: 1171 | B1270: AZ | C1270: Solar+Battery | D1270: 2015.2 | E1270: 2025.2 | F1270: 10
A1271: 1196 | B1271: CA | C1271: Solar+Battery | D1271: 2015.2 | E1271: 2023.8 | F1271: 8.5
A1272: 1198 | B1272: CA | C1272: Solar+Battery | D1272: 2015.2 | E1272: 2024.9 | F1272: 9.67
A1273: 1200 | B1273: CA | C1273: Solar+Battery | D1273: 2015.2 | E1273: 2024.2 | F1273: 8.92
A1274: 1211 | B1274: CA | C1274: Solar+Battery | D1274: 2015.2 | E1274: 2025.6 | F1274: 10.33
A1275: 1215 | B1275: CA | C1275: Solar+Battery | D1275: 2015.2 | E1275: 2025.3 | F1275: 10.08
A1276: 1244 | B1276: CA | C1276: Solar+Battery | D1276: 2016.3 | E1276: 2024.4 | F1276: 8.08
A1277: 1291 | B1277: AZ | C1277: Solar+Battery | D1277: 2016.3 | E1277: 2024 | F1277: 7.67
A1278: 1302 | B1278: CA | C1278: Solar+Battery | D1278: 2016.3 | E1278: 2024.2 | F1278: 7.92
... A1303: Q15 | B1303: AZ | C1303: Solar+Battery | D1303: 2010.5 | E1303: 2019.9 | F1303: 9.42

Sheet Power Build-up
A1: Delivered Power Build-up — wholesale + delivery split, validated vs observed industrial all-in ($/MWh) | C1: =IF(Checks!$C$4>0,"MODEL IN ERROR","checks OK") -> checks OK
A2: Delivered price (col E) = the Assumptions country-table Base, externally validated against an observed industrial all-in price (col G). Wholesale (col C) is sourced; the grid/T&D+firming line (col D) is now an ILLUSTRATIVE SPLIT (delivered − wholesale), not a claim. US = ERCOT basis; Norway = blended NO zones; Saudi = regulated tariff.
A3: REFERENCE TAB — reconciled to the Assumptions country table (delivered power) by Checks r24; not live-linked. Assumptions holds the authoritative hardcodes.
B4: Country | C4: Wholesale avg | D4: Grid/T&D + firming (illustrative split = delivered − wholesale) | E4: Delivered (build-up) | F4: Wholesale source | G4: Observed industrial all-in ($/MWh) | H4: Observed-price source | I4: Notes / basis
B5: Norway | C5: 40 | D5: =Assumptions!$D$50-C5 -> 12 | E5: =C5+D5 -> 52 | F5: [22] | G5: 55 | H5: [37] | I5: IEA Nordics H1-2025 ~$40/MWh (SSB/Nord Pool); delivered = wholesale + grid/T&D + firming
B6: United States | C6: 30 | D6: =Assumptions!$D$51-C6 -> 30 | E6: =C6+D6 -> 60 | F6: [22] | G6: 62 | H6: [37] | I6: IEA/EIA ERCOT 2025 ~$30/MWh; delivered $60 = ERCOT + ~$30 grid/T&D
B7: India | C7: 49 | D7: =Assumptions!$D$52-C7 -> 46 | E7: =C7+D7 -> 95 | F7: [23] | G7: 92 | H7: [37] | I7: IEX DAM 2025 ~₹4.2/kWh ≈ $49/MWh
B8: Ireland | C8: 95 | D8: =Assumptions!$D$53-C8 -> 55 | E8: =C8+D8 -> 150 | F8: [22] | G8: 155 | H8: [37] | I8: IEA EU H1-2025 ~$90/MWh; IE higher (SEMOpx)
B9: Saudi Arabia | C9: 48 | D9: =Assumptions!$D$54-C9 -> 0 | E9: =C9+D9 -> 48 | F9: [22] | G9: 50 | H9: [37] | I9: Regulated SEC/SERA industrial tariff ~$48/MWh
B11: Delivered (col E) ties to the Assumptions country table (Base) — arithmetic verified on Checks r24 — and is cross-checked against an independent observed industrial all-in price (col G, Checks r17). The wholesale/delivery split (cols C/D) is illustrative decomposition, not the source of the number.
A13: External validation — max |delivered − observed industrial all-in| ÷ observed (flag if > 20%): | C13: =MAX(ABS(E5-G5)/G5, ABS(E6-G6)/G6, ABS(E7-G7)/G7, ABS(E8-G8)/G8, ABS(E9-G9)/G9) -> 0.054545455 | D13: =--(C13>0.2) -> 0

Sheet WACC Build-up
A1: WACC Build-up (unlevered project hurdle rate) — USD risk-free + country-risk premium + project premium. This is an unlevered hurdle rate used as a WACC proxy; NOT a levered WACC (no debt cost, beta, ERP or capital structure). | C1: =IF(Checks!$C$4>0,"MODEL IN ERROR","checks OK") -> checks OK
A2: USD-nominal cost of capital decomposed. Risk-free = US 10-yr less US default spread (Damodaran method); CRP from Damodaran Jan-2026 (sourced); the project/asset premium is a disclosed judgment residual. Reconciles to the country table (Base).
A3: REFERENCE TAB — reconciled to the Assumptions country-table WACC by Checks r25; not live-linked. Assumptions holds the authoritative hardcodes.
B4: USD risk-free (linked from Assumptions input) | E4: =Risk_free -> 0.04236 | F4: Risk-free linked from Assumptions [21] (FRED DGS10). Project premium = disclosed judgment.
B5: Country | C5: Risk-free | D5: CRP (Damodaran) [20] | E5: Project premium (disclosed judgment) | F5: WACC (build-up) | G5: Source
B6: Norway | C6: =$E$4 -> 0.04236 | D6: 0 | E6: 0.021 | F6: =C6+D6+E6 -> 0.06336 | G6: [20][21]
B7: United States | C7: =$E$4 -> 0.04236 | D7: 0.0023 | E7: 0.0187 | F7: =C7+D7+E7 -> 0.06336 | G7: [20][21]
B8: India | C8: =$E$4 -> 0.04236 | D8: 0.0285 | E8: 0.0075 | F8: =C8+D8+E8 -> 0.07836 | G8: [20][21]
B9: Ireland | C9: =$E$4 -> 0.04236 | D9: 0.0078 | E9: 0.0182 | F9: =C9+D9+E9 -> 0.06836 | G9: [20][21]
B10: Saudi Arabia | C10: =$E$4 -> 0.04236 | D10: 0.0078 | E10: 0.0182 | F10: =C10+D10+E10 -> 0.06836 | G10: [20][21]
B12: WACC (col F) ties to the Assumptions country table (Base) — reconciliation verified on Checks. Risk-free & CRP are High-reliability (FRED / Damodaran); the project premium is a disclosed judgment residual (Low).
B13: India's project premium is smallest (0.75pp) — its frozen 8.0% WACC sits only modestly above the sourced rf+CRP floor of 7.25%.

Sheet Assumptions
A1: Assumptions | C1: =IF(Checks!$C$4>0,"MODEL IN ERROR","checks OK") -> checks OK
A2: Every input. The sourcing/build-up tabs before this one (GPU Specs, GPU Price Index, Power/WACC Build-ups) evidence the key drivers; those ties are verified on Checks. BLUE = input you may change; the Active column feeds the engine. Col K = Materiality (High = defend cold). Energy Security block (rows 79+) is a LABELLED IMPLICATION and does NOT feed the P&L.
A4: Scenario (all countries) | B4: Base
A5: Country (drill-down only) | B5: Norway
A6: Energy-source analysis | B6: → see EnergyDynamics tab
A7: Deal type (Contracted/Merchant) | B7: Contracted
A9: # | B9: Driver | C9: Units | D9: Bear | E9: Base | F9: Bull | G9: Active | H9: Source | I9: Comment
A10: 1 | B10: Facility build capex (ex-interconnect) | C10: $m/MW | D10: 24 | E10: 17 | F10: 13 | G10: =INDEX(D10:F10,MATCH($B$4,$D$9:$F$9,0)) -> 17 | H10: [1] | I10: -
A11: 2 | B11: GPU + IT capex (per single GPU) | C11: $/GPU | D11: 50000 | E11: 42000 | F11: 35000 | G11: =INDEX(D11:F11,MATCH($B$4,$D$9:$F$9,0)) -> 42000 | H11: [2] | I11: 'GPU'=one single B200 accelerator (~600/MW, ~$42k/GPU). Basis: DGX B200 ~$35–40k/GPU; HGX B200 ~$56k; bare card $40–50k; Base $42k = DGX-class + IT share.
A12: 3 | B12: GPUs per MW (single accelerator) | C12: #/MW | D12: 600 | E12: 600 | F12: 600 | G12: =INDEX(D12:F12,MATCH($B$4,$D$9:$F$9,0)) -> 600 | H12: [3] | I12: B200 1000W TDP; HGX 8-GPU node ~13.3kW at IT level (GPU+CPU+NVSwitch+networking) → 1 MW ÷ 1.667 kW/GPU ≈ 600 GPU/MW.
A13: 4 | B13: PUE (per usage effectiveness) | C13: % | D13: =INDEX($M$50:$M$54,MATCH($B$5,$B$50:$B$54,0)) -> 1.15 | E13: =INDEX($M$50:$M$54,MATCH($B$5,$B$50:$B$54,0)) -> 1.15 | F13: =INDEX($M$50:$M$54,MATCH($B$5,$B$50:$B$54,0)) -> 1.15 | G13: =INDEX(D13:F13,MATCH($B$4,$D$9:$F$9,0)) -> 1.15 | H13: [4] | I13: A measure of how efficiently GPU's consume energy, accounting for cooling, power conversion/distribtion losses, and overhead. Lower rate is more efficient. PUE = total facility electricity / IT electricity.
A14: 5 | B14: Compute price P0 (year-1, today) | C14: $/GPU-hr | D14: 4 | E14: 5.7 | F14: 9 | G14: =INDEX(D14:F14,MATCH($B$4,$D$9:$F$9,0)) -> 5.7 | H14: [5] | I14: P0 = year-1 realized committed rate (NOT a hold-average); ENTRY price = P0×(1−decline)^TTP, then erodes toward the floor. On-demand ≈ $6.85.
A15: 6 | B15: Paid occupancy (Deal type) | C15: % | D15: =$G$45 -> 0.88 | E15: =$G$45 -> 0.88 | F15: =$G$45 -> 0.88 | G15: =$G$45 -> 0.88 | H15: [6] | I15: -
A16: 7 | B16: GPU economic life | C16: yr | D16: 3 | E16: 5 | F16: 6 | G16: =INDEX(D16:F16,MATCH($B$4,$D$9:$F$9,0)) -> 5 | H16: [7] | I16: -
A17: 8 | B17: Fixed O&M (incl. water/staff) | C17: $m/MW/yr | D17: 0.9 | E17: 0.7 | F17: 0.5 | G17: =INDEX(D17:F17,MATCH($B$4,$D$9:$F$9,0)) -> 0.7 | H17: [33] | I17: -
A18: 9 | B18: Facility salvage (% of facility capex — PRE-TAX terminal proceeds on shell + live interconnection; no recapture/gain tax) | C18: % | D18: 0.4 | E18: 0.45 | F18: 0.55 | G18: =INDEX(D18:F18,MATCH($B$4,$D$9:$F$9,0)) -> 0.45 | H18: [31] | I18: 45% blended residual: durable powered shell + interconnection (30+yr, appreciating) holds most value; cooling/fit-out depreciates faster. Modelled as PRE-TAX proceeds (no recapture/gain tax on shell); GPU salvage is after-tax — see Limitations.
A19: 10 | B19: GPU salvage (% of GPU capex, recovered at exit — spent accelerators) | C19: % | D19: 0.1 | E19: 0.1 | F19: 0.1 | G19: =INDEX(D19:F19,MATCH($B$4,$D$9:$F$9,0)) -> 0.1 | H19: [31] | I19: 10% GPU residual at 5-yr exit — conservative. Accelerators cascade (frontier yr1–2 → inference yr3–4 → batch yr5–6): ~50–60% at 3yr, collapsing to ~10% by yr5.
A20: 11 | B20: Operating hold (yr = GPU life, single flip) | C20: yr | D20: =$G$16 -> 5 | E20: =$G$16 -> 5 | F20: =$G$16 -> 5 | G20: =$G$16 -> 5 | H20: - | I20: Derived from GPU economic life; energization/GPU install period.
A21: 12 | B21: IT load | C21: MW | D21: 100 | E21: 100 | F21: 100 | G21: =INDEX(D21:F21,MATCH($B$4,$D$9:$F$9,0)) -> 100 | H21: - | I21: Design choice
A22: 13 | B22: Delivered power | C22: $/MWh | D22: =INDEX($C$50:$C$54,MATCH($B$5,$B$50:$B$54,0)) -> 80 | E22: =INDEX($D$50:$D$54,MATCH($B$5,$B$50:$B$54,0)) -> 52 | F22: =INDEX($E$50:$E$54,MATCH($B$5,$B$50:$B$54,0)) -> 30 | G22: =INDEX(D22:F22,MATCH($B$4,$D$9:$F$9,0)) -> 52 | H22: [22][23][37] | I22: source and confidence documented in "Calculations"
A23: 14 | B23: Time-to-power | C23: yr | D23: =INDEX($F$50:$F$54,MATCH($B$5,$B$50:$B$54,0)) -> 2.5911111 | E23: =INDEX($G$50:$G$54,MATCH($B$5,$B$50:$B$54,0)) -> 2 | F23: =INDEX($H$50:$H$54,MATCH($B$5,$B$50:$B$54,0)) -> 1.4088889 | G23: =INDEX(D23:F23,MATCH($B$4,$D$9:$F$9,0)) -> 2 | H23: [24][25][26][27][28][46] | I23: source and confidence documented in "Calculations"
A24: 15 | B24: Cost of capital — unlevered project hurdle rate (rf + country-risk premium; a WACC proxy, not a levered WACC) | C24: % | D24: =INDEX($I$50:$I$54,MATCH($B$5,$B$50:$B$54,0)) -> 0.0784 | E24: =INDEX($J$50:$J$54,MATCH($B$5,$B$50:$B$54,0)) -> 0.0634 | F24: =INDEX($K$50:$K$54,MATCH($B$5,$B$50:$B$54,0)) -> 0.0584 | G24: =INDEX(D24:F24,MATCH($B$4,$D$9:$F$9,0))+$G$46 -> 0.0634 | H24: [20][21] | I24: source and confidence documented in "Calculations"
I25: -
A26: 17 | B26: Corporate tax rate | C26: % | D26: =INDEX($L$50:$L$54,MATCH($B$5,$B$50:$B$54,0)) -> 0.22 | E26: =INDEX($L$50:$L$54,MATCH($B$5,$B$50:$B$54,0)) -> 0.22 | F26: =INDEX($L$50:$L$54,MATCH($B$5,$B$50:$B$54,0)) -> 0.22 | G26: =INDEX(D26:F26,MATCH($B$4,$D$9:$F$9,0)) -> 0.22 | H26: [29] | I26: source and confidence documented in "Calculations"
A27: Secondary assumptions — Low materiality (standard conventions; single value each) | I27: -
B28: Hours per year | C28: h | F28: 8760 | H28: - | I28: 8760 h/yr
B29: Unit scale ($ per $m) | C29: $ | F29: 1000000 | H29: - | I29: $1m = 1,000,000
B30: Insurance rate (x GPU capex) | C30: % | F30: 0.004 | H30: [43] | I30: 0.4% of GPU capex (Hotaling/Lockton operating insurance).
B31: Property tax abatement ((1-abate) applied) | C31: % | F31: 0.5 | H31: [29] | I31: -
B32: Ramp yr-1 occupancy (% of steady) | C32: % | F32: 0.65 | H32: [32] | I32: -
B33: Ramp yr-2 occupancy (% of steady) | C33: % | F33: 0.85 | H33: [32] | I33: -
B34: Facility life (sense-check only) | C34: yr | F34: 15 | H34: - | I34: deprec uses shell/fit-out below
B35: Shell fraction of facility capex | C35: % | F35: 0.45 | H35: [43] | I35: -
B36: Shell / building life | C36: yr | F36: 25 | H36: [43] | I36: -
B37: AI fit-out life (cooling/MEP) | C37: yr | F37: 12 | H37: [43] | I37: -
B38: Idle-shell holding cost (%/yr facility capex, wait) | C38: % | F38: 0.015 | H38: [14] | I38: -
B39: USD risk-free rate (10-yr Treasury; feeds WACC) | C39: % | F39: 0.04236 | H39: [21] | I39: US 10-yr 4.466% 90-day avg (FRED DGS10) − US default 0.23% (Damodaran) = USD risk-free.
B40: Shadow carbon price (context lens; not in P&L) | C40: $/tCO₂ | F40: 190 | H40: [47] | I40: US EPA 2023 social cost of carbon ≈ $190/t (2020$, ~2% near-term); EU ETS ≈ $80/t alternative. Editable. Context lens only — priced in the Comparison carbon-adjusted view, excluded from the core NPV.
A44: Deal structure — Contracted vs Merchant | C44: Contracted | D44: Merchant | G44: Active | I44: Contracted=anchor offtake (low WACC, high occ); Merchant=speculative (WACC premium, lower occ).
B45: Paid occupancy | C45: 0.88 | D45: 0.7 | G45: =INDEX(C45:D45,MATCH($B$7,$C$44:$D$44,0)) -> 0.88 | H45: [6] | I45: -
B46: WACC premium (pp) | C46: 0 | D46: 0.045 | G46: =INDEX(C46:D46,MATCH($B$7,$C$44:$D$44,0)) -> 0 | H46: [13] | I46: Merchant premium +4.5pp (Merchant deal only; Contracted = 0). Equity ~12–15% merchant vs ~7–9% contracted; debt +125–250bps; +4.5pp sits inside the observed gap.
A48: Country data — varying levers (Bear/Base/Bull). KEY: delivered power · time-to-power · WACC.
B49: Country | C49: Pow Bear | D49: Pow Base | E49: Pow Bull | F49: TTP Bear | G49: TTP Base | H49: TTP Bull | I49: WACC Bear | J49: WACC Base | K49: WACC Bull | L49: Tax | M49: PUE | N49: Interconn $m/MW | O49: PropTax %capex/yr | P49: Grid carbon (gCO2/kWh)
B50: Norway | C50: 80 | D50: 52 | E50: 30 | F50: =G50*TTP_disp_hi -> 2.5911111 | G50: 2 | H50: =G50*TTP_disp_lo -> 1.4088889 | I50: 0.0784 | J50: 0.0634 | K50: 0.0584 | L50: 0.22 | M50: 1.15 | N50: 0.4 | O50: 0.003 | P50: 28
B51: United States | C51: 130 | D51: 60 | E51: 45 | F51: ='Interconnection Queue'!$C$4 -> 5.83 | G51: ='Interconnection Queue'!$C$3 -> 4.5 | H51: ='Interconnection Queue'!$C$5 -> 3.17 | I51: 0.0784 | J51: 0.0634 | K51: 0.0584 | L51: 0.21 | M51: 1.3 | N51: 0.6 | O51: 0.01 | P51: 384
B52: India | C52: 120 | D52: 95 | E52: 70 | F52: =G52*TTP_disp_hi -> 3.8866667 | G52: 3 | H52: =G52*TTP_disp_lo -> 2.1133333 | I52: 0.1084 | J52: 0.0784 | K52: 0.0684 | L52: 0.25 | M52: 1.5 | N52: 0.5 | O52: 0.005 | P52: 670
B53: Ireland | C53: 180 | D53: 150 | E53: 130 | F53: =G53*TTP_disp_hi -> 7.7733333 | G53: 6 | H53: =G53*TTP_disp_lo -> 4.2266667 | I53: 0.0834 | J53: 0.0684 | K53: 0.0634 | L53: 0.125 | M53: 1.2 | N53: 0.8 | O53: 0.001 | P53: 290
B54: Saudi Arabia | C54: 65 | D54: 48 | E54: 30 | F54: =G54*TTP_disp_hi -> 2.5911111 | G54: 2 | H54: =G54*TTP_disp_lo -> 1.4088889 | I54: 0.0884 | J54: 0.0684 | K54: 0.0584 | L54: 0.2 | M54: 1.45 | N54: 0.3 | O54: 0.0005 | P54: 590
A55: Source key → | B55: [8]–[12] | C55: [22][23][37] | D55: [22][23][37] | E55: [22][23][37] | F55: [24][25][26][27][28][46] | G55: [24][25][26][27][28][46] | H55: [24][25][26][27][28][46] | I55: [20][21] | J55: [20][21] | K55: [20][21] | L55: [29] | M55: [4] | N55: [8][9][10][11][12] | O55: [29] | P55: [38]
A56: Lists — data-validation sources (named ranges)
A57: Note — Time-to-power: for Norway/India/Ireland/Saudi the MEDIAN (Base, col G) is the editable register-sourced input; the Bear/Bull band is DERIVED = median × US-LBNL observed IQR (TTP_disp_hi/lo on the Interconnection Queue tab), so dispersion is consistent across all five. US is fully linked to the LBNL queue (median/p75/p25). Assumes connection-time dispersion is broadly grid-invariant; Ireland’s upper tail is likely fatter (CRU policy).
A58: List_ReviewStatus | B58: Pass
B59: Concern
B60: Fail
A62: List_Scenario | B62: range Assumptions!D9:F9 (single source; drives scenario MATCH)
A63: List_Country | B63: range Assumptions!B50:B54 (single source)
A64: Compute-price dynamics — erosion path (P0 row 14 = year-1/today; entry = P0*(1-decline)^TTP; Contracted locks entry, Merchant keeps eroding to the floor)
B65: Compute price annual decline | C65: % | D65: 0.3 | E65: 0.2 | F65: 0.15 | G65: =INDEX(D65:F65,MATCH($B$4,$D$9:$F$9,0)) -> 0.2 | H65: [30] | I65: Annual decline of realized $/GPU-hr: Bear −30% (glut) / Base −20% / Bull −15%.
B66: Compute price floor ($/GPU-hr) | C66: $ | D66: 1.7 | E66: 2.5 | F66: 2.5 | G66: =INDEX(D66:F66,MATCH($B$4,$D$9:$F$9,0)) -> 2.5 | H66: [34][35][36] | I66: Full-cost floor = low-cost producer break-even (Norway/Saudi, NPV=0), see Price Floor tab. Base $2.50 sits inside the observed B200 committed-floor band $2.50–3.00; Bear $1.70 = crash/glut analog (H100 trough).
B67: B200 observed committed-floor band — low (Silicon Data SDB200RT) | D67: 2.5 | H67: [34] | I67: - | J67: -
B68: B200 observed committed-floor band — high (Silicon Data SDB200RT) | D68: 3 | E68: 3 | F68: 3 | G68: 3 | H68: [34] | I68: - | J68: -
B69: Floor reconciliation tolerance ($/GPU-hr) | D69: 0.1 | E69: 0.1 | F69: 0.1 | G69: 0.1 | H69: - | I69: Tolerance for the Price Floor internal-consistency check (|Base floor − model break-even|). Was a hardcoded 0.1 literal; promoted to a named range.
A70: Scope disclosures (mirror of Cover) — descriptive only, feeds no calculation:
A71: (1) Revenue is country-invariant: the compute price is applied identically across all five countries — no data-residency, sovereignty, latency, or local-demand price premia (defensible: compute is globally traded).
A72: (2) All figures are USD-nominal: revenue, power, capex, opex and salvage in USD; WACC is USD-nominal (Damodaran country-risk); no local-currency inflation is modeled.
A73: (3) FX risk is out of scope: India and Norway cash flows are treated in USD with no currency translation or hedging cost, though a real deployment would carry FX exposure on local power, tax and O&M.
A74: Power-regime thresholds — Revenue Mix 'Power Regime' block only (presentation; feeds no P&L):
B76: Share of revenue where Power is "material" | C76: 0.1 | D76: analyst-derived presentation threshold
B77: Share of revenue where Power is "heavy" | C77: 0.2 | D77: analyst-derived presentation threshold
A79: Energy Security inputs — WEC World Energy Trilemma Index (Energy Security dimension). Electricity mix (Ember 2024) drives diversity + firm share; self-sufficiency (IEA) = import independence. Sources: generation mix [41]; self-sufficiency [42]; WEC framework [40].
B80: Country | C80: Hydro % | D80: Wind % | E80: Solar % | F80: Nuclear % | G80: Coal % | H80: Gas % | I80: Oil % | J80: Bio/other % | K80: Self-suff % (IEA)
B81: Norway | C81: 88 | D81: 10 | E81: 0 | F81: 0 | G81: 0 | H81: 2 | I81: 0 | J81: 0 | K81: 100
B82: United States | C82: 6 | D82: 10 | E82: 5 | F82: 18 | G82: 15 | H82: 43 | I82: 0 | J82: 3 | K82: 100
B83: India | C83: 9 | D83: 6 | E83: 9 | F83: 3 | G83: 68 | H83: 3 | I83: 0 | J83: 2 | K83: 60
B84: Ireland | C84: 3 | D84: 33 | E84: 4 | F84: 0 | G84: 6 | H84: 41 | I84: 0 | J84: 13 | K84: 21
B85: Saudi Arabia | C85: 0 | D85: 0 | E85: 2 | F85: 0 | G85: 0 | H85: 63 | I85: 35 | J85: 0 | K85: 100
B86: Source key → | C86: [41] | D86: [41] | E86: [41] | F86: [41] | G86: [41] | H86: [41] | I86: [41] | J86: [41] | K86: [42]

Sheet ▸ CALCULATIONS
A1: ▸ CALCULATIONS

Sheet Capex Stack
A1: Capex Stack — per MW build-up ($m/MW, active country) | C1: =IF(Checks!$C$4>0,"MODEL IN ERROR","checks OK") -> checks OK
A2: Total capex/MW decomposed into sourced layers. In-rack networking (NVLink/switching) is carried inside the rack-allocated GPU+IT figure (SemiAnalysis). Reconciles to the Unit Economics per-MW Base total.
B4: Layer | C4: $m/MW | D4: Basis / source | E4: Notes / basis
B5: Shell / building (45% of facility, Base) | C5: =Assumptions!$F$35*Assumptions!$E$10 -> 7.65 | D5: [1] | E5: Shell/building 45% of facility; life 25yr (McKinsey/dgtlinfra)
B6: Fit-out — cooling/MEP (55% of facility, Base) | C6: =(1-Assumptions!$F$35)*Assumptions!$E$10 -> 9.35 | D6: [1] | E6: Fit-out cooling/MEP 55% of facility; life 12yr (liquid-cooled AI)
B7: GPU + in-rack IT/networking (per MW) | C7: =Assumptions!$G$12*Assumptions!$E$11/Unit_scale -> 25.2 | D7: [2] | E7: SemiAnalysis Blackwell B200 server BOM ($42k/GPU × 600/MW)
B8: Interconnection (active country) | C8: =INDEX(Assumptions!$N$50:$N$54,MATCH(Assumptions!$B$5,Assumptions!$B$50:$B$54,0)) -> 0.4 | D8: [8][9][10][11][12] | E8: Country cards — per-country interconnection ($m/MW)
B9: Total capex per MW (stack) | C9: =SUM(C5:C8) -> 42.6
B10: Unit Economics Base capex/MW | C10: ='Unit Economics'!$C$15 -> 42.6
B11: Reconciliation gap (must be 0) | C11: =C9-C10 -> 0

Sheet Unit Economics
A1: Unit Economics — one megawatt of IT load (bottom-up build block) | C1: =IF(Checks!$C$4>0,"MODEL IN ERROR","checks OK") -> checks OK
A2: The atomic build unit. Everything scales linearly from here: totals = per-MW × IT load. Blue = linked from Assumptions; black = calculated. Rows 14–15 are tied to independent benchmarks (external anchor).
B3: Item | C3: Value | D3: Low | E3: High | F3: Units | G3: Note | H3: Source
B4: GPUs per MW (active) | C4: =Assumptions!$G$12 -> 600 | F4: #/MW | G4: NVIDIA B200 / HGX B200 datasheet | H4: [3][17]
B5: GPU + IT capex per GPU (active) | C5: =Assumptions!$G$11 -> 42000 | F5: $/GPU | G5: SemiAnalysis rack-allocated | H5: [2]
B6: Compute price (active) | C6: =Assumptions!$G$14 -> 5.7 | F6: $/GPU-hr | G6: Triangulated | H6: [5]
B7: Paid occupancy (deal) | C7: =Paid_occupancy -> 0.88 | F7: % | G7: Deal structure
B8: Facility capex per MW (active, ex-interconnect) | C8: =Facility_capex_MW -> 17 | F8: $m/MW | G8: AI liquid-cooled 2026 | H8: [1]
B9: Interconnection per MW (active country) | C9: =INDEX(Assumptions!$N$50:$N$54,MATCH(Assumptions!$B$5,Assumptions!$B$50:$B$54,0)) -> 0.4 | F9: $m/MW | G9: Country cards | H9: [8][9][10][11][12]
B10: — GPU capex per MW (active) | C10: =C4*C5/Unit_scale -> 25.2 | F10: $m/MW | G10: GPUs/MW × $/GPU
B11: — Revenue per MW/yr (active) | C11: =C4*C6*Hours_per_year*C7/Unit_scale -> 26.364096 | F11: $m/MW/yr | G11: GPUs/MW × price × hrs × occ
B12: Total capex per MW (active) — rolls up to totals | C12: =C8+C9+C10 -> 42.6 | F12: $m/MW | G12: facility + interconnect + GPU (per MW)
B14: External anchor — BASE case tied to independent benchmarks (toggle-invariant) | F14: (errors only if Base leaves the sourced band — scenarios legitimately flex outside it)
B15: Base total capex per MW | C15: =Assumptions!$E$10+C9+Assumptions!$G$12*Assumptions!$E$11/Unit_scale -> 42.6 | D15: 30 | E15: 50 | F15: $m/MW | G15: ANCHOR: independent DC all-in capex $30–50m/MW (SemiAnalysis Blackwell BOM / CBRE build cost) | H15: [15]
B16: Base revenue per MW/yr | C16: =Assumptions!$G$12*Assumptions!$E$14*Hours_per_year*Paid_occupancy/Unit_scale -> 26.364096 | D16: 15 | E16: 40 | F16: $m/MW/yr | G16: ANCHOR: hyperscale colo revenue $15–40m/MW/yr (SemiAnalysis rental index × density) | H16: [16]
B18: Roll-up reconciliation (active per-MW × IT load must tie to Calculations)
B19: Total capex per MW (active) × IT load | C19: =C12*IT_load_MW -> 4260
B20: Calculations facility + GPU capex | C20: =Calculations!$C$7+Calculations!$C$6 -> 4260
B21: Reconciliation gap (must be 0) | C21: =C19-C20 -> 0

Sheet Buildout Schedule
A1: Buildout Schedule — facility-capex draw & reconciliation | C1: =IF(Checks!$C$4>0,"MODEL IN ERROR","checks OK") -> checks OK
A2: Facility capex is drawn evenly across the pre-power build (periods 0..S−1); GPUs are bought in full at energisation. The former 4-phase display was removed (Aug 2026): it did not feed the DCF and could be misread as a rival schedule. DCF timing comes from the draw schedule below; the reconciliation (H3) ties the DCF’s realised facility-capex line to the capex driver.
E3: Reconciliation gap (must be 0): | H3: =ABS(SUM(Calculations!D48:W48)+Calculations!C7)+C18 -> 0
A13: Facility-capex DRAW schedule — active country: this is the TIMING the Calculations timeline reads (row 16). Facility capex is disbursed evenly across the build (periods 0..S−1), not all at t=0; GPU capex lands at ops-start.
A14: Ops start S (active, = ROUND(TTP)) | C14: =ROUND(Assumptions!$G$23,0) -> 2
A15: Period | D15: 0 | E15: 1 | F15: 2 | G15: 3 | H15: 4 | I15: 5 | J15: 6 | K15: 7 | L15: 8 | M15: 9 | N15: 10 | O15: 11 | P15: 12 | Q15: 13 | R15: 14 | S15: 15 | T15: 16 | U15: 17 | V15: 18 | W15: 19
A16: Draw weight (feeds Calculations!row48) | D16: =IF($C$14=0,--(D15=0),--(D15<=$C$14-1)/$C$14) -> 0.5 | E16: =IF($C$14=0,--(E15=0),--(E15<=$C$14-1)/$C$14) -> 0.5 | F16: =IF($C$14=0,--(F15=0),--(F15<=$C$14-1)/$C$14) -> 0 | G16: =IF($C$14=0,--(G15=0),--(G15<=$C$14-1)/$C$14) -> 0 | H16: =IF($C$14=0,--(H15=0),--(H15<=$C$14-1)/$C$14) -> 0 | I16: =IF($C$14=0,--(I15=0),--(I15<=$C$14-1)/$C$14) -> 0 | J16: =IF($C$14=0,--(J15=0),--(J15<=$C$14-1)/$C$14) -> 0 | K16: =IF($C$14=0,--(K15=0),--(K15<=$C$14-1)/$C$14) -> 0 | ... W16: =IF($C$14=0,--(W15=0),--(W15<=$C$14-1)/$C$14) -> 0
A17: Draw ($m) | D17: =D16*$C$19 -> 870 | E17: =E16*$C$19 -> 870 | F17: =F16*$C$19 -> 0 | G17: =G16*$C$19 -> 0 | H17: =H16*$C$19 -> 0 | I17: =I16*$C$19 -> 0 | J17: =J16*$C$19 -> 0 | K17: =K16*$C$19 -> 0 | ... W17: =W16*$C$19 -> 0
A18: Draw schedule reconciles (weights sum to 1, $m sum to facility) — must be 0 | C18: =ABS(SUM(D16:W16)-1)+ABS(SUM(D17:W17)-C19) -> 0
A19: Facility capex total ($m) | C19: =('Unit Economics'!$C$8+'Unit Economics'!$C$9)*IT_load_MW -> 1740
A21: Assumption — facility draw profile: capex is spread EVENLY across the pre-power build (periods 0..S−1), GPUs purchased in full at energisation (ops-start). Modelling convention, not a separately toggled input.
A22: Assumption — ops-start uses integer periods: S = ROUND(time-to-power). Fractional-year queues round to the nearest annual period (e.g., 4.5 yr → period 5). Annual granularity is a deliberate simplification.

Sheet Calculations
A1: ="Calculations — "&Assumptions!$B$5&" ("&Assumptions!$B$4&")" -> Calculations — Norway (Base) | C1: =IF(Checks!$C$4>0,"MODEL IN ERROR","checks OK") -> checks OK
A2: Single-country DCF for the selected country/scenario: annual feeders, then the per-period cash-flow statement, then outputs. Blue = value linked in from Assumptions; black = calculated here. All $m.
A4: Single-country aggregates (annual, active country/scenario) — feed the statement below
A5: Number of GPUs | B5: # | C5: =IT_load_MW*Assumptions!$G$12 -> 60000
A6: GPU capex | B6: $m | C6: =C5*Assumptions!$G$11/Unit_scale -> 2520
A7: Facility capex (incl. interconnect) | B7: $m | C7: =IT_load_MW*Facility_capex_MW+IT_load_MW*INDEX(Assumptions!$N$50:$N$54,MATCH(Assumptions!$B$5,Assumptions!$B$50:$B$54,0)) -> 1740
A8: Total power draw | B8: MW | C8: =IT_load_MW*Assumptions!$G$13 -> 115
A9: Annual revenue | B9: $m | C9: =C5*Assumptions!$G$14*Hours_per_year*Paid_occupancy/Unit_scale -> 2636.4096
A10: Annual power cost | B10: $m | C10: =C8*Hours_per_year*Assumptions!$G$22*Paid_occupancy/Unit_scale -> 46.098624
A11: Insurance ($m/yr) | B11: $m | C11: =Insurance_rate*C6 -> 10.08
A12: Property tax ($m/yr) | B12: $m | C12: =INDEX(Assumptions!$O$50:$O$54,MATCH(Assumptions!$B$5,Assumptions!$B$50:$B$54,0))*(C7+C6)*(1-Prop_tax_abatement) -> 6.39
A13: Annual opex (O&M+ins+proptax) | B13: $m | C13: =IT_load_MW*OM_fixed+C11+C12 -> 86.47
A14: Annual EBITDA | B14: $m | C14: =C9-C10-C13 -> 2503.841
A15: Facility deprec rate (blended shell/fit-out) | B15: x | C15: =Assumptions!$F$35/Assumptions!$F$36+(1-Assumptions!$F$35)/Assumptions!$F$37 -> 0.063833333
A16: Annual depreciation | B16: $m | C16: =C6/GPU_life+C7*C15 -> 615.07
A17: After-tax annual op. CF (steady) | B17: $m | C17: =C14-Assumptions!$G$26*MAX(C14-C16,0) -> 2088.3114
A18: Occupancy-linked after-tax margin | B18: $m | C18: =(C9-C10)*(1-Assumptions!$G$26) -> 2020.4426
A19: Terminal value (reference) | B19: $m | C19: =C7*Facility_salvage_pct+C6*GPU_salvage_pct -> 1035
A20: Ops start period | B20: yr | C20: =ROUND(Assumptions!$G$23,0) -> 2
A21: Discount base v = 1/(1+WACC) | B21: x | C21: =1/(1+Assumptions!$G$24) -> 0.94037991
A22: Ramp PV haircut | B22: $m | C22: =C18*((1-Ramp_yr1)*C21^(C20)+(1-Ramp_yr2)*C21^(C20+1)) -> 877.37467
A23: Revenue per unit util | B23: $m | C23: =C5*Assumptions!$G$14*Hours_per_year/Unit_scale -> 2995.92
A24: Power per unit util | B24: $m | C24: =C8*Hours_per_year*Assumptions!$G$22/Unit_scale -> 52.3848
A26: Phased facility capex: even draw over the build (periods 0..S−1); GPU capex at ops-start. Both feed the statement below (see Buildout Schedule).
A34: Per-period cash-flow statement (periods 0–19). Revenue uses the per-period compute-price path: entry = P0·(1−decline)^TTP, then Contracted holds it flat while Merchant keeps eroding to the floor.
A35: Line item | B35: Units | D35: 0 | E35: 1 | F35: 2 | G35: 3 | H35: 4 | I35: 5 | J35: 6 | K35: 7 | L35: 8 | M35: 9 | N35: 10 | O35: 11 | P35: 12 | Q35: 13 | R35: 14 | S35: 15 | T35: 16 | U35: 17 | V35: 18 | W35: 19 | X35: Check
A36: Period counter | B36: # | D36: 0 | E36: =D36+1 -> 1 | F36: =E36+1 -> 2 | G36: =F36+1 -> 3 | H36: =G36+1 -> 4 | I36: =H36+1 -> 5 | J36: =I36+1 -> 6 | K36: =J36+1 -> 7 | L36: =K36+1 -> 8 | ... W36: =V36+1 -> 19
A37: Operating year? (1 = in ops) | B37: flag | D37: =--(D56>0) -> 0 | E37: =--(E56>0) -> 0 | F37: =--(F56>0) -> 1 | G37: =--(G56>0) -> 1 | H37: =--(H56>0) -> 1 | I37: =--(I56>0) -> 1 | J37: =--(J56>0) -> 1 | K37: =--(K56>0) -> 0 | ... W37: =--(W56>0) -> 0 | X37: =--(SUM(D37:W37)<>GPU_life) -> 0
A38: Occupancy factor (lease-up ramp) | B38: x | D38: =D37*(1-(1-Ramp_yr1)*((D36-$C$20-MAX(D56-1,0)*GPU_life)=0)-(1-Ramp_yr2)*((D36-$C$20-MAX(D56-1,0)*GPU_life)=1)) -> 0 | E38: =E37*(1-(1-Ramp_yr1)*((E36-$C$20-MAX(E56-1,0)*GPU_life)=0)-(1-Ramp_yr2)*((E36-$C$20-MAX(E56-1,0)*GPU_life)=1)) -> 0 | F38: =F37*(1-(1-Ramp_yr1)*((F36-$C$20-MAX(F56-1,0)*GPU_life)=0)-(1-Ramp_yr2)*((F36-$C$20-MAX(F56-1,0)*GPU_life)=1)) -> 0.65 | G38: =G37*(1-(1-Ramp_yr1)*((G36-$C$20-MAX(G56-1,0)*GPU_life)=0)-(1-Ramp_yr2)*((G36-$C$20-MAX(G56-1,0)*GPU_life)=1)) -> 0.85 | H38: =H37*(1-(1-Ramp_yr1)*((H36-$C$20-MAX(H56-1,0)*GPU_life)=0)-(1-Ramp_yr2)*((H36-$C$20-MAX(H56-1,0)*GPU_life)=1)) -> 1 | I38: =I37*(1-(1-Ramp_yr1)*((I36-$C$20-MAX(I56-1,0)*GPU_life)=0)-(1-Ramp_yr2)*((I36-$C$20-MAX(I56-1,0)*GPU_life)=1)) -> 1 | J38: =J37*(1-(1-Ramp_yr1)*((J36-$C$20-MAX(J56-1,0)*GPU_life)=0)-(1-Ramp_yr2)*((J36-$C$20-MAX(J56-1,0)*GPU_life)=1)) -> 1 | K38: =K37*(1-(1-Ramp_yr1)*((K36-$C$20-MAX(K56-1,0)*GPU_life)=0)-(1-Ramp_yr2)*((K36-$C$20-MAX(K56-1,0)*GPU_life)=1)) -> 0 | ... W38: =W37*(1-(1-Ramp_yr1)*((W36-$C$20-MAX(W56-1,0)*GPU_life)=0)-(1-Ramp_yr2)*((W36-$C$20-MAX(W56-1,0)*GPU_life)=1)) -> 0
A39: Compute price this period | B39: $/GPU-hr | D39: =IF(Assumptions!$B$7="Contracted",MAX(Price_floor,Compute_P0*(1-Price_decline)^(Assumptions!$G$23+MAX(D56-1,0)*GPU_life)),MAX(Price_floor,Compute_P0*(1-Price_decline)^MAX(Assumptions!$G$23+D36-$C$20))) -> 3.648 | E39: =IF(Assumptions!$B$7="Contracted",MAX(Price_floor,Compute_P0*(1-Price_decline)^(Assumptions!$G$23+MAX(E56-1,0)*GPU_life)),MAX(Price_floor,Compute_P0*(1-Price_decline)^MAX(Assumptions!$G$23+E36-$C$20))) -> 3.648 | F39: =IF(Assumptions!$B$7="Contracted",MAX(Price_floor,Compute_P0*(1-Price_decline)^(Assumptions!$G$23+MAX(F56-1,0)*GPU_life)),MAX(Price_floor,Compute_P0*(1-Price_decline)^MAX(Assumptions!$G$23+F36-$C$20))) -> 3.648 | G39: =IF(Assumptions!$B$7="Contracted",MAX(Price_floor,Compute_P0*(1-Price_decline)^(Assumptions!$G$23+MAX(G56-1,0)*GPU_life)),MAX(Price_floor,Compute_P0*(1-Price_decline)^MAX(Assumptions!$G$23+G36-$C$20))) -> 3.648 | H39: =IF(Assumptions!$B$7="Contracted",MAX(Price_floor,Compute_P0*(1-Price_decline)^(Assumptions!$G$23+MAX(H56-1,0)*GPU_life)),MAX(Price_floor,Compute_P0*(1-Price_decline)^MAX(Assumptions!$G$23+H36-$C$20))) -> 3.648 | I39: =IF(Assumptions!$B$7="Contracted",MAX(Price_floor,Compute_P0*(1-Price_decline)^(Assumptions!$G$23+MAX(I56-1,0)*GPU_life)),MAX(Price_floor,Compute_P0*(1-Price_decline)^MAX(Assumptions!$G$23+I36-$C$20))) -> 3.648 | J39: =IF(Assumptions!$B$7="Contracted",MAX(Price_floor,Compute_P0*(1-Price_decline)^(Assumptions!$G$23+MAX(J56-1,0)*GPU_life)),MAX(Price_floor,Compute_P0*(1-Price_decline)^MAX(Assumptions!$G$23+J36-$C$20))) -> 3.648 | K39: =IF(Assumptions!$B$7="Contracted",MAX(Price_floor,Compute_P0*(1-Price_decline)^(Assumptions!$G$23+MAX(K56-1,0)*GPU_life)),MAX(Price_floor,Compute_P0*(1-Price_decline)^MAX(Assumptions!$G$23+K36-$C$20))) -> 3.648 | ... W39: =IF(Assumptions!$B$7="Contracted",MAX(Price_floor,Compute_P0*(1-Price_decline)^(Assumptions!$G$23+MAX(W56-1,0)*GPU_life)),MAX(Price_floor,Compute_P0*(1-Price_decline)^MAX(Assumptions!$G$23+W36-$C$20))) -> 3.648
A40: Revenue (price × occupancy) | B40: $m | D40: =$C$9*D39/Compute_P0*D38 -> 0 | E40: =$C$9*E39/Compute_P0*E38 -> 0 | F40: =$C$9*F39/Compute_P0*F38 -> 1096.7464 | G40: =$C$9*G39/Compute_P0*G38 -> 1434.2068 | H40: =$C$9*H39/Compute_P0*H38 -> 1687.3021 | I40: =$C$9*I39/Compute_P0*I38 -> 1687.3021 | J40: =$C$9*J39/Compute_P0*J38 -> 1687.3021 | K40: =$C$9*K39/Compute_P0*K38 -> 0 | ... W40: =$C$9*W39/Compute_P0*W38 -> 0 | X40: =--(SUMPRODUCT(--(D40:W40<0))>0) -> 0
A41: Power cost | B41: $m | D41: =-$C$10*D38 -> 0 | E41: =-$C$10*E38 -> 0 | F41: =-$C$10*F38 -> -29.964106 | G41: =-$C$10*G38 -> -39.18383 | H41: =-$C$10*H38 -> -46.098624 | I41: =-$C$10*I38 -> -46.098624 | J41: =-$C$10*J38 -> -46.098624 | K41: =-$C$10*K38 -> 0 | ... W41: =-$C$10*W38 -> 0
A42: O&M + insurance + property tax | B42: $m | D42: =-$C$13*D37 -> 0 | E42: =-$C$13*E37 -> 0 | F42: =-$C$13*F37 -> -86.47 | G42: =-$C$13*G37 -> -86.47 | H42: =-$C$13*H37 -> -86.47 | I42: =-$C$13*I37 -> -86.47 | J42: =-$C$13*J37 -> -86.47 | K42: =-$C$13*K37 -> 0 | ... W42: =-$C$13*W37 -> 0
A43: EBITDA | B43: $m | D43: =D40+D41+D42 -> 0 | E43: =E40+E41+E42 -> 0 | F43: =F40+F41+F42 -> 980.31229 | G43: =G40+G41+G42 -> 1308.553 | H43: =H40+H41+H42 -> 1554.7335 | I43: =I40+I41+I42 -> 1554.7335 | J43: =J40+J41+J42 -> 1554.7335 | K43: =K40+K41+K42 -> 0 | ... W43: =W40+W41+W42 -> 0
A44: Depreciation | B44: $m | D44: =-($C$7*$C$15+$C$6/GPU_life)*D37 -> 0 | E44: =-($C$7*$C$15+$C$6/GPU_life)*E37 -> 0 | F44: =-($C$7*$C$15+$C$6/GPU_life)*F37 -> -615.07 | G44: =-($C$7*$C$15+$C$6/GPU_life)*G37 -> -615.07 | H44: =-($C$7*$C$15+$C$6/GPU_life)*H37 -> -615.07 | I44: =-($C$7*$C$15+$C$6/GPU_life)*I37 -> -615.07 | J44: =-($C$7*$C$15+$C$6/GPU_life)*J37 -> -615.07 | K44: =-($C$7*$C$15+$C$6/GPU_life)*K37 -> 0 | ... W44: =-($C$7*$C$15+$C$6/GPU_life)*W37 -> 0
A45: Taxable income (EBIT) | B45: $m | D45: =D43+D44 -> 0 | E45: =E43+E44 -> 0 | F45: =F43+F44 -> 365.24229 | G45: =G43+G44 -> 693.48299 | H45: =H43+H44 -> 939.66352 | I45: =I43+I44 -> 939.66352 | J45: =J43+J44 -> 939.66352 | K45: =K43+K44 -> 0 | ... W45: =W43+W44 -> 0
A46: Tax (no loss refund) | B46: $m | D46: =-Assumptions!$G$26*MAX(D45,0) -> 0 | E46: =-Assumptions!$G$26*MAX(E45,0) -> 0 | F46: =-Assumptions!$G$26*MAX(F45,0) -> -80.353303 | G46: =-Assumptions!$G$26*MAX(G45,0) -> -152.56626 | H46: =-Assumptions!$G$26*MAX(H45,0) -> -206.72597 | I46: =-Assumptions!$G$26*MAX(I45,0) -> -206.72597 | J46: =-Assumptions!$G$26*MAX(J45,0) -> -206.72597 | K46: =-Assumptions!$G$26*MAX(K45,0) -> 0 | ... W46: =-Assumptions!$G$26*MAX(W45,0) -> 0
A47: After-tax operating CF | B47: $m | D47: =D43+D46 -> 0 | E47: =E43+E46 -> 0 | F47: =F43+F46 -> 899.95898 | G47: =G43+G46 -> 1155.9867 | H47: =H43+H46 -> 1348.0075 | I47: =I43+I46 -> 1348.0075 | J47: =J43+J46 -> 1348.0075 | K47: =K43+K46 -> 0 | ... W47: =W43+W46 -> 0
A48: Facility capex (phased over build) | B48: $m | D48: =-$C$7*'Buildout Schedule'!D16 -> -870 | E48: =-$C$7*'Buildout Schedule'!E16 -> -870 | F48: =-$C$7*'Buildout Schedule'!F16 -> 0 | G48: =-$C$7*'Buildout Schedule'!G16 -> 0 | H48: =-$C$7*'Buildout Schedule'!H16 -> 0 | I48: =-$C$7*'Buildout Schedule'!I16 -> 0 | J48: =-$C$7*'Buildout Schedule'!J16 -> 0 | K48: =-$C$7*'Buildout Schedule'!K16 -> 0 | ... W48: =-$C$7*'Buildout Schedule'!W16 -> 0
A49: Holding cost (idle shell, pre-power) | B49: $m | D49: =-$C$7*Assumptions!$F$38*IF(AND(D36>=1,D36<=$C$20),1,0) -> 0 | E49: =-$C$7*Assumptions!$F$38*IF(AND(E36>=1,E36<=$C$20),1,0) -> -26.1 | F49: =-$C$7*Assumptions!$F$38*IF(AND(F36>=1,F36<=$C$20),1,0) -> -26.1 | G49: =-$C$7*Assumptions!$F$38*IF(AND(G36>=1,G36<=$C$20),1,0) -> 0 | H49: =-$C$7*Assumptions!$F$38*IF(AND(H36>=1,H36<=$C$20),1,0) -> 0 | I49: =-$C$7*Assumptions!$F$38*IF(AND(I36>=1,I36<=$C$20),1,0) -> 0 | J49: =-$C$7*Assumptions!$F$38*IF(AND(J36>=1,J36<=$C$20),1,0) -> 0 | K49: =-$C$7*Assumptions!$F$38*IF(AND(K36>=1,K36<=$C$20),1,0) -> 0 | ... W49: =-$C$7*Assumptions!$F$38*IF(AND(W36>=1,W36<=$C$20),1,0) -> 0
A50: GPU capex (at ops-start) | B50: $m | D50: =-$C$6*(D36=$C$20) -> 0 | E50: =-$C$6*(E36=$C$20) -> 0 | F50: =-$C$6*(F36=$C$20) -> -2520 | G50: =-$C$6*(G36=$C$20) -> 0 | H50: =-$C$6*(H36=$C$20) -> 0 | I50: =-$C$6*(I36=$C$20) -> 0 | J50: =-$C$6*(J36=$C$20) -> 0 | K50: =-$C$6*(K36=$C$20) -> 0 | ... W50: =-$C$6*(W36=$C$20) -> 0
A51: Salvage at exit (terminal value): facility shell + interconnection at PRE-TAX proceeds (no depreciation-recapture/gain tax) + spent GPUs after-tax | B51: $m | D51: =($C$7*Facility_salvage_pct+$C$6*GPU_salvage_pct*(1-Assumptions!$G$26))*(D36=$C$20+GPU_life-1) -> 0 | E51: =($C$7*Facility_salvage_pct+$C$6*GPU_salvage_pct*(1-Assumptions!$G$26))*(E36=$C$20+GPU_life-1) -> 0 | F51: =($C$7*Facility_salvage_pct+$C$6*GPU_salvage_pct*(1-Assumptions!$G$26))*(F36=$C$20+GPU_life-1) -> 0 | G51: =($C$7*Facility_salvage_pct+$C$6*GPU_salvage_pct*(1-Assumptions!$G$26))*(G36=$C$20+GPU_life-1) -> 0 | H51: =($C$7*Facility_salvage_pct+$C$6*GPU_salvage_pct*(1-Assumptions!$G$26))*(H36=$C$20+GPU_life-1) -> 0 | I51: =($C$7*Facility_salvage_pct+$C$6*GPU_salvage_pct*(1-Assumptions!$G$26))*(I36=$C$20+GPU_life-1) -> 0 | J51: =($C$7*Facility_salvage_pct+$C$6*GPU_salvage_pct*(1-Assumptions!$G$26))*(J36=$C$20+GPU_life-1) -> 979.56 | K51: =($C$7*Facility_salvage_pct+$C$6*GPU_salvage_pct*(1-Assumptions!$G$26))*(K36=$C$20+GPU_life-1) -> 0 | ... W51: =($C$7*Facility_salvage_pct+$C$6*GPU_salvage_pct*(1-Assumptions!$G$26))*(W36=$C$20+GPU_life-1) -> 0
A52: Net free cash flow | B52: $m | D52: =D47+D48+D49+D50+D51 -> -870 | E52: =E47+E48+E49+E50+E51 -> -896.1 | F52: =F47+F48+F49+F50+F51 -> -1646.141 | G52: =G47+G48+G49+G50+G51 -> 1155.9867 | H52: =H47+H48+H49+H50+H51 -> 1348.0075 | I52: =I47+I48+I49+I50+I51 -> 1348.0075 | J52: =J47+J48+J49+J50+J51 -> 2327.5675 | K52: =K47+K48+K49+K50+K51 -> 0 | ... W52: =W47+W48+W49+W50+W51 -> 0
A53: Discount factor | B53: x | D53: =$C$21^D36 -> 1 | E53: =$C$21^E36 -> 0.94037991 | F53: =$C$21^F36 -> 0.88431438 | G53: =$C$21^G36 -> 0.83159148 | H53: =$C$21^H36 -> 0.78201193 | I53: =$C$21^I36 -> 0.73538831 | J53: =$C$21^J36 -> 0.69154439 | K53: =$C$21^K36 -> 0.65031446 | ... W53: =$C$21^W36 -> 0.31100225 | X53: =--(D53<>1) -> 0
A54: Discounted FCF | B54: $m | D54: =D52*D53 -> -870 | E54: =E52*E53 -> -842.67444 | F54: =F52*F53 -> -1455.7062 | G54: =G52*G53 -> 961.30872 | H54: =H52*H53 -> 1054.158 | I54: =I52*I53 -> 991.30899 | J54: =J52*J53 -> 1609.6163 | K54: =K52*K53 -> 0 | ... W54: =W52*W53 -> 0
A55: Cumulative net FCF | B55: $m | D55: =D52 -> -870 | E55: =D55+E52 -> -1766.1 | F55: =E55+F52 -> -3412.241 | G55: =F55+G52 -> -2256.2543 | H55: =G55+H52 -> -908.24674 | I55: =H55+I52 -> 439.76081 | J55: =I55+J52 -> 2767.3284 | K55: =J55+K52 -> 2767.3284 | L55: =K55+L52 -> 2767.3284 | ... W55: =V55+W52 -> 2767.3284
A56: Operating cycle (0 = idle, 1 = single hold) | D56: =IF(D36<$C$20,0,IF(D36<=$C$20+GPU_life-1,1,0)) -> 0 | E56: =IF(E36<$C$20,0,IF(E36<=$C$20+GPU_life-1,1,0)) -> 0 | F56: =IF(F36<$C$20,0,IF(F36<=$C$20+GPU_life-1,1,0)) -> 1 | G56: =IF(G36<$C$20,0,IF(G36<=$C$20+GPU_life-1,1,0)) -> 1 | H56: =IF(H36<$C$20,0,IF(H36<=$C$20+GPU_life-1,1,0)) -> 1 | I56: =IF(I36<$C$20,0,IF(I36<=$C$20+GPU_life-1,1,0)) -> 1 | J56: =IF(J36<$C$20,0,IF(J36<=$C$20+GPU_life-1,1,0)) -> 1 | K56: =IF(K36<$C$20,0,IF(K36<=$C$20+GPU_life-1,1,0)) -> 0 | ... W56: =IF(W36<$C$20,0,IF(W36<=$C$20+GPU_life-1,1,0)) -> 0
A57: After-tax operating-margin PV (occupancy-scaling part — feeds break-even) | C57: =SUMPRODUCT((D40:W40+D41:W41),D53:W53)*(1-Assumptions!$G$26) -> 4468.4545
A58: Internal row-checks (must be 0) | C58: =SUM(X37,X53,X40) -> 0
A60: Summary outputs
A61: NPV (sum of discounted FCF) | B61: $m | C61: =SUM(D54:W54) -> 1448.0114
A62: IRR | B62: % | C62: =IFERROR(IRR(D52:W52),"n/a") -> 0.18467513
A63: Payback (incl. build) | B63: yr | C63: =SUMPRODUCT(--(D55:W55<0)) -> 5
A64: Break-even utilization | B64: % | C64: =IF(C57<=0,"n/a",IF(Paid_occupancy*(1-C61/C57)>1,">100% (never)",IFERROR(Paid_occupancy*(1-C61/C57),"n/a"))) -> 0.59483429

Sheet Country Engine
A1: Country Engine — every country × deal, per period (identical method to Calculations) | C1: =IF(Checks!$C$4>0,"MODEL IN ERROR","checks OK") -> checks OK
A2: Each country's full 20-period cash flow, computed BOTH deal types, so the multi-country and both-deal NPVs use the SAME method as the single-country drill — the closed-form that could out-run the grid is retired. Feeds Comparison (active deal) and Deal Comparison (both). All $m.
A3: Period index | D3: 0 | E3: 1 | F3: 2 | G3: 3 | H3: 4 | I3: 5 | J3: 6 | K3: 7 | L3: 8 | M3: 9 | N3: 10 | O3: 11 | P3: 12 | Q3: 13 | R3: 14 | S3: 15 | T3: 16 | U3: 17 | V3: 18 | W3: 19
A5: ── Norway · Contracted ── | B5: Norway
A6: Ops start S (yr) | C6: =ROUND($C$27,0) -> 2
A7: WACC (incl deal) | C7: =INDEX(Assumptions!$I$50:$K$54,$C$11,MATCH(Assumptions!$B$4,Assumptions!$D$9:$F$9,0))+Assumptions!$C$46 -> 0.0634
A8: Discount base v | C8: =1/(1+$C$7) -> 0.94037991
A9: Power cost (full occ) $m | C9: =IT_load_MW*INDEX(Assumptions!$M$50:$M$54,$C$11,1)*Hours_per_year*INDEX(Assumptions!$C$50:$E$54,$C$11,MATCH(Assumptions!$B$4,Assumptions!$D$9:$F$9,0))*Assumptions!$C$45/Unit_scale -> 46.098624
A10: Opex $m | C10: =IT_load_MW*OM_fixed+Insurance_rate*Calculations!$C$6+INDEX(Assumptions!$O$50:$O$54,$C$11,1)*($C$13+Calculations!$C$6)*(1-Prop_tax_abatement) -> 86.47
A11: country row index | C11: =MATCH($B$5,Assumptions!$B$50:$B$54,0) -> 1
A12: Tax rate | C12: =INDEX(Assumptions!$L$50:$L$54,MATCH($B$5,Assumptions!$B$50:$B$54,0),1) -> 0.22
A13: Facility capex $m | C13: =IT_load_MW*(Facility_capex_MW+INDEX(Assumptions!$N$50:$N$54,$C$11,1)) -> 1740
A14: GPU capex $m | C14: =Calculations!$C$6 -> 2520
A15: Year-1 full revenue $m | C15: =IT_load_MW*Assumptions!$G$12*Hours_per_year*Assumptions!$C$45/Unit_scale*Compute_P0 -> 2636.4096
A16: operating flag | D16: =IF(D$3<$C$6,0,IF(D$3<=$C$6+GPU_life-1,1,0)) -> 0 | E16: =IF(E$3<$C$6,0,IF(E$3<=$C$6+GPU_life-1,1,0)) -> 0 | F16: =IF(F$3<$C$6,0,IF(F$3<=$C$6+GPU_life-1,1,0)) -> 1 | G16: =IF(G$3<$C$6,0,IF(G$3<=$C$6+GPU_life-1,1,0)) -> 1 | H16: =IF(H$3<$C$6,0,IF(H$3<=$C$6+GPU_life-1,1,0)) -> 1 | I16: =IF(I$3<$C$6,0,IF(I$3<=$C$6+GPU_life-1,1,0)) -> 1 | J16: =IF(J$3<$C$6,0,IF(J$3<=$C$6+GPU_life-1,1,0)) -> 1 | K16: =IF(K$3<$C$6,0,IF(K$3<=$C$6+GPU_life-1,1,0)) -> 0 | ... W16: =IF(W$3<$C$6,0,IF(W$3<=$C$6+GPU_life-1,1,0)) -> 0
A17: flag | D17: =--(D16>0) -> 0 | E17: =--(E16>0) -> 0 | F17: =--(F16>0) -> 1 | G17: =--(G16>0) -> 1 | H17: =--(H16>0) -> 1 | I17: =--(I16>0) -> 1 | J17: =--(J16>0) -> 1 | K17: =--(K16>0) -> 0 | ... W17: =--(W16>0) -> 0
A18: occupancy | D18: =D17*(1-(1-Ramp_yr1)*((D$3-$C$6)=0)-(1-Ramp_yr2)*((D$3-$C$6)=1)) -> 0 | E18: =E17*(1-(1-Ramp_yr1)*((E$3-$C$6)=0)-(1-Ramp_yr2)*((E$3-$C$6)=1)) -> 0 | F18: =F17*(1-(1-Ramp_yr1)*((F$3-$C$6)=0)-(1-Ramp_yr2)*((F$3-$C$6)=1)) -> 0.65 | G18: =G17*(1-(1-Ramp_yr1)*((G$3-$C$6)=0)-(1-Ramp_yr2)*((G$3-$C$6)=1)) -> 0.85 | H18: =H17*(1-(1-Ramp_yr1)*((H$3-$C$6)=0)-(1-Ramp_yr2)*((H$3-$C$6)=1)) -> 1 | I18: =I17*(1-(1-Ramp_yr1)*((I$3-$C$6)=0)-(1-Ramp_yr2)*((I$3-$C$6)=1)) -> 1 | J18: =J17*(1-(1-Ramp_yr1)*((J$3-$C$6)=0)-(1-Ramp_yr2)*((J$3-$C$6)=1)) -> 1 | K18: =K17*(1-(1-Ramp_yr1)*((K$3-$C$6)=0)-(1-Ramp_yr2)*((K$3-$C$6)=1)) -> 0 | ... W18: =W17*(1-(1-Ramp_yr1)*((W$3-$C$6)=0)-(1-Ramp_yr2)*((W$3-$C$6)=1)) -> 0
A19: price $/GPU-hr | D19: =MAX(Price_floor,Compute_P0*(1-Price_decline)^$C$27) -> 3.648 | E19: =MAX(Price_floor,Compute_P0*(1-Price_decline)^$C$27) -> 3.648 | F19: =MAX(Price_floor,Compute_P0*(1-Price_decline)^$C$27) -> 3.648 | G19: =MAX(Price_floor,Compute_P0*(1-Price_decline)^$C$27) -> 3.648 | H19: =MAX(Price_floor,Compute_P0*(1-Price_decline)^$C$27) -> 3.648 | I19: =MAX(Price_floor,Compute_P0*(1-Price_decline)^$C$27) -> 3.648 | J19: =MAX(Price_floor,Compute_P0*(1-Price_decline)^$C$27) -> 3.648 | K19: =MAX(Price_floor,Compute_P0*(1-Price_decline)^$C$27) -> 3.648 | ... W19: =MAX(Price_floor,Compute_P0*(1-Price_decline)^$C$27) -> 3.648
A20: revenue | D20: =$C$15*D19/Compute_P0*D18 -> 0 | E20: =$C$15*E19/Compute_P0*E18 -> 0 | F20: =$C$15*F19/Compute_P0*F18 -> 1096.7464 | G20: =$C$15*G19/Compute_P0*G18 -> 1434.2068 | H20: =$C$15*H19/Compute_P0*H18 -> 1687.3021 | I20: =$C$15*I19/Compute_P0*I18 -> 1687.3021 | J20: =$C$15*J19/Compute_P0*J18 -> 1687.3021 | K20: =$C$15*K19/Compute_P0*K18 -> 0 | ... W20: =$C$15*W19/Compute_P0*W18 -> 0
A21: EBITDA | D21: =D20-$C$9*D18-$C$10*D17 -> 0 | E21: =E20-$C$9*E18-$C$10*E17 -> 0 | F21: =F20-$C$9*F18-$C$10*F17 -> 980.31229 | G21: =G20-$C$9*G18-$C$10*G17 -> 1308.553 | H21: =H20-$C$9*H18-$C$10*H17 -> 1554.7335 | I21: =I20-$C$9*I18-$C$10*I17 -> 1554.7335 | J21: =J20-$C$9*J18-$C$10*J17 -> 1554.7335 | K21: =K20-$C$9*K18-$C$10*K17 -> 0 | ... W21: =W20-$C$9*W18-$C$10*W17 -> 0
A22: depreciation | D22: =-($C$13*Calculations!$C$15+$C$14/GPU_life)*D17 -> 0 | E22: =-($C$13*Calculations!$C$15+$C$14/GPU_life)*E17 -> 0 | F22: =-($C$13*Calculations!$C$15+$C$14/GPU_life)*F17 -> -615.07 | G22: =-($C$13*Calculations!$C$15+$C$14/GPU_life)*G17 -> -615.07 | H22: =-($C$13*Calculations!$C$15+$C$14/GPU_life)*H17 -> -615.07 | I22: =-($C$13*Calculations!$C$15+$C$14/GPU_life)*I17 -> -615.07 | J22: =-($C$13*Calculations!$C$15+$C$14/GPU_life)*J17 -> -615.07 | K22: =-($C$13*Calculations!$C$15+$C$14/GPU_life)*K17 -> 0 | ... W22: =-($C$13*Calculations!$C$15+$C$14/GPU_life)*W17 -> 0
A23: tax | D23: =-$C$12*MAX(D21+D22,0) -> 0 | E23: =-$C$12*MAX(E21+E22,0) -> 0 | F23: =-$C$12*MAX(F21+F22,0) -> -80.353303 | G23: =-$C$12*MAX(G21+G22,0) -> -152.56626 | H23: =-$C$12*MAX(H21+H22,0) -> -206.72597 | I23: =-$C$12*MAX(I21+I22,0) -> -206.72597 | J23: =-$C$12*MAX(J21+J22,0) -> -206.72597 | K23: =-$C$12*MAX(K21+K22,0) -> 0 | ... W23: =-$C$12*MAX(W21+W22,0) -> 0
A24: net FCF | D24: =D21+D23-$C$13*IF($C$6=0,--(D$3=0),--(D$3<=$C$6-1)/$C$6)-$C$13*Assumptions!$F$38*IF(AND(D$3>=1,D$3<=$C$6),1,0)-$C$14*(D$3=$C$6)+($C$13*Facility_salvage_pct+$C$14*GPU_salvage_pct*(1-$C$12))*(D$3=$C$6+GPU_life-1) -> -870 | E24: =E21+E23-$C$13*IF($C$6=0,--(E$3=0),--(E$3<=$C$6-1)/$C$6)-$C$13*Assumptions!$F$38*IF(AND(E$3>=1,E$3<=$C$6),1,0)-$C$14*(E$3=$C$6)+($C$13*Facility_salvage_pct+$C$14*GPU_salvage_pct*(1-$C$12))*(E$3=$C$6+GPU_life-1) -> -896.1 | F24: =F21+F23-$C$13*IF($C$6=0,--(F$3=0),--(F$3<=$C$6-1)/$C$6)-$C$13*Assumptions!$F$38*IF(AND(F$3>=1,F$3<=$C$6),1,0)-$C$14*(F$3=$C$6)+($C$13*Facility_salvage_pct+$C$14*GPU_salvage_pct*(1-$C$12))*(F$3=$C$6+GPU_life-1) -> -1646.141 | G24: =G21+G23-$C$13*IF($C$6=0,--(G$3=0),--(G$3<=$C$6-1)/$C$6)-$C$13*Assumptions!$F$38*IF(AND(G$3>=1,G$3<=$C$6),1,0)-$C$14*(G$3=$C$6)+($C$13*Facility_salvage_pct+$C$14*GPU_salvage_pct*(1-$C$12))*(G$3=$C$6+GPU_life-1) -> 1155.9867 | H24: =H21+H23-$C$13*IF($C$6=0,--(H$3=0),--(H$3<=$C$6-1)/$C$6)-$C$13*Assumptions!$F$38*IF(AND(H$3>=1,H$3<=$C$6),1,0)-$C$14*(H$3=$C$6)+($C$13*Facility_salvage_pct+$C$14*GPU_salvage_pct*(1-$C$12))*(H$3=$C$6+GPU_life-1) -> 1348.0075 | I24: =I21+I23-$C$13*IF($C$6=0,--(I$3=0),--(I$3<=$C$6-1)/$C$6)-$C$13*Assumptions!$F$38*IF(AND(I$3>=1,I$3<=$C$6),1,0)-$C$14*(I$3=$C$6)+($C$13*Facility_salvage_pct+$C$14*GPU_salvage_pct*(1-$C$12))*(I$3=$C$6+GPU_life-1) -> 1348.0075 | J24: =J21+J23-$C$13*IF($C$6=0,--(J$3=0),--(J$3<=$C$6-1)/$C$6)-$C$13*Assumptions!$F$38*IF(AND(J$3>=1,J$3<=$C$6),1,0)-$C$14*(J$3=$C$6)+($C$13*Facility_salvage_pct+$C$14*GPU_salvage_pct*(1-$C$12))*(J$3=$C$6+GPU_life-1) -> 2327.5675 | K24: =K21+K23-$C$13*IF($C$6=0,--(K$3=0),--(K$3<=$C$6-1)/$C$6)-$C$13*Assumptions!$F$38*IF(AND(K$3>=1,K$3<=$C$6),1,0)-$C$14*(K$3=$C$6)+($C$13*Facility_salvage_pct+$C$14*GPU_salvage_pct*(1-$C$12))*(K$3=$C$6+GPU_life-1) -> 0 | ... W24: =W21+W23-$C$13*IF($C$6=0,--(W$3=0),--(W$3<=$C$6-1)/$C$6)-$C$13*Assumptions!$F$38*IF(AND(W$3>=1,W$3<=$C$6),1,0)-$C$14*(W$3=$C$6)+($C$13*Facility_salvage_pct+$C$14*GPU_salvage_pct*(1-$C$12))*(W$3=$C$6+GPU_life-1) -> 0
A25: discounted FCF | D25: =D24*$C$8^D$3 -> -870 | E25: =E24*$C$8^E$3 -> -842.67444 | F25: =F24*$C$8^F$3 -> -1455.7062 | G25: =G24*$C$8^G$3 -> 961.30872 | H25: =H24*$C$8^H$3 -> 1054.158 | I25: =I24*$C$8^I$3 -> 991.30899 | J25: =J24*$C$8^J$3 -> 1609.6163 | K25: =K24*$C$8^K$3 -> 0 | ... W25: =W24*$C$8^W$3 -> 0
A26: op-margin PV term | D26: =(D20-$C$9*D18)*(1-$C$12)*$C$8^D$3 -> 0 | E26: =(E20-$C$9*E18)*(1-$C$12)*$C$8^E$3 -> 0 | F26: =(F20-$C$9*F18)*(1-$C$12)*$C$8^F$3 -> 735.82932 | G26: =(G20-$C$9*G18)*(1-$C$12)*$C$8^G$3 -> 904.8696 | H26: =(H20-$C$9*H18)*(1-$C$12)*$C$8^H$3 -> 1001.0838 | I26: =(I20-$C$9*I18)*(1-$C$12)*$C$8^I$3 -> 941.39906 | J26: =(J20-$C$9*J18)*(1-$C$12)*$C$8^J$3 -> 885.27277 | K26: =(K20-$C$9*K18)*(1-$C$12)*$C$8^K$3 -> 0 | ... W26: =(W20-$C$9*W18)*(1-$C$12)*$C$8^W$3 -> 0
A27: active TTP (raw) | C27: =INDEX(Assumptions!$F$50:$H$54,$C$11,MATCH(Assumptions!$B$4,Assumptions!$D$9:$F$9,0)) -> 2
A28: NPV ($m) | C28: =SUM(D25:W25) -> 1448.0114
A29: Op-margin PV | C29: =SUM(D26:W26) -> 4468.4545
A30: Break-even utilization | C30: =IF(C29<=0,"n/a",IF(Assumptions!$C$45*(1-C28/C29)>1,">100% (never)",Assumptions!$C$45*(1-C28/C29))) -> 0.59483429
A49: ── Norway · Merchant ── | B49: Norway
A50: Ops start S (yr) | C50: =ROUND($C$71,0) -> 2
A51: WACC (incl deal) | C51: =INDEX(Assumptions!$I$50:$K$54,$C$55,MATCH(Assumptions!$B$4,Assumptions!$D$9:$F$9,0))+Assumptions!$D$46 -> 0.1084
A52: Discount base v | C52: =1/(1+$C$51) -> 0.90220137
A53: Power cost (full occ) $m | C53: =IT_load_MW*INDEX(Assumptions!$M$50:$M$54,$C$55,1)*Hours_per_year*INDEX(Assumptions!$C$50:$E$54,$C$55,MATCH(Assumptions!$B$4,Assumptions!$D$9:$F$9,0))*Assumptions!$D$45/Unit_scale -> 36.66936
A54: Opex $m | C54: =IT_load_MW*OM_fixed+Insurance_rate*Calculations!$C$6+INDEX(Assumptions!$O$50:$O$54,$C$55,1)*($C$57+Calculations!$C$6)*(1-Prop_tax_abatement) -> 86.47
A55: country row index | C55: =MATCH($B$49,Assumptions!$B$50:$B$54,0) -> 1
A56: Tax rate | C56: =INDEX(Assumptions!$L$50:$L$54,MATCH($B$49,Assumptions!$B$50:$B$54,0),1) -> 0.22
A57: Facility capex $m | C57: =IT_load_MW*(Facility_capex_MW+INDEX(Assumptions!$N$50:$N$54,$C$55,1)) -> 1740
A58: GPU capex $m | C58: =Calculations!$C$6 -> 2520
A59: Year-1 full revenue $m | C59: =IT_load_MW*Assumptions!$G$12*Hours_per_year*Assumptions!$D$45/Unit_scale*Compute_P0 -> 2097.144
A60: operating flag | D60: =IF(D$3<$C$50,0,IF(D$3<=$C$50+GPU_life-1,1,0)) -> 0 | E60: =IF(E$3<$C$50,0,IF(E$3<=$C$50+GPU_life-1,1,0)) -> 0 | F60: =IF(F$3<$C$50,0,IF(F$3<=$C$50+GPU_life-1,1,0)) -> 1 | G60: =IF(G$3<$C$50,0,IF(G$3<=$C$50+GPU_life-1,1,0)) -> 1 | H60: =IF(H$3<$C$50,0,IF(H$3<=$C$50+GPU_life-1,1,0)) -> 1 | I60: =IF(I$3<$C$50,0,IF(I$3<=$C$50+GPU_life-1,1,0)) -> 1 | J60: =IF(J$3<$C$50,0,IF(J$3<=$C$50+GPU_life-1,1,0)) -> 1 | K60: =IF(K$3<$C$50,0,IF(K$3<=$C$50+GPU_life-1,1,0)) -> 0 | ... W60: =IF(W$3<$C$50,0,IF(W$3<=$C$50+GPU_life-1,1,0)) -> 0
A61: flag | D61: =--(D60>0) -> 0 | E61: =--(E60>0) -> 0 | F61: =--(F60>0) -> 1 | G61: =--(G60>0) -> 1 | H61: =--(H60>0) -> 1 | I61: =--(I60>0) -> 1 | J61: =--(J60>0) -> 1 | K61: =--(K60>0) -> 0 | ... W61: =--(W60>0) -> 0
A62: occupancy | D62: =D61*(1-(1-Ramp_yr1)*((D$3-$C$50)=0)-(1-Ramp_yr2)*((D$3-$C$50)=1)) -> 0 | E62: =E61*(1-(1-Ramp_yr1)*((E$3-$C$50)=0)-(1-Ramp_yr2)*((E$3-$C$50)=1)) -> 0 | F62: =F61*(1-(1-Ramp_yr1)*((F$3-$C$50)=0)-(1-Ramp_yr2)*((F$3-$C$50)=1)) -> 0.65 | G62: =G61*(1-(1-Ramp_yr1)*((G$3-$C$50)=0)-(1-Ramp_yr2)*((G$3-$C$50)=1)) -> 0.85 | H62: =H61*(1-(1-Ramp_yr1)*((H$3-$C$50)=0)-(1-Ramp_yr2)*((H$3-$C$50)=1)) -> 1 | I62: =I61*(1-(1-Ramp_yr1)*((I$3-$C$50)=0)-(1-Ramp_yr2)*((I$3-$C$50)=1)) -> 1 | J62: =J61*(1-(1-Ramp_yr1)*((J$3-$C$50)=0)-(1-Ramp_yr2)*((J$3-$C$50)=1)) -> 1 | K62: =K61*(1-(1-Ramp_yr1)*((K$3-$C$50)=0)-(1-Ramp_yr2)*((K$3-$C$50)=1)) -> 0 | ... W62: =W61*(1-(1-Ramp_yr1)*((W$3-$C$50)=0)-(1-Ramp_yr2)*((W$3-$C$50)=1)) -> 0
A63: price $/GPU-hr | D63: =MAX(Price_floor,Compute_P0*(1-Price_decline)^MAX($C$71+D$3-$C$50)) -> 5.7 | E63: =MAX(Price_floor,Compute_P0*(1-Price_decline)^MAX($C$71+E$3-$C$50)) -> 4.56 | F63: =MAX(Price_floor,Compute_P0*(1-Price_decline)^MAX($C$71+F$3-$C$50)) -> 3.648 | G63: =MAX(Price_floor,Compute_P0*(1-Price_decline)^MAX($C$71+G$3-$C$50)) -> 2.9184 | H63: =MAX(Price_floor,Compute_P0*(1-Price_decline)^MAX($C$71+H$3-$C$50)) -> 2.5 | I63: =MAX(Price_floor,Compute_P0*(1-Price_decline)^MAX($C$71+I$3-$C$50)) -> 2.5 | J63: =MAX(Price_floor,Compute_P0*(1-Price_decline)^MAX($C$71+J$3-$C$50)) -> 2.5 | K63: =MAX(Price_floor,Compute_P0*(1-Price_decline)^MAX($C$71+K$3-$C$50)) -> 2.5 | ... W63: =MAX(Price_floor,Compute_P0*(1-Price_decline)^MAX($C$71+W$3-$C$50)) -> 2.5
A64: revenue | D64: =$C$59*D63/Compute_P0*D62 -> 0 | E64: =$C$59*E63/Compute_P0*E62 -> 0 | F64: =$C$59*F63/Compute_P0*F62 -> 872.4119 | G64: =$C$59*G63/Compute_P0*G62 -> 912.67707 | H64: =$C$59*H63/Compute_P0*H62 -> 919.8 | I64: =$C$59*I63/Compute_P0*I62 -> 919.8 | J64: =$C$59*J63/Compute_P0*J62 -> 919.8 | K64: =$C$59*K63/Compute_P0*K62 -> 0 | ... W64: =$C$59*W63/Compute_P0*W62 -> 0
A65: EBITDA | D65: =D64-$C$53*D62-$C$54*D61 -> 0 | E65: =E64-$C$53*E62-$C$54*E61 -> 0 | F65: =F64-$C$53*F62-$C$54*F61 -> 762.10682 | G65: =G64-$C$53*G62-$C$54*G61 -> 795.03811 | H65: =H64-$C$53*H62-$C$54*H61 -> 796.66064 | I65: =I64-$C$53*I62-$C$54*I61 -> 796.66064 | J65: =J64-$C$53*J62-$C$54*J61 -> 796.66064 | K65: =K64-$C$53*K62-$C$54*K61 -> 0 | ... W65: =W64-$C$53*W62-$C$54*W61 -> 0
A66: depreciation | D66: =-($C$57*Calculations!$C$15+$C$58/GPU_life)*D61 -> 0 | E66: =-($C$57*Calculations!$C$15+$C$58/GPU_life)*E61 -> 0 | F66: =-($C$57*Calculations!$C$15+$C$58/GPU_life)*F61 -> -615.07 | G66: =-($C$57*Calculations!$C$15+$C$58/GPU_life)*G61 -> -615.07 | H66: =-($C$57*Calculations!$C$15+$C$58/GPU_life)*H61 -> -615.07 | I66: =-($C$57*Calculations!$C$15+$C$58/GPU_life)*I61 -> -615.07 | J66: =-($C$57*Calculations!$C$15+$C$58/GPU_life)*J61 -> -615.07 | K66: =-($C$57*Calculations!$C$15+$C$58/GPU_life)*K61 -> 0 | ... W66: =-($C$57*Calculations!$C$15+$C$58/GPU_life)*W61 -> 0
A67: tax | D67: =-$C$56*MAX(D65+D66,0) -> 0 | E67: =-$C$56*MAX(E65+E66,0) -> 0 | F67: =-$C$56*MAX(F65+F66,0) -> -32.3481 | G67: =-$C$56*MAX(G65+G66,0) -> -39.592985 | H67: =-$C$56*MAX(H65+H66,0) -> -39.949941 | I67: =-$C$56*MAX(I65+I66,0) -> -39.949941 | J67: =-$C$56*MAX(J65+J66,0) -> -39.949941 | K67: =-$C$56*MAX(K65+K66,0) -> 0 | ... W67: =-$C$56*MAX(W65+W66,0) -> 0
A68: net FCF | D68: =D65+D67-$C$57*IF($C$50=0,--(D$3=0),--(D$3<=$C$50-1)/$C$50)-$C$57*Assumptions!$F$38*IF(AND(D$3>=1,D$3<=$C$50),1,0)-$C$58*(D$3=$C$50)+($C$57*Facility_salvage_pct+$C$58*GPU_salvage_pct*(1-$C$56))*(D$3=$C$50+GPU_life-1) -> -870 | E68: =E65+E67-$C$57*IF($C$50=0,--(E$3=0),--(E$3<=$C$50-1)/$C$50)-$C$57*Assumptions!$F$38*IF(AND(E$3>=1,E$3<=$C$50),1,0)-$C$58*(E$3=$C$50)+($C$57*Facility_salvage_pct+$C$58*GPU_salvage_pct*(1-$C$56))*(E$3=$C$50+GPU_life-1) -> -896.1 | F68: =F65+F67-$C$57*IF($C$50=0,--(F$3=0),--(F$3<=$C$50-1)/$C$50)-$C$57*Assumptions!$F$38*IF(AND(F$3>=1,F$3<=$C$50),1,0)-$C$58*(F$3=$C$50)+($C$57*Facility_salvage_pct+$C$58*GPU_salvage_pct*(1-$C$56))*(F$3=$C$50+GPU_life-1) -> -1816.3413 | G68: =G65+G67-$C$57*IF($C$50=0,--(G$3=0),--(G$3<=$C$50-1)/$C$50)-$C$57*Assumptions!$F$38*IF(AND(G$3>=1,G$3<=$C$50),1,0)-$C$58*(G$3=$C$50)+($C$57*Facility_salvage_pct+$C$58*GPU_salvage_pct*(1-$C$56))*(G$3=$C$50+GPU_life-1) -> 755.44513 | H68: =H65+H67-$C$57*IF($C$50=0,--(H$3=0),--(H$3<=$C$50-1)/$C$50)-$C$57*Assumptions!$F$38*IF(AND(H$3>=1,H$3<=$C$50),1,0)-$C$58*(H$3=$C$50)+($C$57*Facility_salvage_pct+$C$58*GPU_salvage_pct*(1-$C$56))*(H$3=$C$50+GPU_life-1) -> 756.7107 | I68: =I65+I67-$C$57*IF($C$50=0,--(I$3=0),--(I$3<=$C$50-1)/$C$50)-$C$57*Assumptions!$F$38*IF(AND(I$3>=1,I$3<=$C$50),1,0)-$C$58*(I$3=$C$50)+($C$57*Facility_salvage_pct+$C$58*GPU_salvage_pct*(1-$C$56))*(I$3=$C$50+GPU_life-1) -> 756.7107 | J68: =J65+J67-$C$57*IF($C$50=0,--(J$3=0),--(J$3<=$C$50-1)/$C$50)-$C$57*Assumptions!$F$38*IF(AND(J$3>=1,J$3<=$C$50),1,0)-$C$58*(J$3=$C$50)+($C$57*Facility_salvage_pct+$C$58*GPU_salvage_pct*(1-$C$56))*(J$3=$C$50+GPU_life-1) -> 1736.2707 | K68: =K65+K67-$C$57*IF($C$50=0,--(K$3=0),--(K$3<=$C$50-1)/$C$50)-$C$57*Assumptions!$F$38*IF(AND(K$3>=1,K$3<=$C$50),1,0)-$C$58*(K$3=$C$50)+($C$57*Facility_salvage_pct+$C$58*GPU_salvage_pct*(1-$C$56))*(K$3=$C$50+GPU_life-1) -> 0 | ... W68: =W65+W67-$C$57*IF($C$50=0,--(W$3=0),--(W$3<=$C$50-1)/$C$50)-$C$57*Assumptions!$F$38*IF(AND(W$3>=1,W$3<=$C$50),1,0)-$C$58*(W$3=$C$50)+($C$57*Facility_salvage_pct+$C$58*GPU_salvage_pct*(1-$C$56))*(W$3=$C$50+GPU_life-1) -> 0
A69: discounted FCF | D69: =D68*$C$52^D$3 -> -870 | E69: =E68*$C$52^E$3 -> -808.46265 | F69: =F68*$C$52^F$3 -> -1478.4424 | G69: =G68*$C$52^G$3 -> 554.77052 | H69: =H68*$C$52^H$3 -> 501.35322 | I69: =I68*$C$52^I$3 -> 452.32156 | J69: =J68*$C$52^J$3 -> 936.35026 | K69: =K68*$C$52^K$3 -> 0 | ... W69: =W68*$C$52^W$3 -> 0
A70: op-margin PV term | D70: =(D64-$C$53*D62)*(1-$C$56)*$C$52^D$3 -> 0 | E70: =(E64-$C$53*E62)*(1-$C$56)*$C$52^E$3 -> 0 | F70: =(F64-$C$53*F62)*(1-$C$56)*$C$52^F$3 -> 538.75676 | G70: =(G64-$C$53*G62)*(1-$C$56)*$C$52^G$3 -> 504.93022 | H70: =(H64-$C$53*H62)*(1-$C$56)*$C$52^H$3 -> 456.38723 | I70: =(I64-$C$53*I62)*(1-$C$56)*$C$52^I$3 -> 411.75319 | J70: =(J64-$C$53*J62)*(1-$C$56)*$C$52^J$3 -> 371.48429 | K70: =(K64-$C$53*K62)*(1-$C$56)*$C$52^K$3 -> 0 | ... W70: =(W64-$C$53*W62)*(1-$C$56)*$C$52^W$3 -> 0
A71: active TTP (raw) | C71: =INDEX(Assumptions!$F$50:$H$54,$C$55,MATCH(Assumptions!$B$4,Assumptions!$D$9:$F$9,0)) -> 2
A72: NPV ($m) | C72: =SUM(D69:W69) -> -712.10953
A73: Op-margin PV | C73: =SUM(D70:W70) -> 2283.3117
A74: Break-even utilization | C74: =IF(C73<=0,"n/a",IF(Assumptions!$D$45*(1-C72/C73)>1,">100% (never)",Assumptions!$D$45*(1-C72/C73))) -> 0.91831302
A93: ── United States · Contracted ── | B93: United States
A94: Ops start S (yr) | C94: =ROUND($C$115,0) -> 5
A95: WACC (incl deal) | C95: =INDEX(Assumptions!$I$50:$K$54,$C$99,MATCH(Assumptions!$B$4,Assumptions!$D$9:$F$9,0))+Assumptions!$C$46 -> 0.0634
A96: Discount base v | C96: =1/(1+$C$95) -> 0.94037991
A97: Power cost (full occ) $m | C97: =IT_load_MW*INDEX(Assumptions!$M$50:$M$54,$C$99,1)*Hours_per_year*INDEX(Assumptions!$C$50:$E$54,$C$99,MATCH(Assumptions!$B$4,Assumptions!$D$9:$F$9,0))*Assumptions!$C$45/Unit_scale -> 60.12864
A98: Opex $m | C98: =IT_load_MW*OM_fixed+Insurance_rate*Calculations!$C$6+INDEX(Assumptions!$O$50:$O$54,$C$99,1)*($C$101+Calculations!$C$6)*(1-Prop_tax_abatement) -> 101.48
A99: country row index | C99: =MATCH($B$93,Assumptions!$B$50:$B$54,0) -> 2
A100: Tax rate | C100: =INDEX(Assumptions!$L$50:$L$54,MATCH($B$93,Assumptions!$B$50:$B$54,0),1) -> 0.21
A101: Facility capex $m | C101: =IT_load_MW*(Facility_capex_MW+INDEX(Assumptions!$N$50:$N$54,$C$99,1)) -> 1760
A102: GPU capex $m | C102: =Calculations!$C$6 -> 2520
A103: Year-1 full revenue $m | C103: =IT_load_MW*Assumptions!$G$12*Hours_per_year*Assumptions!$C$45/Unit_scale*Compute_P0 -> 2636.4096
A104: operating flag | D104: =IF(D$3<$C$94,0,IF(D$3<=$C$94+GPU_life-1,1,0)) -> 0 | E104: =IF(E$3<$C$94,0,IF(E$3<=$C$94+GPU_life-1,1,0)) -> 0 | F104: =IF(F$3<$C$94,0,IF(F$3<=$C$94+GPU_life-1,1,0)) -> 0 | G104: =IF(G$3<$C$94,0,IF(G$3<=$C$94+GPU_life-1,1,0)) -> 0 | H104: =IF(H$3<$C$94,0,IF(H$3<=$C$94+GPU_life-1,1,0)) -> 0 | I104: =IF(I$3<$C$94,0,IF(I$3<=$C$94+GPU_life-1,1,0)) -> 1 | J104: =IF(J$3<$C$94,0,IF(J$3<=$C$94+GPU_life-1,1,0)) -> 1 | K104: =IF(K$3<$C$94,0,IF(K$3<=$C$94+GPU_life-1,1,0)) -> 1 | ... W104: =IF(W$3<$C$94,0,IF(W$3<=$C$94+GPU_life-1,1,0)) -> 0
A105: flag | D105: =--(D104>0) -> 0 | E105: =--(E104>0) -> 0 | F105: =--(F104>0) -> 0 | G105: =--(G104>0) -> 0 | H105: =--(H104>0) -> 0 | I105: =--(I104>0) -> 1 | J105: =--(J104>0) -> 1 | K105: =--(K104>0) -> 1 | ... W105: =--(W104>0) -> 0
A106: occupancy | D106: =D105*(1-(1-Ramp_yr1)*((D$3-$C$94)=0)-(1-Ramp_yr2)*((D$3-$C$94)=1)) -> 0 | E106: =E105*(1-(1-Ramp_yr1)*((E$3-$C$94)=0)-(1-Ramp_yr2)*((E$3-$C$94)=1)) -> 0 | F106: =F105*(1-(1-Ramp_yr1)*((F$3-$C$94)=0)-(1-Ramp_yr2)*((F$3-$C$94)=1)) -> 0 | G106: =G105*(1-(1-Ramp_yr1)*((G$3-$C$94)=0)-(1-Ramp_yr2)*((G$3-$C$94)=1)) -> 0 | H106: =H105*(1-(1-Ramp_yr1)*((H$3-$C$94)=0)-(1-Ramp_yr2)*((H$3-$C$94)=1)) -> 0 | I106: =I105*(1-(1-Ramp_yr1)*((I$3-$C$94)=0)-(1-Ramp_yr2)*((I$3-$C$94)=1)) -> 0.65 | J106: =J105*(1-(1-Ramp_yr1)*((J$3-$C$94)=0)-(1-Ramp_yr2)*((J$3-$C$94)=1)) -> 0.85 | K106: =K105*(1-(1-Ramp_yr1)*((K$3-$C$94)=0)-(1-Ramp_yr2)*((K$3-$C$94)=1)) -> 1 | ... W106: =W105*(1-(1-Ramp_yr1)*((W$3-$C$94)=0)-(1-Ramp_yr2)*((W$3-$C$94)=1)) -> 0
A107: price $/GPU-hr | D107: =MAX(Price_floor,Compute_P0*(1-Price_decline)^$C$115) -> 2.5 | E107: =MAX(Price_floor,Compute_P0*(1-Price_decline)^$C$115) -> 2.5 | F107: =MAX(Price_floor,Compute_P0*(1-Price_decline)^$C$115) -> 2.5 | G107: =MAX(Price_floor,Compute_P0*(1-Price_decline)^$C$115) -> 2.5 | H107: =MAX(Price_floor,Compute_P0*(1-Price_decline)^$C$115) -> 2.5 | I107: =MAX(Price_floor,Compute_P0*(1-Price_decline)^$C$115) -> 2.5 | J107: =MAX(Price_floor,Compute_P0*(1-Price_decline)^$C$115) -> 2.5 | K107: =MAX(Price_floor,Compute_P0*(1-Price_decline)^$C$115) -> 2.5 | ... W107: =MAX(Price_floor,Compute_P0*(1-Price_decline)^$C$115) -> 2.5
A108: revenue | D108: =$C$103*D107/Compute_P0*D106 -> 0 | E108: =$C$103*E107/Compute_P0*E106 -> 0 | F108: =$C$103*F107/Compute_P0*F106 -> 0 | G108: =$C$103*G107/Compute_P0*G106 -> 0 | H108: =$C$103*H107/Compute_P0*H106 -> 0 | I108: =$C$103*I107/Compute_P0*I106 -> 751.608 | J108: =$C$103*J107/Compute_P0*J106 -> 982.872 | K108: =$C$103*K107/Compute_P0*K106 -> 1156.32 | ... W108: =$C$103*W107/Compute_P0*W106 -> 0
A109: EBITDA | D109: =D108-$C$97*D106-$C$98*D105 -> 0 | E109: =E108-$C$97*E106-$C$98*E105 -> 0 | F109: =F108-$C$97*F106-$C$98*F105 -> 0 | G109: =G108-$C$97*G106-$C$98*G105 -> 0 | H109: =H108-$C$97*H106-$C$98*H105 -> 0 | I109: =I108-$C$97*I106-$C$98*I105 -> 611.04438 | J109: =J108-$C$97*J106-$C$98*J105 -> 830.28266 | K109: =K108-$C$97*K106-$C$98*K105 -> 994.71136 | ... W109: =W108-$C$97*W106-$C$98*W105 -> 0
A110: depreciation | D110: =-($C$101*Calculations!$C$15+$C$102/GPU_life)*D105 -> 0 | E110: =-($C$101*Calculations!$C$15+$C$102/GPU_life)*E105 -> 0 | F110: =-($C$101*Calculations!$C$15+$C$102/GPU_life)*F105 -> 0 | G110: =-($C$101*Calculations!$C$15+$C$102/GPU_life)*G105 -> 0 | H110: =-($C$101*Calculations!$C$15+$C$102/GPU_life)*H105 -> 0 | I110: =-($C$101*Calculations!$C$15+$C$102/GPU_life)*I105 -> -616.34667 | J110: =-($C$101*Calculations!$C$15+$C$102/GPU_life)*J105 -> -616.34667 | K110: =-($C$101*Calculations!$C$15+$C$102/GPU_life)*K105 -> -616.34667 | ... W110: =-($C$101*Calculations!$C$15+$C$102/GPU_life)*W105 -> 0
A111: tax | D111: =-$C$100*MAX(D109+D110,0) -> 0 | E111: =-$C$100*MAX(E109+E110,0) -> 0 | F111: =-$C$100*MAX(F109+F110,0) -> 0 | G111: =-$C$100*MAX(G109+G110,0) -> 0 | H111: =-$C$100*MAX(H109+H110,0) -> 0 | I111: =-$C$100*MAX(I109+I110,0) -> 0 | J111: =-$C$100*MAX(J109+J110,0) -> -44.926558 | K111: =-$C$100*MAX(K109+K110,0) -> -79.456586 | ... W111: =-$C$100*MAX(W109+W110,0) -> 0
A112: net FCF | D112: =D109+D111-$C$101*IF($C$94=0,--(D$3=0),--(D$3<=$C$94-1)/$C$94)-$C$101*Assumptions!$F$38*IF(AND(D$3>=1,D$3<=$C$94),1,0)-$C$102*(D$3=$C$94)+($C$101*Facility_salvage_pct+$C$102*GPU_salvage_pct*(1-$C$100))*(D$3=$C$94+GPU_life-1) -> -352 | E112: =E109+E111-$C$101*IF($C$94=0,--(E$3=0),--(E$3<=$C$94-1)/$C$94)-$C$101*Assumptions!$F$38*IF(AND(E$3>=1,E$3<=$C$94),1,0)-$C$102*(E$3=$C$94)+($C$101*Facility_salvage_pct+$C$102*GPU_salvage_pct*(1-$C$100))*(E$3=$C$94+GPU_life-1) -> -378.4 | F112: =F109+F111-$C$101*IF($C$94=0,--(F$3=0),--(F$3<=$C$94-1)/$C$94)-$C$101*Assumptions!$F$38*IF(AND(F$3>=1,F$3<=$C$94),1,0)-$C$102*(F$3=$C$94)+($C$101*Facility_salvage_pct+$C$102*GPU_salvage_pct*(1-$C$100))*(F$3=$C$94+GPU_life-1) -> -378.4 | G112: =G109+G111-$C$101*IF($C$94=0,--(G$3=0),--(G$3<=$C$94-1)/$C$94)-$C$101*Assumptions!$F$38*IF(AND(G$3>=1,G$3<=$C$94),1,0)-$C$102*(G$3=$C$94)+($C$101*Facility_salvage_pct+$C$102*GPU_salvage_pct*(1-$C$100))*(G$3=$C$94+GPU_life-1) -> -378.4 | H112: =H109+H111-$C$101*IF($C$94=0,--(H$3=0),--(H$3<=$C$94-1)/$C$94)-$C$101*Assumptions!$F$38*IF(AND(H$3>=1,H$3<=$C$94),1,0)-$C$102*(H$3=$C$94)+($C$101*Facility_salvage_pct+$C$102*GPU_salvage_pct*(1-$C$100))*(H$3=$C$94+GPU_life-1) -> -378.4 | I112: =I109+I111-$C$101*IF($C$94=0,--(I$3=0),--(I$3<=$C$94-1)/$C$94)-$C$101*Assumptions!$F$38*IF(AND(I$3>=1,I$3<=$C$94),1,0)-$C$102*(I$3=$C$94)+($C$101*Facility_salvage_pct+$C$102*GPU_salvage_pct*(1-$C$100))*(I$3=$C$94+GPU_life-1) -> -1935.3556 | J112: =J109+J111-$C$101*IF($C$94=0,--(J$3=0),--(J$3<=$C$94-1)/$C$94)-$C$101*Assumptions!$F$38*IF(AND(J$3>=1,J$3<=$C$94),1,0)-$C$102*(J$3=$C$94)+($C$101*Facility_salvage_pct+$C$102*GPU_salvage_pct*(1-$C$100))*(J$3=$C$94+GPU_life-1) -> 785.3561 | K112: =K109+K111-$C$101*IF($C$94=0,--(K$3=0),--(K$3<=$C$94-1)/$C$94)-$C$101*Assumptions!$F$38*IF(AND(K$3>=1,K$3<=$C$94),1,0)-$C$102*(K$3=$C$94)+($C$101*Facility_salvage_pct+$C$102*GPU_salvage_pct*(1-$C$100))*(K$3=$C$94+GPU_life-1) -> 915.25477 | ... W112: =W109+W111-$C$101*IF($C$94=0,--(W$3=0),--(W$3<=$C$94-1)/$C$94)-$C$101*Assumptions!$F$38*IF(AND(W$3>=1,W$3<=$C$94),1,0)-$C$102*(W$3=$C$94)+($C$101*Facility_salvage_pct+$C$102*GPU_salvage_pct*(1-$C$100))*(W$3=$C$94+GPU_life-1) -> 0
A113: discounted FCF | D113: =D112*$C$96^D$3 -> -352 | E113: =E112*$C$96^E$3 -> -355.83976 | F113: =F112*$C$96^F$3 -> -334.62456 | G113: =G112*$C$96^G$3 -> -314.67422 | H113: =H112*$C$96^H$3 -> -295.91331 | I113: =I112*$C$96^I$3 -> -1423.2379 | J113: =J112*$C$96^J$3 -> 543.10861 | K113: =K112*$C$96^K$3 -> 595.20341 | ... W113: =W112*$C$96^W$3 -> 0
A114: op-margin PV term | D114: =(D108-$C$97*D106)*(1-$C$100)*$C$96^D$3 -> 0 | E114: =(E108-$C$97*E106)*(1-$C$100)*$C$96^E$3 -> 0 | F114: =(F108-$C$97*F106)*(1-$C$100)*$C$96^F$3 -> 0 | G114: =(G108-$C$97*G106)*(1-$C$100)*$C$96^G$3 -> 0 | H114: =(H108-$C$97*H106)*(1-$C$100)*$C$96^H$3 -> 0 | I114: =(I108-$C$97*I106)*(1-$C$100)*$C$96^I$3 -> 413.94586 | J114: =(J108-$C$97*J106)*(1-$C$100)*$C$96^J$3 -> 509.04064 | K114: =(K108-$C$97*K106)*(1-$C$100)*$C$96^K$3 -> 563.16658 | ... W114: =(W108-$C$97*W106)*(1-$C$100)*$C$96^W$3 -> 0
A115: active TTP (raw) | C115: =INDEX(Assumptions!$F$50:$H$54,$C$99,MATCH(Assumptions!$B$4,Assumptions!$D$9:$F$9,0)) -> 4.5
A116: NPV ($m) | C116: =SUM(D113:W113) -> -281.96077
A117: Op-margin PV | C117: =SUM(D114:W114) -> 2513.7599
A118: Break-even utilization | C118: =IF(C117<=0,"n/a",IF(Assumptions!$C$45*(1-C116/C117)>1,">100% (never)",Assumptions!$C$45*(1-C116/C117))) -> 0.97870691
A137: ── United States · Merchant ── | B137: United States
A138: Ops start S (yr) | C138: =ROUND($C$159,0) -> 5
A139: WACC (incl deal) | C139: =INDEX(Assumptions!$I$50:$K$54,$C$143,MATCH(Assumptions!$B$4,Assumptions!$D$9:$F$9,0))+Assumptions!$D$46 -> 0.1084
A140: Discount base v | C140: =1/(1+$C$139) -> 0.90220137
A141: Power cost (full occ) $m | C141: =IT_load_MW*INDEX(Assumptions!$M$50:$M$54,$C$143,1)*Hours_per_year*INDEX(Assumptions!$C$50:$E$54,$C$143,MATCH(Assumptions!$B$4,Assumptions!$D$9:$F$9,0))*Assumptions!$D$45/Unit_scale -> 47.8296
A142: Opex $m | C142: =IT_load_MW*OM_fixed+Insurance_rate*Calculations!$C$6+INDEX(Assumptions!$O$50:$O$54,$C$143,1)*($C$145+Calculations!$C$6)*(1-Prop_tax_abatement) -> 101.48
A143: country row index | C143: =MATCH($B$137,Assumptions!$B$50:$B$54,0) -> 2
A144: Tax rate | C144: =INDEX(Assumptions!$L$50:$L$54,MATCH($B$137,Assumptions!$B$50:$B$54,0),1) -> 0.21
A145: Facility capex $m | C145: =IT_load_MW*(Facility_capex_MW+INDEX(Assumptions!$N$50:$N$54,$C$143,1)) -> 1760
A146: GPU capex $m | C146: =Calculations!$C$6 -> 2520
A147: Year-1 full revenue $m | C147: =IT_load_MW*Assumptions!$G$12*Hours_per_year*Assumptions!$D$45/Unit_scale*Compute_P0 -> 2097.144
A148: operating flag | D148: =IF(D$3<$C$138,0,IF(D$3<=$C$138+GPU_life-1,1,0)) -> 0 | E148: =IF(E$3<$C$138,0,IF(E$3<=$C$138+GPU_life-1,1,0)) -> 0 | F148: =IF(F$3<$C$138,0,IF(F$3<=$C$138+GPU_life-1,1,0)) -> 0 | G148: =IF(G$3<$C$138,0,IF(G$3<=$C$138+GPU_life-1,1,0)) -> 0 | H148: =IF(H$3<$C$138,0,IF(H$3<=$C$138+GPU_life-1,1,0)) -> 0 | I148: =IF(I$3<$C$138,0,IF(I$3<=$C$138+GPU_life-1,1,0)) -> 1 | J148: =IF(J$3<$C$138,0,IF(J$3<=$C$138+GPU_life-1,1,0)) -> 1 | K148: =IF(K$3<$C$138,0,IF(K$3<=$C$138+GPU_life-1,1,0)) -> 1 | ... W148: =IF(W$3<$C$138,0,IF(W$3<=$C$138+GPU_life-1,1,0)) -> 0
A149: flag | D149: =--(D148>0) -> 0 | E149: =--(E148>0) -> 0 | F149: =--(F148>0) -> 0 | G149: =--(G148>0) -> 0 | H149: =--(H148>0) -> 0 | I149: =--(I148>0) -> 1 | J149: =--(J148>0) -> 1 | K149: =--(K148>0) -> 1 | ... W149: =--(W148>0) -> 0
A150: occupancy | D150: =D149*(1-(1-Ramp_yr1)*((D$3-$C$138)=0)-(1-Ramp_yr2)*((D$3-$C$138)=1)) -> 0 | E150: =E149*(1-(1-Ramp_yr1)*((E$3-$C$138)=0)-(1-Ramp_yr2)*((E$3-$C$138)=1)) -> 0 | F150: =F149*(1-(1-Ramp_yr1)*((F$3-$C$138)=0)-(1-Ramp_yr2)*((F$3-$C$138)=1)) -> 0 | G150: =G149*(1-(1-Ramp_yr1)*((G$3-$C$138)=0)-(1-Ramp_yr2)*((G$3-$C$138)=1)) -> 0 | H150: =H149*(1-(1-Ramp_yr1)*((H$3-$C$138)=0)-(1-Ramp_yr2)*((H$3-$C$138)=1)) -> 0 | I150: =I149*(1-(1-Ramp_yr1)*((I$3-$C$138)=0)-(1-Ramp_yr2)*((I$3-$C$138)=1)) -> 0.65 | J150: =J149*(1-(1-Ramp_yr1)*((J$3-$C$138)=0)-(1-Ramp_yr2)*((J$3-$C$138)=1)) -> 0.85 | K150: =K149*(1-(1-Ramp_yr1)*((K$3-$C$138)=0)-(1-Ramp_yr2)*((K$3-$C$138)=1)) -> 1 | ... W150: =W149*(1-(1-Ramp_yr1)*((W$3-$C$138)=0)-(1-Ramp_yr2)*((W$3-$C$138)=1)) -> 0
A151: price $/GPU-hr | D151: =MAX(Price_floor,Compute_P0*(1-Price_decline)^MAX($C$159+D$3-$C$138)) -> 6.3727937 | E151: =MAX(Price_floor,Compute_P0*(1-Price_decline)^MAX($C$159+E$3-$C$138)) -> 5.098235 | F151: =MAX(Price_floor,Compute_P0*(1-Price_decline)^MAX($C$159+F$3-$C$138)) -> 4.078588 | G151: =MAX(Price_floor,Compute_P0*(1-Price_decline)^MAX($C$159+G$3-$C$138)) -> 3.2628704 | H151: =MAX(Price_floor,Compute_P0*(1-Price_decline)^MAX($C$159+H$3-$C$138)) -> 2.6102963 | I151: =MAX(Price_floor,Compute_P0*(1-Price_decline)^MAX($C$159+I$3-$C$138)) -> 2.5 | J151: =MAX(Price_floor,Compute_P0*(1-Price_decline)^MAX($C$159+J$3-$C$138)) -> 2.5 | K151: =MAX(Price_floor,Compute_P0*(1-Price_decline)^MAX($C$159+K$3-$C$138)) -> 2.5 | ... W151: =MAX(Price_floor,Compute_P0*(1-Price_decline)^MAX($C$159+W$3-$C$138)) -> 2.5
A152: revenue | D152: =$C$147*D151/Compute_P0*D150 -> 0 | E152: =$C$147*E151/Compute_P0*E150 -> 0 | F152: =$C$147*F151/Compute_P0*F150 -> 0 | G152: =$C$147*G151/Compute_P0*G150 -> 0 | H152: =$C$147*H151/Compute_P0*H150 -> 0 | I152: =$C$147*I151/Compute_P0*I150 -> 597.87 | J152: =$C$147*J151/Compute_P0*J150 -> 781.83 | K152: =$C$147*K151/Compute_P0*K150 -> 919.8 | ... W152: =$C$147*W151/Compute_P0*W150 -> 0
A153: EBITDA | D153: =D152-$C$141*D150-$C$142*D149 -> 0 | E153: =E152-$C$141*E150-$C$142*E149 -> 0 | F153: =F152-$C$141*F150-$C$142*F149 -> 0 | G153: =G152-$C$141*G150-$C$142*G149 -> 0 | H153: =H152-$C$141*H150-$C$142*H149 -> 0 | I153: =I152-$C$141*I150-$C$142*I149 -> 465.30076 | J153: =J152-$C$141*J150-$C$142*J149 -> 639.69484 | K153: =K152-$C$141*K150-$C$142*K149 -> 770.4904 | ... W153: =W152-$C$141*W150-$C$142*W149 -> 0
A154: depreciation | D154: =-($C$145*Calculations!$C$15+$C$146/GPU_life)*D149 -> 0 | E154: =-($C$145*Calculations!$C$15+$C$146/GPU_life)*E149 -> 0 | F154: =-($C$145*Calculations!$C$15+$C$146/GPU_life)*F149 -> 0 | G154: =-($C$145*Calculations!$C$15+$C$146/GPU_life)*G149 -> 0 | H154: =-($C$145*Calculations!$C$15+$C$146/GPU_life)*H149 -> 0 | I154: =-($C$145*Calculations!$C$15+$C$146/GPU_life)*I149 -> -616.34667 | J154: =-($C$145*Calculations!$C$15+$C$146/GPU_life)*J149 -> -616.34667 | K154: =-($C$145*Calculations!$C$15+$C$146/GPU_life)*K149 -> -616.34667 | ... W154: =-($C$145*Calculations!$C$15+$C$146/GPU_life)*W149 -> 0
A155: tax | D155: =-$C$144*MAX(D153+D154,0) -> 0 | E155: =-$C$144*MAX(E153+E154,0) -> 0 | F155: =-$C$144*MAX(F153+F154,0) -> 0 | G155: =-$C$144*MAX(G153+G154,0) -> 0 | H155: =-$C$144*MAX(H153+H154,0) -> 0 | I155: =-$C$144*MAX(I153+I154,0) -> 0 | J155: =-$C$144*MAX(J153+J154,0) -> -4.9031164 | K155: =-$C$144*MAX(K153+K154,0) -> -32.370184 | ... W155: =-$C$144*MAX(W153+W154,0) -> 0
...

Sheet Price Floor
A1: Compute-Price Floor — full-cost derivation & external validation | C1: =IF(Checks!$C$4>0,"MODEL IN ERROR","checks OK") -> checks OK
A2: Model-generated: the break-even rental rate ($/GPU-hr at which each country reaches NPV=0), built from its own cost stack (capex, power, O&M, WACC, tax). The floor = the low-cost producer (Norway/Saudi). Cross-checked against the Silicon Data B200 index. Diagnostic — does not feed the engine.
B4: Cost stack & full-cost break-even (this scenario)
C5: =Comparison!C6 -> Norway | D5: =Comparison!D6 -> United States | E5: =Comparison!E6 -> India | F5: =Comparison!F6 -> Ireland | G5: =Comparison!G6 -> Saudi Arabia
B6: Cost of capital — unlevered hurdle rate (incl. deal) | C6: =Comparison!C10 -> 0.0634 | D6: =Comparison!D10 -> 0.0634 | E6: =Comparison!E10 -> 0.0784 | F6: =Comparison!F10 -> 0.0684 | G6: =Comparison!G10 -> 0.0684
B7: Corporate tax | C7: =Comparison!C11 -> 0.22 | D7: =Comparison!D11 -> 0.21 | E7: =Comparison!E11 -> 0.25 | F7: =Comparison!F11 -> 0.125 | G7: =Comparison!G11 -> 0.2
B8: Ops-start S (yr) | C8: =Comparison!C16 -> 2 | D8: =Comparison!D16 -> 5 | E8: =Comparison!E16 -> 3 | F8: =Comparison!F16 -> 6 | G8: =Comparison!G16 -> 2
B9: Entry price P_e ($/GPU-hr) | C9: =Comparison!C17 -> 3.648 | D9: =Comparison!D17 -> 2.5 | E9: =Comparison!E17 -> 2.9184 | F9: =Comparison!F17 -> 2.5 | G9: =Comparison!G17 -> 3.648
B10: Revenue at entry ($m/yr, full occ) | C10: =Comparison!C18 -> 1687.3021 | D10: =Comparison!D18 -> 1156.32 | E10: =Comparison!E18 -> 1349.8417 | F10: =Comparison!F18 -> 1156.32 | G10: =Comparison!G18 -> 1687.3021
B11: Facility capex ($m) | C11: =Comparison!C21 -> 1740 | D11: =Comparison!D21 -> 1760 | E11: =Comparison!E21 -> 1750 | F11: =Comparison!F21 -> 1780 | G11: =Comparison!G21 -> 1730
B12: GPU capex ($m) | C12: =Comparison!C20 -> 2520 | D12: =Comparison!D20 -> 2520 | E12: =Comparison!E20 -> 2520 | F12: =Comparison!F20 -> 2520 | G12: =Comparison!G20 -> 2520
B13: Power ($m/yr) | C13: =Comparison!C19 -> 46.098624 | D13: =Comparison!D19 -> 60.12864 | E13: =Comparison!E19 -> 109.8504 | F13: =Comparison!F19 -> 138.7584 | G13: =Comparison!G19 -> 53.653248
B14: Opex — O&M+ins+tax ($m/yr) | C14: =Comparison!C22 -> 86.47 | D14: =Comparison!D22 -> 101.48 | E14: =Comparison!E22 -> 90.755 | F14: =Comparison!F22 -> 82.23 | G14: =Comparison!G22 -> 81.1425
B15: NPV at entry price ($m) | C15: =Comparison!C38 -> 1448.0114 | D15: =Comparison!D38 -> -281.96077 | E15: =Comparison!E38 -> 12.417256 | F15: =Comparison!F38 -> -460.96698 | G15: =Comparison!G38 -> 1428.7514
B16: Discount factor v = 1/(1+WACC) | C16: =1/(1+C6) -> 0.94037991 | D16: =1/(1+D6) -> 0.94037991 | E16: =1/(1+E6) -> 0.9272997 | F16: =1/(1+F6) -> 0.93597903 | G16: =1/(1+G6) -> 0.93597903
B17: Hold annuity A = v^(S+1)(1−v^L)/(1−v) | C17: =C16^(C8)*(1-C16^GPU_life)/(1-C16) -> 3.9248505 | D17: =D16^(D8)*(1-D16^GPU_life)/(1-D16) -> 3.2638722 | E17: =E16^(E8)*(1-E16^GPU_life)/(1-E16) -> 3.4477974 | F17: =F16^(F8)*(1-F16^GPU_life)/(1-F16) -> 2.9580007 | G17: =G16^(G8)*(1-G16^GPU_life)/(1-G16) -> 3.8541959
B18: Ramp-adj revenue annuity | C18: =C17-(1-Ramp_yr1)*C16^(C8)-(1-Ramp_yr2)*C16^(C8+1) -> 3.4906017 | D18: =D17-(1-Ramp_yr1)*D16^(D8)-(1-Ramp_yr2)*D16^(D8+1) -> 2.9027547 | E18: =E17-(1-Ramp_yr1)*E16^(E8)-(1-Ramp_yr2)*E16^(E8+1) -> 3.0578073 | F18: =F17-(1-Ramp_yr1)*F16^(F8)-(1-Ramp_yr2)*F16^(F8+1) -> 2.6282813 | G18: =G17-(1-Ramp_yr1)*G16^(G8)-(1-Ramp_yr2)*G16^(G8+1) -> 3.4245804
B19: Revenue PV after-tax ($m) | C19: =C10*C18*(1-C7) -> 4593.9658 | D19: =D10*D18*(1-D7) -> 2651.6455 | E19: =E10*E18*(1-E7) -> 3095.6669 | F19: =F10*F18*(1-F7) -> 2659.2425 | G19: =G10*G18*(1-G7) -> 4622.6415
B20: BREAK-EVEN rental rate ($/GPU-hr) [NPV=0] | C20: =C9*(1-C15/C19) -> 2.4981557 | D20: =D9*(1-D15/D19) -> 2.7658357 | E20: =E9*(1-E15/E19) -> 2.9066938 | F20: =F9*(1-F15/F19) -> 2.9333631 | G20: =G9*(1-G15/G19) -> 2.5204877
B22: MODEL FULL-COST FLOOR = low-cost producer (min of Norway, Saudi) | C22: =MIN(C20,G20) -> 2.4981557
B24: External validation — B200 observed committed-floor band (Silicon Data SDB200RT)
B25: B200 committed-floor band — low (SDB200RT) | C25: =Floor_ext_low -> 2.5
B26: B200 committed-floor band — high (SDB200RT) | C26: =Floor_ext_high -> 3
B28: Reconciliation
B29: Floor input, Base case (Assumptions) | C29: =Assumptions!$E$66 -> 2.5
B30: Model full-cost floor (this scenario) | C30: =C22 -> 2.4981557
B31: Internal-consistency flag (0=ok; |Base floor − model floor|, enforced at Base·Contracted) | C31: =IF(AND(Assumptions!$B$4="Base",Assumptions!$B$7="Contracted"),--(ABS(Assumptions!$G$66-C22)>FloorTolerance),0) -> 0
B32: External-coherence flag (0=ok: band-low ≤ model floor ≤ band-high) | C32: =--NOT(AND(C25<=Assumptions!$E$66,Assumptions!$E$66<=C26)) -> 0
B34: Note: the full-cost floor is a Base-case central anchor ($2.50), cost-derived and inside the B200 observed committed-floor band ($2.50–3.00). The H100 completed cycle ($1.70 trough → $2.35 rebound) is the mean-reversion analog. Break-even is a linear (taxable>0) approximation — exact for the profitable low-cost producers that set the floor.
B35: Sources: Silicon Data SDB200RT (B200 index, grade High); Silicon Analysts / neocloud cost decomposition (Med); H100 lifecycle analog $1.70→$2.35 (mean-reversion). Vintage 2026.

Sheet ▸ OUTPUTS
A1: ▸ OUTPUTS

Sheet Comparison
A1: Comparison — five-country infrastructure-cost ranking under COMMON revenue & lawful-chip-access assumptions. CONDITIONAL: results depend on lawful Blackwell/B200 access (export-controlled for some destinations), single-point time-to-power estimates, and projected ~20%/yr price erosion toward the full-cost floor — see Limitations before citing any rank. | C1: =IF(Checks!$C$4>0,"MODEL IN ERROR","checks OK") -> checks OK
A2: Every country computed identically; none is the base. Scenario set on Assumptions; applies to all. Blue = country lever linked in; black = calculation; red = headline output. Drill on Calculations / Country detail.
A4: Scenario (set on Assumptions) | B4: =Assumptions!$B$4 -> Base | D4: Workbook status | E4: =IF(Checks!$C$4>0,"MODEL IN ERROR","checks OK") -> checks OK
A6: Metric | C6: Norway | D6: United States | E6: India | F6: Ireland | G6: Saudi Arabia
A7: Country-varying levers (this scenario)
B8: Delivered power ($/MWh) | C8: =INDEX(Assumptions!$C$50:$E$54,MATCH(C$6,Assumptions!$B$50:$B$54,0),MATCH($B$4,Assumptions!$D$9:$F$9,0)) -> 52 | D8: =INDEX(Assumptions!$C$50:$E$54,MATCH(D$6,Assumptions!$B$50:$B$54,0),MATCH($B$4,Assumptions!$D$9:$F$9,0)) -> 60 | E8: =INDEX(Assumptions!$C$50:$E$54,MATCH(E$6,Assumptions!$B$50:$B$54,0),MATCH($B$4,Assumptions!$D$9:$F$9,0)) -> 95 | F8: =INDEX(Assumptions!$C$50:$E$54,MATCH(F$6,Assumptions!$B$50:$B$54,0),MATCH($B$4,Assumptions!$D$9:$F$9,0)) -> 150 | G8: =INDEX(Assumptions!$C$50:$E$54,MATCH(G$6,Assumptions!$B$50:$B$54,0),MATCH($B$4,Assumptions!$D$9:$F$9,0)) -> 48
B9: Time-to-power (yr) | C9: =INDEX(Assumptions!$F$50:$H$54,MATCH(C$6,Assumptions!$B$50:$B$54,0),MATCH($B$4,Assumptions!$D$9:$F$9,0)) -> 2 | D9: =INDEX(Assumptions!$F$50:$H$54,MATCH(D$6,Assumptions!$B$50:$B$54,0),MATCH($B$4,Assumptions!$D$9:$F$9,0)) -> 4.5 | E9: =INDEX(Assumptions!$F$50:$H$54,MATCH(E$6,Assumptions!$B$50:$B$54,0),MATCH($B$4,Assumptions!$D$9:$F$9,0)) -> 3 | F9: =INDEX(Assumptions!$F$50:$H$54,MATCH(F$6,Assumptions!$B$50:$B$54,0),MATCH($B$4,Assumptions!$D$9:$F$9,0)) -> 6 | G9: =INDEX(Assumptions!$F$50:$H$54,MATCH(G$6,Assumptions!$B$50:$B$54,0),MATCH($B$4,Assumptions!$D$9:$F$9,0)) -> 2
B10: Cost of capital — unlevered hurdle rate (incl. deal premium) | C10: =INDEX(Assumptions!$I$50:$K$54,MATCH(C$6,Assumptions!$B$50:$B$54,0),MATCH($B$4,Assumptions!$D$9:$F$9,0))+Deal_WACC_premium -> 0.0634 | D10: =INDEX(Assumptions!$I$50:$K$54,MATCH(D$6,Assumptions!$B$50:$B$54,0),MATCH($B$4,Assumptions!$D$9:$F$9,0))+Deal_WACC_premium -> 0.0634 | E10: =INDEX(Assumptions!$I$50:$K$54,MATCH(E$6,Assumptions!$B$50:$B$54,0),MATCH($B$4,Assumptions!$D$9:$F$9,0))+Deal_WACC_premium -> 0.0784 | F10: =INDEX(Assumptions!$I$50:$K$54,MATCH(F$6,Assumptions!$B$50:$B$54,0),MATCH($B$4,Assumptions!$D$9:$F$9,0))+Deal_WACC_premium -> 0.0684 | G10: =INDEX(Assumptions!$I$50:$K$54,MATCH(G$6,Assumptions!$B$50:$B$54,0),MATCH($B$4,Assumptions!$D$9:$F$9,0))+Deal_WACC_premium -> 0.0684
B11: Corporate tax | C11: =INDEX(Assumptions!$L$50:$L$54,MATCH(C$6,Assumptions!$B$50:$B$54,0),1) -> 0.22 | D11: =INDEX(Assumptions!$L$50:$L$54,MATCH(D$6,Assumptions!$B$50:$B$54,0),1) -> 0.21 | E11: =INDEX(Assumptions!$L$50:$L$54,MATCH(E$6,Assumptions!$B$50:$B$54,0),1) -> 0.25 | F11: =INDEX(Assumptions!$L$50:$L$54,MATCH(F$6,Assumptions!$B$50:$B$54,0),1) -> 0.125 | G11: =INDEX(Assumptions!$L$50:$L$54,MATCH(G$6,Assumptions!$B$50:$B$54,0),1) -> 0.2
B12: PUE (per unit efficiency) | C12: =INDEX(Assumptions!$M$50:$M$54,MATCH(C$6,Assumptions!$B$50:$B$54,0),1) -> 1.15 | D12: =INDEX(Assumptions!$M$50:$M$54,MATCH(D$6,Assumptions!$B$50:$B$54,0),1) -> 1.3 | E12: =INDEX(Assumptions!$M$50:$M$54,MATCH(E$6,Assumptions!$B$50:$B$54,0),1) -> 1.5 | F12: =INDEX(Assumptions!$M$50:$M$54,MATCH(F$6,Assumptions!$B$50:$B$54,0),1) -> 1.2 | G12: =INDEX(Assumptions!$M$50:$M$54,MATCH(G$6,Assumptions!$B$50:$B$54,0),1) -> 1.45
B13: Interconnection ($m/MW) | C13: =INDEX(Assumptions!$N$50:$N$54,MATCH(C$6,Assumptions!$B$50:$B$54,0),1) -> 0.4 | D13: =INDEX(Assumptions!$N$50:$N$54,MATCH(D$6,Assumptions!$B$50:$B$54,0),1) -> 0.6 | E13: =INDEX(Assumptions!$N$50:$N$54,MATCH(E$6,Assumptions!$B$50:$B$54,0),1) -> 0.5 | F13: =INDEX(Assumptions!$N$50:$N$54,MATCH(F$6,Assumptions!$B$50:$B$54,0),1) -> 0.8 | G13: =INDEX(Assumptions!$N$50:$N$54,MATCH(G$6,Assumptions!$B$50:$B$54,0),1) -> 0.3
B14: Property tax rate (%/yr, pre-abate) | C14: =INDEX(Assumptions!$O$50:$O$54,MATCH(C$6,Assumptions!$B$50:$B$54,0),1) -> 0.003 | D14: =INDEX(Assumptions!$O$50:$O$54,MATCH(D$6,Assumptions!$B$50:$B$54,0),1) -> 0.01 | E14: =INDEX(Assumptions!$O$50:$O$54,MATCH(E$6,Assumptions!$B$50:$B$54,0),1) -> 0.005 | F14: =INDEX(Assumptions!$O$50:$O$54,MATCH(F$6,Assumptions!$B$50:$B$54,0),1) -> 0.001 | G14: =INDEX(Assumptions!$O$50:$O$54,MATCH(G$6,Assumptions!$B$50:$B$54,0),1) -> 0.0005
A15: Economics (per country; entry-price basis). NPV/BE come from the per-period Country Engine — these rows are descriptive.
B16: Ops start S (period) = ROUND(TTP) | C16: =ROUND(C9,0) -> 2 | D16: =ROUND(D9,0) -> 5 | E16: =ROUND(E9,0) -> 3 | F16: =ROUND(F9,0) -> 6 | G16: =ROUND(G9,0) -> 2
B17: Entry price P_e ($/GPU-hr) = P0·(1−d)^TTP | C17: =MAX(Price_floor,Compute_P0*(1-Price_decline)^C9) -> 3.648 | D17: =MAX(Price_floor,Compute_P0*(1-Price_decline)^D9) -> 2.5 | E17: =MAX(Price_floor,Compute_P0*(1-Price_decline)^E9) -> 2.9184 | F17: =MAX(Price_floor,Compute_P0*(1-Price_decline)^F9) -> 2.5 | G17: =MAX(Price_floor,Compute_P0*(1-Price_decline)^G9) -> 3.648
B18: Revenue at entry (level, full occ, $m) | C18: =Calculations!$C$9*C17/Compute_P0 -> 1687.3021 | D18: =Calculations!$C$9*D17/Compute_P0 -> 1156.32 | E18: =Calculations!$C$9*E17/Compute_P0 -> 1349.8417 | F18: =Calculations!$C$9*F17/Compute_P0 -> 1156.32 | G18: =Calculations!$C$9*G17/Compute_P0 -> 1687.3021
B19: Power cost ($m) | C19: =IT_load_MW*C12*Hours_per_year*C8*Paid_occupancy/Unit_scale -> 46.098624 | D19: =IT_load_MW*D12*Hours_per_year*D8*Paid_occupancy/Unit_scale -> 60.12864 | E19: =IT_load_MW*E12*Hours_per_year*E8*Paid_occupancy/Unit_scale -> 109.8504 | F19: =IT_load_MW*F12*Hours_per_year*F8*Paid_occupancy/Unit_scale -> 138.7584 | G19: =IT_load_MW*G12*Hours_per_year*G8*Paid_occupancy/Unit_scale -> 53.653248
B20: GPU capex ($m) — country-invariant | C20: =Calculations!$C$6 -> 2520 | D20: =Calculations!$C$6 -> 2520 | E20: =Calculations!$C$6 -> 2520 | F20: =Calculations!$C$6 -> 2520 | G20: =Calculations!$C$6 -> 2520
B21: Facility capex incl. interconnect ($m) | C21: =IT_load_MW*(Facility_capex_MW+C13) -> 1740 | D21: =IT_load_MW*(Facility_capex_MW+D13) -> 1760 | E21: =IT_load_MW*(Facility_capex_MW+E13) -> 1750 | F21: =IT_load_MW*(Facility_capex_MW+F13) -> 1780 | G21: =IT_load_MW*(Facility_capex_MW+G13) -> 1730
B22: Opex — O&M+ins+prop tax ($m) | C22: =IT_load_MW*OM_fixed+Insurance_rate*C20+C14*(C21+C20)*(1-Prop_tax_abatement) -> 86.47 | D22: =IT_load_MW*OM_fixed+Insurance_rate*D20+D14*(D21+D20)*(1-Prop_tax_abatement) -> 101.48 | E22: =IT_load_MW*OM_fixed+Insurance_rate*E20+E14*(E21+E20)*(1-Prop_tax_abatement) -> 90.755 | F22: =IT_load_MW*OM_fixed+Insurance_rate*F20+F14*(F21+F20)*(1-Prop_tax_abatement) -> 82.23 | G22: =IT_load_MW*OM_fixed+Insurance_rate*G20+G14*(G21+G20)*(1-Prop_tax_abatement) -> 81.1425
B23: EBITDA at entry ($m) | C23: =C18-C19-C22 -> 1554.7335 | D23: =D18-D19-D22 -> 994.71136 | E23: =E18-E19-E22 -> 1149.2363 | F23: =F18-F19-F22 -> 935.3316 | G23: =G18-G19-G22 -> 1552.5064
B24: Total capex (facility + GPU) ($m) | C24: =C20+C21 -> 4260 | D24: =D20+D21 -> 4280 | E24: =E20+E21 -> 4270 | F24: =F20+F21 -> 4300 | G24: =G20+G21 -> 4250
B25: Effective energy burden ($/MWh) = PUE × price | C25: =C8*C12 -> 59.8 | D25: =D8*D12 -> 78 | E25: =E8*E12 -> 142.5 | F25: =F8*F12 -> 180 | G25: =G8*G12 -> 69.6
A37: Results — from the per-period Country Engine (active deal). ▲ INDICATIVE / DIRECTIONAL: NPVs are for cross-country RANKING, not bankable valuations. Also CONDITIONAL on lawful Blackwell access (US/NO/IE unrestricted; Saudi/India licensed/conditional — see Limitations #7). See the Limitations tab.
B38: NPV ($m) — per-period (Country Engine) | C38: =INDEX('Country Engine'!$E$671:$E$675,MATCH(C$6,'Country Engine'!$A$671:$A$675,0)) -> 1448.0114 | D38: =INDEX('Country Engine'!$E$671:$E$675,MATCH(D$6,'Country Engine'!$A$671:$A$675,0)) -> -281.96077 | E38: =INDEX('Country Engine'!$E$671:$E$675,MATCH(E$6,'Country Engine'!$A$671:$A$675,0)) -> 12.417256 | F38: =INDEX('Country Engine'!$E$671:$E$675,MATCH(F$6,'Country Engine'!$A$671:$A$675,0)) -> -460.96698 | G38: =INDEX('Country Engine'!$E$671:$E$675,MATCH(G$6,'Country Engine'!$A$671:$A$675,0)) -> 1428.7514
B39: Break-even utilization | C39: =INDEX('Country Engine'!$F$671:$F$675,MATCH(C$6,'Country Engine'!$A$671:$A$675,0)) -> 0.59483429 | D39: =INDEX('Country Engine'!$F$671:$F$675,MATCH(D$6,'Country Engine'!$A$671:$A$675,0)) -> 0.97870691 | E39: =INDEX('Country Engine'!$F$671:$F$675,MATCH(E$6,'Country Engine'!$A$671:$A$675,0)) -> 0.87615746 | F39: =INDEX('Country Engine'!$F$671:$F$675,MATCH(F$6,'Country Engine'!$A$671:$A$675,0)) -> >100% (never) | G39: =INDEX('Country Engine'!$F$671:$F$675,MATCH(G$6,'Country Engine'!$A$671:$A$675,0)) -> 0.59907962
B40: Rank by NPV (this scenario)* | C40: =RANK(C38,$C$38:$G$38,0) -> 1 | D40: =RANK(D38,$C$38:$G$38,0) -> 4 | E40: =RANK(E38,$C$38:$G$38,0) -> 3 | F40: =RANK(F38,$C$38:$G$38,0) -> 5 | G40: =RANK(G38,$C$38:$G$38,0) -> 2 | H40: =IF(Assumptions!$B$4="Bear","◄ Ireland rank overstated — excludes CRU policy cost (see Limitations)","")
B41: Profitability index (1 + NPV/capital) | C41: =1+C38/C24 -> 1.3399088 | D41: =1+D38/D24 -> 0.93412132 | E41: =1+E38/E24 -> 1.002908 | F41: =1+F38/F24 -> 0.89279838 | G41: =1+G38/G24 -> 1.3361768
B42: Grid carbon intensity (gCO2/kWh) — context lens, NOT in NPV | C42: =Assumptions!$P$50 -> 28 | D42: =Assumptions!$P$51 -> 384 | E42: =Assumptions!$P$52 -> 670 | F42: =Assumptions!$P$53 -> 290 | G42: =Assumptions!$P$54 -> 590
B43: Water intensity (WUE / cooling-water) — not assessed (context lens, NOT in NPV; material in hot climates — India, Saudi) | C43: n/a | D43: n/a | E43: n/a | F43: n/a | G43: n/a
B44: * Ireland's NPV rank excludes the CRU self-generation capex & ~6-yr renewables/approval burden (CRU 2025). It doesn't change the Base/Bull result (Ireland already last), but Ireland's Bear ‘least-bad’ rank is overstated and would fall if costed — see Limitations.
B45: Carbon-adjusted view — shadow price on grid CO₂ (separate lens; excluded from the NPV & ranks above)
B46: Shadow carbon price ($/tCO₂) — set on Assumptions (context lens) | C46: =Shadow_carbon_price -> 190
B47: Annual grid energy (MWh) | C47: =IT_load_MW*C12*Hours_per_year*Paid_occupancy -> 886512 | D47: =IT_load_MW*D12*Hours_per_year*Paid_occupancy -> 1002144 | E47: =IT_load_MW*E12*Hours_per_year*Paid_occupancy -> 1156320 | F47: =IT_load_MW*F12*Hours_per_year*Paid_occupancy -> 925056 | G47: =IT_load_MW*G12*Hours_per_year*Paid_occupancy -> 1117776
B48: Annual grid CO₂ (t/yr) = MWh × intensity ÷ 1000 | C48: =C47*C42/1000 -> 24822.336 | D48: =D47*D42/1000 -> 384823.3 | E48: =E47*E42/1000 -> 774734.4 | F48: =F47*F42/1000 -> 268266.24 | G48: =G47*G42/1000 -> 659487.84
B49: Carbon cost, PV over hold ($m) = t/yr × price × annuity ÷ 1e6 | C49: =C48*Shadow_carbon_price*'Price Floor'!C18/1000000 -> 16.462529 | D49: =D48*Shadow_carbon_price*'Price Floor'!D18/1000000 -> 212.23905 | E49: =E48*Shadow_carbon_price*'Price Floor'!E18/1000000 -> 450.10782 | F49: =F48*Shadow_carbon_price*'Price Floor'!F18/1000000 -> 133.96504 | G49: =G48*Shadow_carbon_price*'Price Floor'!G18/1000000 -> 429.10914
B50: Carbon-adjusted NPV ($m) = NPV − carbon cost PV | C50: =C38-C49 -> 1431.5488 | D50: =D38-D49 -> -494.19981 | E50: =E38-E49 -> -437.69056 | F50: =F38-F49 -> -594.93202 | G50: =G38-G49 -> 999.64222
B51: Carbon-adjusted rank (this scenario) | C51: =RANK(C50,$C$50:$G$50,0) -> 1 | D51: =RANK(D50,$C$50:$G$50,0) -> 4 | E51: =RANK(E50,$C$50:$G$50,0) -> 3 | F51: =RANK(F50,$C$50:$G$50,0) -> 5 | G51: =RANK(G50,$C$50:$G$50,0) -> 2
B52: Method: grid CO₂ = IT energy × grid carbon intensity, costed at the shadow price and discounted over the operating hold using the same annuity as revenue. Illustrative — does not feed the NPV or ranks above.

Sheet Sensitivity
A1: Sensitivity — price × utilization, lease-up ramp, one-way tornado | C1: =IF(Checks!$C$4>0,"MODEL IN ERROR","checks OK") -> checks OK
A2: For the country + scenario + deal selected on Assumptions. A two-way price×utilization grid and a one-way tornado; the LIVE case reconciles to the Comparison NPV (Checks). Scenarios/deal are COHERENT states, not free sliders. Labelled analysis; does not feed the P&L. NOTE: the tornado is a closed-form approximation — exact at Base, indicative for floored/loss countries (see A53).
D3: Workbook status | E3: =IF(Checks!$C$4>0,"MODEL IN ERROR","checks OK") -> checks OK
A4: Selected-country constants — CONTRACTED entry-price basis (from Calculations). The tornado is the contracted-case sensitivity; the live case reconciles to the engine NPV.
B5: Revenue base (level, entry price, full occ) ($m) | C5: =Calculations!$C$9*MAX(Price_floor,Compute_P0*(1-Price_decline)^Assumptions!$G$23)/Compute_P0 -> 1687.3021
B6: Power cost ($m) | C6: =Calculations!$C$10 -> 46.098624
B7: Opex — O&M+ins+proptax ($m) | C7: =Calculations!$C$13 -> 86.47
B8: Deprec/yr ($m) | C8: =Calculations!$C$16 -> 615.07
B9: Tax rate | C9: =Assumptions!$G$26 -> 0.22
B10: Annuity factor (ops years) | C10: =Calculations!$C$21^(Calculations!$C$20)*(1-Calculations!$C$21^GPU_life)/(1-Calculations!$C$21) -> 3.9248505
B11: Capex PV (phased facility + GPU) ($m) | C11: =Calculations!$C$7*IF(Calculations!$C$20=0,1,(1-Calculations!$C$21^Calculations!$C$20)/(1-Calculations!$C$21)/Calculations!$C$20)+Calculations!$C$6*Calculations!$C$21^Calculations!$C$20 -> 3916.6028
B12: Holding cost PV ($m) | C12: =Calculations!$C$7*Assumptions!$F$38*Calculations!$C$21*(1-Calculations!$C$21^Calculations!$C$20)/(1-Calculations!$C$21) -> 47.624521
B13: TV PV ($m) | C13: =(Calculations!$C$7*Facility_salvage_pct+Calculations!$C$6*GPU_salvage_pct*(1-$C$9))*Calculations!$C$21^(Calculations!$C$20+GPU_life-1) -> 677.40923
B14: Base price×util (entry price × occ) | C14: =MAX(Price_floor,Compute_P0*(1-Price_decline)^Assumptions!$G$23)*Assumptions!$G$15 -> 3.21024
B15: Contracted NPV (selected, from engine) | C15: =INDEX('Country Engine'!$C$671:$C$675,MATCH(Assumptions!$B$5,'Country Engine'!$A$671:$A$675,0)) -> 1448.0114
B16: Live EBITDA ($m) | C16: =$C$5-$C$6-$C$7 -> 1554.7335
A17: Working — EBITDA ($m) at each price (cols) × utilization (rows)
C18: 3 | D18: 4 | E18: 4.5 | F18: 5.5 | G18: 7
B19: 0.6 | C19: =$C$5*(C$18*$B19)/$C$14-$C$6*($B19/Assumptions!$G$15)-$C$7 -> 828.17912 | D19: =$C$5*(D$18*$B19)/$C$14-$C$6*($B19/Assumptions!$G$15)-$C$7 -> 1143.5391 | E19: =$C$5*(E$18*$B19)/$C$14-$C$6*($B19/Assumptions!$G$15)-$C$7 -> 1301.2191 | F19: =$C$5*(F$18*$B19)/$C$14-$C$6*($B19/Assumptions!$G$15)-$C$7 -> 1616.5791 | G19: =$C$5*(G$18*$B19)/$C$14-$C$6*($B19/Assumptions!$G$15)-$C$7 -> 2089.6191
B20: 0.7 | C20: =$C$5*(C$18*$B20)/$C$14-$C$6*($B20/Assumptions!$G$15)-$C$7 -> 980.62064 | D20: =$C$5*(D$18*$B20)/$C$14-$C$6*($B20/Assumptions!$G$15)-$C$7 -> 1348.5406 | E20: =$C$5*(E$18*$B20)/$C$14-$C$6*($B20/Assumptions!$G$15)-$C$7 -> 1532.5006 | F20: =$C$5*(F$18*$B20)/$C$14-$C$6*($B20/Assumptions!$G$15)-$C$7 -> 1900.4206 | G20: =$C$5*(G$18*$B20)/$C$14-$C$6*($B20/Assumptions!$G$15)-$C$7 -> 2452.3006
B21: 0.85 | C21: =$C$5*(C$18*$B21)/$C$14-$C$6*($B21/Assumptions!$G$15)-$C$7 -> 1209.2829 | D21: =$C$5*(D$18*$B21)/$C$14-$C$6*($B21/Assumptions!$G$15)-$C$7 -> 1656.0429 | E21: =$C$5*(E$18*$B21)/$C$14-$C$6*($B21/Assumptions!$G$15)-$C$7 -> 1879.4229 | F21: =$C$5*(F$18*$B21)/$C$14-$C$6*($B21/Assumptions!$G$15)-$C$7 -> 2326.1829 | G21: =$C$5*(G$18*$B21)/$C$14-$C$6*($B21/Assumptions!$G$15)-$C$7 -> 2996.3229
B22: 0.9 | C22: =$C$5*(C$18*$B22)/$C$14-$C$6*($B22/Assumptions!$G$15)-$C$7 -> 1285.5037 | D22: =$C$5*(D$18*$B22)/$C$14-$C$6*($B22/Assumptions!$G$15)-$C$7 -> 1758.5437 | E22: =$C$5*(E$18*$B22)/$C$14-$C$6*($B22/Assumptions!$G$15)-$C$7 -> 1995.0637 | F22: =$C$5*(F$18*$B22)/$C$14-$C$6*($B22/Assumptions!$G$15)-$C$7 -> 2468.1037 | G22: =$C$5*(G$18*$B22)/$C$14-$C$6*($B22/Assumptions!$G$15)-$C$7 -> 3177.6637
B23: 0.95 | C23: =$C$5*(C$18*$B23)/$C$14-$C$6*($B23/Assumptions!$G$15)-$C$7 -> 1361.7244 | D23: =$C$5*(D$18*$B23)/$C$14-$C$6*($B23/Assumptions!$G$15)-$C$7 -> 1861.0444 | E23: =$C$5*(E$18*$B23)/$C$14-$C$6*($B23/Assumptions!$G$15)-$C$7 -> 2110.7044 | F23: =$C$5*(F$18*$B23)/$C$14-$C$6*($B23/Assumptions!$G$15)-$C$7 -> 2610.0244 | G23: =$C$5*(G$18*$B23)/$C$14-$C$6*($B23/Assumptions!$G$15)-$C$7 -> 3359.0044
A25: Two-way NPV grid ($m) — compute price (cols) × utilization (rows). A range; the live case reconciles below.
C26: 3 | D26: 4 | E26: 4.5 | F26: 5.5 | G26: 7
B27: 0.6 | C27: =-$C$11-$C$12+(C19-$C$9*MAX(C19-$C$8,0))*$C$10+$C$13 -> -220.35155 | D27: =-$C$11-$C$12+(D19-$C$9*MAX(D19-$C$8,0))*$C$10+$C$13 -> 745.08631 | E27: =-$C$11-$C$12+(E19-$C$9*MAX(E19-$C$8,0))*$C$10+$C$13 -> 1227.8052 | F27: =-$C$11-$C$12+(F19-$C$9*MAX(F19-$C$8,0))*$C$10+$C$13 -> 2193.2431 | G27: =-$C$11-$C$12+(G19-$C$9*MAX(G19-$C$8,0))*$C$10+$C$13 -> 3641.3999
B28: 0.7 | C28: =-$C$11-$C$12+(C20-$C$9*MAX(C20-$C$8,0))*$C$10+$C$13 -> 246.33038 | D28: =-$C$11-$C$12+(D20-$C$9*MAX(D20-$C$8,0))*$C$10+$C$13 -> 1372.6746 | E28: =-$C$11-$C$12+(E20-$C$9*MAX(E20-$C$8,0))*$C$10+$C$13 -> 1935.8466 | F28: =-$C$11-$C$12+(F20-$C$9*MAX(F20-$C$8,0))*$C$10+$C$13 -> 3062.1908 | G28: =-$C$11-$C$12+(G20-$C$9*MAX(G20-$C$8,0))*$C$10+$C$13 -> 4751.7071
B29: 0.85 | C29: =-$C$11-$C$12+(C21-$C$9*MAX(C21-$C$8,0))*$C$10+$C$13 -> 946.35329 | D29: =-$C$11-$C$12+(D21-$C$9*MAX(D21-$C$8,0))*$C$10+$C$13 -> 2314.0569 | E29: =-$C$11-$C$12+(E21-$C$9*MAX(E21-$C$8,0))*$C$10+$C$13 -> 2997.9087 | F29: =-$C$11-$C$12+(F21-$C$9*MAX(F21-$C$8,0))*$C$10+$C$13 -> 4365.6124 | G29: =-$C$11-$C$12+(G21-$C$9*MAX(G21-$C$8,0))*$C$10+$C$13 -> 6417.1678
B30: 0.9 | C30: =-$C$11-$C$12+(C22-$C$9*MAX(C22-$C$8,0))*$C$10+$C$13 -> 1179.6943 | D30: =-$C$11-$C$12+(D22-$C$9*MAX(D22-$C$8,0))*$C$10+$C$13 -> 2627.851 | E30: =-$C$11-$C$12+(E22-$C$9*MAX(E22-$C$8,0))*$C$10+$C$13 -> 3351.9294 | F30: =-$C$11-$C$12+(F22-$C$9*MAX(F22-$C$8,0))*$C$10+$C$13 -> 4800.0862 | G30: =-$C$11-$C$12+(G22-$C$9*MAX(G22-$C$8,0))*$C$10+$C$13 -> 6972.3214
B31: 0.95 | C31: =-$C$11-$C$12+(C23-$C$9*MAX(C23-$C$8,0))*$C$10+$C$13 -> 1413.0352 | D31: =-$C$11-$C$12+(D23-$C$9*MAX(D23-$C$8,0))*$C$10+$C$13 -> 2941.6452 | E31: =-$C$11-$C$12+(E23-$C$9*MAX(E23-$C$8,0))*$C$10+$C$13 -> 3705.9501 | F31: =-$C$11-$C$12+(F23-$C$9*MAX(F23-$C$8,0))*$C$10+$C$13 -> 5234.5601 | G31: =-$C$11-$C$12+(G23-$C$9*MAX(G23-$C$8,0))*$C$10+$C$13 -> 7527.475
A33: Lease-up ramp — Base utilization is the blended average of a lease-up path (illustrative, sourced)
C34: Yr 1 | D34: Yr 2 | E34: Yr 3 | F34: Yr 4 | G34: Yr 5
B35: Occupancy (illustrative) | C35: 0.65 | D35: 0.9 | E35: 0.9 | F35: 0.9 | G35: 0.9
B36: Blended (simple average) | C36: =AVERAGE(C35:G35) -> 0.85
B37: ~6–12mo lease-up (yr-1 ~65%) → steady state; the ~85% average is ILLUSTRATIVE (feeds nothing). Live Base occupancy is deal-driven (Assumptions G15). Sources: hyperscaler ramp tranches; CBRE colo vacancy 1.4%; CoreWeave ~74% pre-leased.
A39: Effective revenue per installed GPU-hr = price × utilization (cross-check vs neocloud)
B40: Model effective (Base P×U) | C40: =Assumptions!$G$14*Assumptions!$G$15 -> 5.016
B41: Neocloud 2025 blended (CoreWeave rev/installed GPU) | C41: ~$2–3
B42: Steady-state contracted (B200 committed ~$5.70) | C42: ~$3.8
B43: Model effective (~4.5 × 0.88 Contracted) aligns with the contracted benchmark; lower 2025 blended reflects ramp + older-gen fleet (captured by the ramp above).
B44: Live case NPV (contracted, entry price, incl. ramp, $m) | C44: =-$C$11-$C$12+($C$16-$C$9*MAX($C$16-$C$8,0))*$C$10+$C$13-($C$5-$C$6)*(1-$C$9)*Calculations!$C$21^(Calculations!$C$20)*((1-Ramp_yr1)+(1-Ramp_yr2)*Calculations!$C$21) -> 1448.0114
A45: Read / method
B46: Read the DIAGONAL: a tight market lifts BOTH price and utilization (top-right), a glut cuts BOTH (bottom-left) — those are the coherent market states. Off-diagonal corners are transient operator trade-offs, not steady states.
B48: Check: live case NPV = Comparison NPV (all scenarios/deals) | C48: =--(ABS(C44-$C$15)>ErrorTolerance) -> 0 | D48: Tab check | E48: =IF(C48>0,"CHECK","ok") -> ok
B50: Density one-way (disclosure): GPUs/MW is a FLAT engineering spec (600), held OFF the Bear/Bull market toggle. Disclosed band 500–600; its one-way NPV effect is shown LIVE in the tornado (row 76). Across chip generations density & chip price are physically coupled — read one at a time.
A52: One-way sensitivity (tornado) — CONTRACTED case. Each lever swings across its band; the base column reconciles to the engine NPV (Check). Levers move the LEVEL; the country ranking is invariant.
A53: LIMITATION (closed-form tornado): swings are computed from a parametric closed form, not the per-period engine. The base reconciles to the engine EXACTLY at Base scenario, but is an APPROXIMATION where the tax-loss kink binds — i.e. for floored/loss-making countries (US, Ireland at Base) whose entry price is at the .40 floor. Treat the swing magnitudes there as indicative, not exact; the ranking of levers (compute price ≫ decline > chip ≈ density > power) is robust. Flagged live by Checks C27 (sense).
D58: Base | E58: P0 $5 | F58: P0 $9 | G58: Decl −30% | H58: Decl −15% | I58: Density 500 | J58: Chip $50k | K58: Chip $35k | L58: Salv 0.40 | M58: Salv 0.55 | N58: Power Bear | O58: Power Bull
B59: P0 ($/GPU-hr) | D59: =Compute_P0 -> 5.7 | E59: =Assumptions!$D$14 -> 4 | F59: =Assumptions!$F$14 -> 9 | G59: =Compute_P0 -> 5.7 | H59: =Compute_P0 -> 5.7 | I59: =Compute_P0 -> 5.7 | J59: =Compute_P0 -> 5.7 | K59: =Compute_P0 -> 5.7 | L59: =Compute_P0 -> 5.7 | M59: =Compute_P0 -> 5.7 | N59: =Compute_P0 -> 5.7 | O59: =Compute_P0 -> 5.7
B60: Decline | D60: =Price_decline -> 0.2 | E60: =Price_decline -> 0.2 | F60: =Price_decline -> 0.2 | G60: =Assumptions!$D$65 -> 0.3 | H60: =Assumptions!$F$65 -> 0.15 | I60: =Price_decline -> 0.2 | J60: =Price_decline -> 0.2 | K60: =Price_decline -> 0.2 | L60: =Price_decline -> 0.2 | M60: =Price_decline -> 0.2 | N60: =Price_decline -> 0.2 | O60: =Price_decline -> 0.2
B61: Density mult | D61: 1 | E61: 1 | F61: 1 | G61: 1 | H61: 1 | I61: =500/Assumptions!$G$12 -> 0.83333333 | J61: 1 | K61: 1 | L61: 1 | M61: 1 | N61: 1 | O61: 1
B62: Chip mult | D62: 1 | E62: 1 | F62: 1 | G62: 1 | H62: 1 | I62: 1 | J62: =Assumptions!$D$11/Assumptions!$G$11 -> 1.1904762 | K62: =Assumptions!$F$11/Assumptions!$G$11 -> 0.83333333 | L62: 1 | M62: 1 | N62: 1 | O62: 1
B63: Salvage | D63: =Facility_salvage_pct -> 0.45 | E63: =Facility_salvage_pct -> 0.45 | F63: =Facility_salvage_pct -> 0.45 | G63: =Facility_salvage_pct -> 0.45 | H63: =Facility_salvage_pct -> 0.45 | I63: =Facility_salvage_pct -> 0.45 | J63: =Facility_salvage_pct -> 0.45 | K63: =Facility_salvage_pct -> 0.45 | L63: =Assumptions!$D$18 -> 0.4 | M63: =Assumptions!$F$18 -> 0.55 | N63: =Facility_salvage_pct -> 0.45 | O63: =Facility_salvage_pct -> 0.45
B64: Power mult | D64: 1 | E64: 1 | F64: 1 | G64: 1 | H64: 1 | I64: 1 | J64: 1 | K64: 1 | L64: 1 | M64: 1 | N64: =Assumptions!$D$22/Assumptions!$G$22 -> 1.5384615 | O64: =Assumptions!$F$22/Assumptions!$G$22 -> 0.57692308
B65: Entry price P_e | D65: =MAX(Price_floor,D59*(1-D60)^Assumptions!$G$23) -> 3.648 | E65: =MAX(Price_floor,E59*(1-E60)^Assumptions!$G$23) -> 2.56 | F65: =MAX(Price_floor,F59*(1-F60)^Assumptions!$G$23) -> 5.76 | G65: =MAX(Price_floor,G59*(1-G60)^Assumptions!$G$23) -> 2.793 | H65: =MAX(Price_floor,H59*(1-H60)^Assumptions!$G$23) -> 4.11825 | I65: =MAX(Price_floor,I59*(1-I60)^Assumptions!$G$23) -> 3.648 | J65: =MAX(Price_floor,J59*(1-J60)^Assumptions!$G$23) -> 3.648 | K65: =MAX(Price_floor,K59*(1-K60)^Assumptions!$G$23) -> 3.648 | ... O65: =MAX(Price_floor,O59*(1-O60)^Assumptions!$G$23) -> 3.648
B66: Revenue (level, full occ) | D66: =Calculations!$C$9*D61*D65/Compute_P0 -> 1687.3021 | E66: =Calculations!$C$9*E61*E65/Compute_P0 -> 1184.0717 | F66: =Calculations!$C$9*F61*F65/Compute_P0 -> 2664.1613 | G66: =Calculations!$C$9*G61*G65/Compute_P0 -> 1291.8407 | H66: =Calculations!$C$9*H61*H65/Compute_P0 -> 1904.8059 | I66: =Calculations!$C$9*I61*I65/Compute_P0 -> 1406.0851 | J66: =Calculations!$C$9*J61*J65/Compute_P0 -> 1687.3021 | K66: =Calculations!$C$9*K61*K65/Compute_P0 -> 1687.3021 | ... O66: =Calculations!$C$9*O61*O65/Compute_P0 -> 1687.3021
B67: GPU capex | D67: =Calculations!$C$6*D61*D62 -> 2520 | E67: =Calculations!$C$6*E61*E62 -> 2520 | F67: =Calculations!$C$6*F61*F62 -> 2520 | G67: =Calculations!$C$6*G61*G62 -> 2520 | H67: =Calculations!$C$6*H61*H62 -> 2520 | I67: =Calculations!$C$6*I61*I62 -> 2100 | J67: =Calculations!$C$6*J61*J62 -> 3000 | K67: =Calculations!$C$6*K61*K62 -> 2100 | ... O67: =Calculations!$C$6*O61*O62 -> 2520
B68: Power cost | D68: =Calculations!$C$10*D64 -> 46.098624 | E68: =Calculations!$C$10*E64 -> 46.098624 | F68: =Calculations!$C$10*F64 -> 46.098624 | G68: =Calculations!$C$10*G64 -> 46.098624 | H68: =Calculations!$C$10*H64 -> 46.098624 | I68: =Calculations!$C$10*I64 -> 46.098624 | J68: =Calculations!$C$10*J64 -> 46.098624 | K68: =Calculations!$C$10*K64 -> 46.098624 | ... O68: =Calculations!$C$10*O64 -> 26.59536
B69: Deprec/yr | D69: =D67/GPU_life+Calculations!$C$7*Calculations!$C$15 -> 615.07 | E69: =E67/GPU_life+Calculations!$C$7*Calculations!$C$15 -> 615.07 | F69: =F67/GPU_life+Calculations!$C$7*Calculations!$C$15 -> 615.07 | G69: =G67/GPU_life+Calculations!$C$7*Calculations!$C$15 -> 615.07 | H69: =H67/GPU_life+Calculations!$C$7*Calculations!$C$15 -> 615.07 | I69: =I67/GPU_life+Calculations!$C$7*Calculations!$C$15 -> 531.07 | J69: =J67/GPU_life+Calculations!$C$7*Calculations!$C$15 -> 711.07 | K69: =K67/GPU_life+Calculations!$C$7*Calculations!$C$15 -> 531.07 | ... O69: =O67/GPU_life+Calculations!$C$7*Calculations!$C$15 -> 615.07
B70: EBITDA | D70: =D66-D68-Calculations!$C$13 -> 1554.7335 | E70: =E66-E68-Calculations!$C$13 -> 1051.5031 | F70: =F66-F68-Calculations!$C$13 -> 2531.5927 | G70: =G66-G68-Calculations!$C$13 -> 1159.2721 | H70: =H66-H68-Calculations!$C$13 -> 1772.2373 | I70: =I66-I68-Calculations!$C$13 -> 1273.5165 | J70: =J66-J68-Calculations!$C$13 -> 1554.7335 | K70: =K66-K68-Calculations!$C$13 -> 1554.7335 | ... O70: =O66-O68-Calculations!$C$13 -> 1574.2368
B71: After-tax steady CF | D71: =D70-$C$9*MAX(D70-D69,0) -> 1348.0075 | E71: =E70-$C$9*MAX(E70-E69,0) -> 955.48778 | F71: =F70-$C$9*MAX(F70-F69,0) -> 2109.9577 | G71: =G70-$C$9*MAX(G70-G69,0) -> 1039.5476 | H71: =H70-$C$9*MAX(H70-H69,0) -> 1517.6605 | I71: =I70-$C$9*MAX(I70-I69,0) -> 1110.1783 | J71: =J70-$C$9*MAX(J70-J69,0) -> 1369.1275 | K71: =K70-$C$9*MAX(K70-K69,0) -> 1329.5275 | ... O71: =O70-$C$9*MAX(O70-O69,0) -> 1363.2201
B72: Capex PV (phased fac + GPU) | D72: =Calculations!$C$7*IF(Calculations!$C$20=0,1,(1-Calculations!$C$21^Calculations!$C$20)/(1-Calculations!$C$21)/Calculations!$C$20)+D67*Calculations!$C$21^Calculations!$C$20 -> 3916.6028 | E72: =Calculations!$C$7*IF(Calculations!$C$20=0,1,(1-Calculations!$C$21^Calculations!$C$20)/(1-Calculations!$C$21)/Calculations!$C$20)+E67*Calculations!$C$21^Calculations!$C$20 -> 3916.6028 | F72: =Calculations!$C$7*IF(Calculations!$C$20=0,1,(1-Calculations!$C$21^Calculations!$C$20)/(1-Calculations!$C$21)/Calculations!$C$20)+F67*Calculations!$C$21^Calculations!$C$20 -> 3916.6028 | G72: =Calculations!$C$7*IF(Calculations!$C$20=0,1,(1-Calculations!$C$21^Calculations!$C$20)/(1-Calculations!$C$21)/Calculations!$C$20)+G67*Calculations!$C$21^Calculations!$C$20 -> 3916.6028 | H72: =Calculations!$C$7*IF(Calculations!$C$20=0,1,(1-Calculations!$C$21^Calculations!$C$20)/(1-Calculations!$C$21)/Calculations!$C$20)+H67*Calculations!$C$21^Calculations!$C$20 -> 3916.6028 | I72: =Calculations!$C$7*IF(Calculations!$C$20=0,1,(1-Calculations!$C$21^Calculations!$C$20)/(1-Calculations!$C$21)/Calculations!$C$20)+I67*Calculations!$C$21^Calculations!$C$20 -> 3545.1907 | J72: =Calculations!$C$7*IF(Calculations!$C$20=0,1,(1-Calculations!$C$21^Calculations!$C$20)/(1-Calculations!$C$21)/Calculations!$C$20)+J67*Calculations!$C$21^Calculations!$C$20 -> 4341.0737 | K72: =Calculations!$C$7*IF(Calculations!$C$20=0,1,(1-Calculations!$C$21^Calculations!$C$20)/(1-Calculations!$C$21)/Calculations!$C$20)+K67*Calculations!$C$21^Calculations!$C$20 -> 3545.1907 | ... O72: =Calculations!$C$7*IF(Calculations!$C$20=0,1,(1-Calculations!$C$21^Calculations!$C$20)/(1-Calculations!$C$21)/Calculations!$C$20)+O67*Calculations!$C$21^Calculations!$C$20 -> 3916.6028
B73: TV PV | D73: =(Calculations!$C$7*D63+D67*GPU_salvage_pct*(1-$C$9))*Calculations!$C$21^(Calculations!$C$20+GPU_life-1) -> 677.40923 | E73: =(Calculations!$C$7*E63+E67*GPU_salvage_pct*(1-$C$9))*Calculations!$C$21^(Calculations!$C$20+GPU_life-1) -> 677.40923 | F73: =(Calculations!$C$7*F63+F67*GPU_salvage_pct*(1-$C$9))*Calculations!$C$21^(Calculations!$C$20+GPU_life-1) -> 677.40923 | G73: =(Calculations!$C$7*G63+G67*GPU_salvage_pct*(1-$C$9))*Calculations!$C$21^(Calculations!$C$20+GPU_life-1) -> 677.40923 | H73: =(Calculations!$C$7*H63+H67*GPU_salvage_pct*(1-$C$9))*Calculations!$C$21^(Calculations!$C$20+GPU_life-1) -> 677.40923 | I73: =(Calculations!$C$7*I63+I67*GPU_salvage_pct*(1-$C$9))*Calculations!$C$21^(Calculations!$C$20+GPU_life-1) -> 654.75423 | J73: =(Calculations!$C$7*J63+J67*GPU_salvage_pct*(1-$C$9))*Calculations!$C$21^(Calculations!$C$20+GPU_life-1) -> 703.30065 | K73: =(Calculations!$C$7*K63+K67*GPU_salvage_pct*(1-$C$9))*Calculations!$C$21^(Calculations!$C$20+GPU_life-1) -> 654.75423 | ... O73: =(Calculations!$C$7*O63+O67*GPU_salvage_pct*(1-$C$9))*Calculations!$C$21^(Calculations!$C$20+GPU_life-1) -> 677.40923
B74: Ramp haircut | D74: =(D66-D68)*(1-$C$9)*Calculations!$C$21^(Calculations!$C$20)*((1-Ramp_yr1)+(1-Ramp_yr2)*Calculations!$C$21) -> 555.89866 | E74: =(E66-E68)*(1-$C$9)*Calculations!$C$21^(Calculations!$C$20)*((1-Ramp_yr1)+(1-Ramp_yr2)*Calculations!$C$21) -> 385.44744 | F74: =(F66-F68)*(1-$C$9)*Calculations!$C$21^(Calculations!$C$20)*((1-Ramp_yr1)+(1-Ramp_yr2)*Calculations!$C$21) -> 886.77455 | G74: =(G66-G68)*(1-$C$9)*Calculations!$C$21^(Calculations!$C$20)*((1-Ramp_yr1)+(1-Ramp_yr2)*Calculations!$C$21) -> 421.95032 | H74: =(H66-H68)*(1-$C$9)*Calculations!$C$21^(Calculations!$C$20)*((1-Ramp_yr1)+(1-Ramp_yr2)*Calculations!$C$21) -> 629.57024 | I74: =(I66-I68)*(1-$C$9)*Calculations!$C$21^(Calculations!$C$20)*((1-Ramp_yr1)+(1-Ramp_yr2)*Calculations!$C$21) -> 460.64651 | J74: =(J66-J68)*(1-$C$9)*Calculations!$C$21^(Calculations!$C$20)*((1-Ramp_yr1)+(1-Ramp_yr2)*Calculations!$C$21) -> 555.89866 | K74: =(K66-K68)*(1-$C$9)*Calculations!$C$21^(Calculations!$C$20)*((1-Ramp_yr1)+(1-Ramp_yr2)*Calculations!$C$21) -> 555.89866 | ... O74: =(O66-O68)*(1-$C$9)*Calculations!$C$21^(Calculations!$C$20)*((1-Ramp_yr1)+(1-Ramp_yr2)*Calculations!$C$21) -> 562.50469
B75: NPV ($m) | D75: =-D72-$C$12+D71*$C$10+D73-D74 -> 1448.0114 | E75: =-E72-$C$12+E71*$C$10+E73-E74 -> 77.881193 | F75: =-F72-$C$12+F71*$C$10+F73-F74 -> 4107.6758 | G75: =-G72-$C$12+G71*$C$10+G73-G74 -> 371.30061 | H75: =-H72-$C$12+H71*$C$10+H73-H74 -> 2040.2023 | I75: =-I72-$C$12+I71*$C$10+I73-I74 -> 958.57619 | J75: =-J72-$C$12+J71*$C$10+J73-J74 -> 1132.3247 | K75: =-K72-$C$12+K71*$C$10+K73-K74 -> 1724.2372 | ... O75: =-O72-$C$12+O71*$C$10+O73-O74 -> 1501.1123
B76: Check: tornado base = engine NPV (selected) | C76: =--(ABS(D75-$C$15)>ErrorTolerance) -> 0 | D76: Tab check | E76: =IF(C76>0,"CHECK","ok") -> ok
A78: Tornado — NPV swing per lever (contracted; each lever swung across its band, all else at base) | B78: Lever (band) | C78: Low NPV ($m) | D78: High NPV ($m) | E78: Swing ($m)
B79: Compute price P0 ($5 → $9 /GPU-hr) | C79: =E75 -> 77.881193 | D79: =F75 -> 4107.6758 | E79: =ABS(F75-E75) -> 4029.7946
B80: Price decline (−30% → −15% /yr) | C80: =G75 -> 371.30061 | D80: =H75 -> 2040.2023 | E80: =ABS(H75-G75) -> 1668.9017
B81: GPU density (500 → 600 /MW) | C81: =I75 -> 958.57619 | D81: =D75 -> 1448.0114 | E81: =ABS(D75-I75) -> 489.43516
B95: Each bar swings ONE lever; the base reconciles to the per-period engine. Compute price and the erosion/decline rate now dominate (price is the whole revenue line); delivered power stays small (~2% of revenue). The country RANKING is invariant; levers move the LEVEL only.
A96: Tornado chart data (sorted by |swing|; floating bars span low→high NPV; base NPV = D75).
B97: Lever (band) | C97: offset (dev from base) | D97: swing ($m)
B98: Compute price P0 ($5→$9) | C98: =MIN(E75,F75) -> 77.881193 | D98: =ABS(F75-E75) -> 4029.7946
B99: Price decline (−30%→−15%) | C99: =MIN(G75,H75) -> 371.30061 | D99: =ABS(H75-G75) -> 1668.9017
B100: GPU chip price ($50k→$35k) | C100: =MIN(J75,K75) -> 1132.3247 | D100: =ABS(K75-J75) -> 591.91245
B101: GPU density (500→600/MW) | C101: =MIN(I75,D75) -> 958.57619 | D101: =ABS(D75-I75) -> 489.43516
B102: Facility salvage (0.40→0.55) | C102: =MIN(L75,M75) -> 1387.847 | D102: =ABS(M75-L75) -> 180.49309
B103: Delivered power (Bear↔Bull) | C103: =MIN(N75,O75) -> 1380.4283 | D103: =ABS(O75-N75) -> 120.68395

Sheet Price Path
A1: Price Path — queue length is destiny (entry price = today’s price eroded over the queue, floored) | C1: =IF(Checks!$C$4>0,"MODEL IN ERROR","checks OK") -> checks OK
A2: The market rate erodes from today’s P0 toward the full-cost floor. A country switches on at the END of its interconnection queue — so a long queue means entering an already-collapsed market. Active scenario (Base).
B4: Market price path | E4: Country entry points (price at switch-on = end of queue)
B5: Years from today | C5: Market price ($/GPU-hr) | E5: Country | F5: Time-to-power (yr) | G5: Entry price ($/GPU-hr) | H5: Payback period | I5: Breakeven utilization | J5: IRR | K5: NPV ($m)
B6: 0 | C6: =MAX(Price_floor,Compute_P0*(1-Price_decline)^B6) -> 5.7 | E6: =Comparison!C6 -> Norway | F6: =Comparison!C9 -> 2 | G6: =Comparison!C17 -> 3.648 | I6: =Comparison!C$39 -> 0.59483429 | K6: =Comparison!C$38 -> 1448.0114
B7: 1 | C7: =MAX(Price_floor,Compute_P0*(1-Price_decline)^B7) -> 4.56 | E7: =Comparison!D6 -> United States | F7: =Comparison!D9 -> 4.5 | G7: =Comparison!D17 -> 2.5 | I7: =Comparison!D$39 -> 0.97870691 | K7: =Comparison!D$38 -> -281.96077
B8: 2 | C8: =MAX(Price_floor,Compute_P0*(1-Price_decline)^B8) -> 3.648 | E8: =Comparison!E6 -> India | F8: =Comparison!E9 -> 3 | G8: =Comparison!E17 -> 2.9184 | I8: =Comparison!E$39 -> 0.87615746 | K8: =Comparison!E$38 -> 12.417256
B9: 3 | C9: =MAX(Price_floor,Compute_P0*(1-Price_decline)^B9) -> 2.9184 | E9: =Comparison!F6 -> Ireland | F9: =Comparison!F9 -> 6 | G9: =Comparison!F17 -> 2.5 | I9: =Comparison!F$39 -> >100% (never) | K9: =Comparison!F$38 -> -460.96698
B10: 4 | C10: =MAX(Price_floor,Compute_P0*(1-Price_decline)^B10) -> 2.5 | E10: =Comparison!G6 -> Saudi Arabia | F10: =Comparison!G9 -> 2 | G10: =Comparison!G17 -> 3.648 | I10: =Comparison!G$39 -> 0.59907962 | K10: =Comparison!G$38 -> 1428.7514
B11: 5 | C11: =MAX(Price_floor,Compute_P0*(1-Price_decline)^B11) -> 2.5
B12: 6 | C12: =MAX(Price_floor,Compute_P0*(1-Price_decline)^B12) -> 2.5
B13: 7 | C13: =MAX(Price_floor,Compute_P0*(1-Price_decline)^B13) -> 2.5
B14: 8 | C14: =MAX(Price_floor,Compute_P0*(1-Price_decline)^B14) -> 2.5
A34: Read: short-queue Norway/Saudi (~2 yr) switch on near today’s price; long-queue Ireland/US enter years into the decline, at or near the $2.70 floor — which is why a signed contract cannot rescue a slow-queue site. Floor = full-cost break-even (Price Floor tab). Source: model (Compute_P0, decline, floor; Comparison TTP/entry).
A36: Check — country entry = P0·(1−decline)^TTP, floored (ties to Comparison): | C36: =--(ABS(SUM(G6:G10)-SUM(Comparison!C17:G17))>ErrorTolerance) -> 0

Sheet Country detail
A1: ="Country detail — "&Assumptions!$B$5&" ("&Assumptions!$B$4&")" -> Country detail — Norway (Base) | C1: =IF(Checks!$C$4>0,"MODEL IN ERROR","checks OK") -> checks OK
A2: One country in depth for the selected country/scenario: headline metrics linked from Calculations. IRR & payback live here. Blue = linked from Calculations.
A3: Headline viability metrics (linked from Calculations)
A4: Country | B4: =Assumptions!$B$5 -> Norway
A5: Scenario | B5: =Assumptions!$B$4 -> Base
A6: Total capex (facility + GPU) | B6: =-(Calculations!$C$7+Calculations!$C$6) -> -4260
A7: Annual EBITDA (steady state) | B7: =Calculations!$C$14 -> 2503.841
A8: NPV | B8: =Calculations!C61 -> 1448.0114
A9: IRR | B9: =Calculations!C62 -> 0.18467513
A10: Payback (incl. build) | B10: =Calculations!C63 -> 5
A11: Break-even utilization | B11: =Calculations!C64 -> 0.59483429
A12: Power as % of revenue | B12: =Calculations!$C$10/Calculations!$C$9 -> 0.01748538
A14: Cash-flow path (per period — linked from Calculations)
A15: Period | B15: =Calculations!D36 -> 0 | C15: =Calculations!E36 -> 1 | D15: =Calculations!F36 -> 2 | E15: =Calculations!G36 -> 3 | F15: =Calculations!H36 -> 4 | G15: =Calculations!I36 -> 5 | H15: =Calculations!J36 -> 6 | I15: =Calculations!K36 -> 7 | ... U15: =Calculations!W36 -> 19
A16: Net FCF ($m) | B16: =Calculations!D52 -> -870 | C16: =Calculations!E52 -> -896.1 | D16: =Calculations!F52 -> -1646.141 | E16: =Calculations!G52 -> 1155.9867 | F16: =Calculations!H52 -> 1348.0075 | G16: =Calculations!I52 -> 1348.0075 | H16: =Calculations!J52 -> 2327.5675 | I16: =Calculations!K52 -> 0 | ... U16: =Calculations!W52 -> 0
A17: Cumulative FCF ($m) | B17: =Calculations!D55 -> -870 | C17: =Calculations!E55 -> -1766.1 | D17: =Calculations!F55 -> -3412.241 | E17: =Calculations!G55 -> -2256.2543 | F17: =Calculations!H55 -> -908.24674 | G17: =Calculations!I55 -> 439.76081 | H17: =Calculations!J55 -> 2767.3284 | I17: =Calculations!K55 -> 2767.3284 | ... U17: =Calculations!W55 -> 2767.3284

Sheet Power Timing
A1: Power Timing — what the grid queue costs, and the ranking if power were instant | C1: =IF(Checks!$C$4>0,"MODEL IN ERROR","checks OK") -> checks OK
A2: Counterfactual computed by the PER-PERIOD engine with ops-start forced to 0 (no queue; entry price = full P0, no erosion-over-the-wait). Blue = linked from the engine; red = headline. Exact — not a closed-form approximation.
B4: Metric | C4: =Comparison!C6 -> Norway | D4: =Comparison!D6 -> United States | E4: =Comparison!E6 -> India | F4: =Comparison!F6 -> Ireland | G4: =Comparison!G6 -> Saudi Arabia
B6: Actual NPV — with grid queue ($m) | C6: =Comparison!C38 -> 1448.0114 | D6: =Comparison!D38 -> -281.96077 | E6: =Comparison!E38 -> 12.417256 | F6: =Comparison!F38 -> -460.96698 | G6: =Comparison!G38 -> 1428.7514
B7: Time-to-power (yr) | C7: =Comparison!C9 -> 2 | D7: =Comparison!D9 -> 4.5 | E7: =Comparison!E9 -> 3 | F7: =Comparison!F9 -> 6 | G7: =Comparison!G9 -> 2
B14: NPV if power were instant ($m) | C14: ='Country Engine'!G671 -> 4782.4227 | D14: ='Country Engine'!G672 -> 4747.3518 | E14: ='Country Engine'!G673 -> 4090.039 | F14: ='Country Engine'!G674 -> 5050.1705 | G14: ='Country Engine'!G675 -> 4834.2224
B15: NPV gap versus instant power ($m) | C15: =C6-C14 -> -3334.4113 | D15: =D6-D14 -> -5029.3125 | E15: =E6-E14 -> -4077.6217 | F15: =F6-F14 -> -5511.1375 | G15: =G6-G14 -> -3405.4711
B16: Rank today (by actual NPV) | C16: =RANK(C6,$C$6:$G$6,0) -> 1 | D16: =RANK(D6,$C$6:$G$6,0) -> 4 | E16: =RANK(E6,$C$6:$G$6,0) -> 3 | F16: =RANK(F6,$C$6:$G$6,0) -> 5 | G16: =RANK(G6,$C$6:$G$6,0) -> 2
B17: Rank if power instant | C17: =RANK(C14,$C$14:$G$14,0) -> 3 | D17: =RANK(D14,$C$14:$G$14,0) -> 4 | E17: =RANK(E14,$C$14:$G$14,0) -> 5 | F17: =RANK(F14,$C$14:$G$14,0) -> 1 | G17: =RANK(G14,$C$14:$G$14,0) -> 2
A19: Chart data (rows = countries)
B20: Country | C20: With grid queue | D20: If power instant | E20: Queue cost ($m)
B21: =Comparison!C6 -> Norway | C21: =C6 -> 1448.0114 | D21: =C14 -> 4782.4227 | E21: =C6-C14 -> -3334.4113
B22: =Comparison!D6 -> United States | C22: =D6 -> -281.96077 | D22: =D14 -> 4747.3518 | E22: =D6-D14 -> -5029.3125
B23: =Comparison!E6 -> India | C23: =E6 -> 12.417256 | D23: =E14 -> 4090.039 | E23: =E6-E14 -> -4077.6217
B24: =Comparison!F6 -> Ireland | C24: =F6 -> -460.96698 | D24: =F14 -> 5050.1705 | E24: =F6-F14 -> -5511.1375
B25: =Comparison!G6 -> Saudi Arabia | C25: =G6 -> 1428.7514 | D25: =G14 -> 4834.2224 | E25: =G6-G14 -> -3405.4711
B27: Check: instant-power NPV ≥ actual for every country (queue is a cost) | C27: =--(MAX(C15:G15)>ErrorTolerance) -> 0 | E27: =IF(MAX(C15:G15)>ErrorTolerance,"CHECK","ok") -> ok

Sheet Deal Comparison
A1: Deal Comparison — contracted vs merchant NPV, every country, both deals at once | C1: =IF(Checks!$C$4>0,"MODEL IN ERROR","checks OK") -> checks OK
A2: Both deal types read straight from the per-period Country Engine (no separate replica to diverge). Contracted locks the eroded entry price; Merchant keeps eroding to the floor. Blue = linked from the engine; red = headline. The ACTIVE deal reconciles to Comparison (Checks).
B4: Metric | C4: =Comparison!C6 -> Norway | D4: =Comparison!D6 -> United States | E4: =Comparison!E6 -> India | F4: =Comparison!F6 -> Ireland | G4: =Comparison!G6 -> Saudi Arabia
A15: Contracted — NPV per country (per-period, from Country Engine)
B26: Contracted NPV ($m) | C26: =INDEX('Country Engine'!$C$671:$C$675,MATCH(C$4,'Country Engine'!$A$671:$A$675,0)) -> 1448.0114 | D26: =INDEX('Country Engine'!$C$671:$C$675,MATCH(D$4,'Country Engine'!$A$671:$A$675,0)) -> -281.96077 | E26: =INDEX('Country Engine'!$C$671:$C$675,MATCH(E$4,'Country Engine'!$A$671:$A$675,0)) -> 12.417256 | F26: =INDEX('Country Engine'!$C$671:$C$675,MATCH(F$4,'Country Engine'!$A$671:$A$675,0)) -> -460.96698 | G26: =INDEX('Country Engine'!$C$671:$C$675,MATCH(G$4,'Country Engine'!$A$671:$A$675,0)) -> 1428.7514
A27: Merchant — NPV per country (per-period, from Country Engine)
B30: Contracted − Merchant spread ($m) = value of the offtake | C30: =C26-C38 -> 2160.1209 | D30: =D26-D38 -> 781.70403 | E30: =E26-E38 -> 1144.892 | F30: =F26-F38 -> 672.77415 | G30: =G26-G38 -> 2154.3142
B38: Merchant NPV ($m) | C38: =INDEX('Country Engine'!$D$671:$D$675,MATCH(C$4,'Country Engine'!$A$671:$A$675,0)) -> -712.10953 | D38: =INDEX('Country Engine'!$D$671:$D$675,MATCH(D$4,'Country Engine'!$A$671:$A$675,0)) -> -1063.6648 | E38: =INDEX('Country Engine'!$D$671:$D$675,MATCH(E$4,'Country Engine'!$A$671:$A$675,0)) -> -1132.4747 | F38: =INDEX('Country Engine'!$D$671:$D$675,MATCH(F$4,'Country Engine'!$A$671:$A$675,0)) -> -1133.7411 | G38: =INDEX('Country Engine'!$D$671:$D$675,MATCH(G$4,'Country Engine'!$A$671:$A$675,0)) -> -725.56288
A40: Reconciliation — the ACTIVE deal must equal the Comparison NPV
B41: NPV — active deal (tie target) | C41: =IF(Assumptions!$B$7="Contracted",C26,C38) -> 1448.0114 | D41: =IF(Assumptions!$B$7="Contracted",D26,D38) -> -281.96077 | E41: =IF(Assumptions!$B$7="Contracted",E26,E38) -> 12.417256 | F41: =IF(Assumptions!$B$7="Contracted",F26,F38) -> -460.96698 | G41: =IF(Assumptions!$B$7="Contracted",G26,G38) -> 1428.7514
B42: Tie residual vs Comparison ($m) | C42: =C41-Comparison!C38 -> 0 | D42: =D41-Comparison!D38 -> 0 | E42: =E41-Comparison!E38 -> 0 | F42: =F41-Comparison!F38 -> 0 | G42: =G41-Comparison!G38 -> 0
B43: Tie total (into Checks) | C43: =SUMPRODUCT(ABS(C42:G42)) -> 0

Sheet Asset Life
A1: Asset Life — grid queue, then a 5-year GPU hold, inside a 25-year shell | C1: =IF(Checks!$C$4>0,"MODEL IN ERROR","checks OK") -> checks OK
A2: Years from start of build: the grid-queue wait, then the GPU operating hold (=GPU life), then residual shell life sold at salvage. Blue = linked. Liquidation year = queue + hold.
B4: Country | C4: Grid queue (yr) | D4: Operating (yr) | E4: Shell residual (yr) | F4: Liquidate (yr)
B5: =Comparison!F6 -> Ireland | C5: =Comparison!F9 -> 6 | D5: =GPU_life -> 5 | E5: =Assumptions!$F$36-C5-D5 -> 14 | F5: =C5+D5 -> 11
B6: =Comparison!D6 -> United States | C6: =Comparison!D9 -> 4.5 | D6: =GPU_life -> 5 | E6: =Assumptions!$F$36-C6-D6 -> 15.5 | F6: =C6+D6 -> 9.5
B7: =Comparison!E6 -> India | C7: =Comparison!E9 -> 3 | D7: =GPU_life -> 5 | E7: =Assumptions!$F$36-C7-D7 -> 17 | F7: =C7+D7 -> 8
B8: =Comparison!G6 -> Saudi Arabia | C8: =Comparison!G9 -> 2 | D8: =GPU_life -> 5 | E8: =Assumptions!$F$36-C8-D8 -> 18 | F8: =C8+D8 -> 7
B9: =Comparison!C6 -> Norway | C9: =Comparison!C9 -> 2 | D9: =GPU_life -> 5 | E9: =Assumptions!$F$36-C9-D9 -> 18 | F9: =C9+D9 -> 7
B11: Shell/building life (yr) | C11: =Assumptions!$F$36 -> 25
B12: Check: queue + hold ≤ shell life (residual ≥ 0) | C12: =--(MIN(E5:E9)<0) -> 0

Sheet Energy Security
A1: Energy Security — Custom Proxy (WEC World Energy Trilemma Framework) | C1: =IF(Checks!$C$4>0,"MODEL IN ERROR","checks OK") -> checks OK
A2: Faithful to the WEC World Energy Trilemma Index Energy-Security dimension: three sourced pillars, equal-weighted, 0–100. (1) Import independence = IEA energy self-sufficiency; (2) Generation diversity = 1−HHI on the Ember 2024 electricity mix; (3) System stability = firm/dispatchable share (all except variable wind+solar). Distinct from carbon (a separate Trilemma dimension).
B4: Country | C4: Import independence (self-suff %) | D4: Generation diversity (1−HHI) | E4: System stability (firm %) | F4: Energy-Security score (0–100) | G4: Rank | H4: Per-country basis (Ember 2024 mix; IEA self-sufficiency): [40][41][42]
B5: =Assumptions!$B$81 -> Norway | C5: =MIN(Assumptions!$K$81,100) -> 100 | D5: =ROUND((1-SUMPRODUCT(Assumptions!$C$81:$J$81,Assumptions!$C$81:$J$81)/10000)*100,1) -> 21.5 | E5: =100-Assumptions!$D$81-Assumptions!$E$81 -> 90 | F5: =ROUND(AVERAGE(C5:E5),1) -> 70.5 | G5: =RANK(F5,$F$5:$F$9) -> 3 | H5: Norway — self-sufficient + 90% firm, but ~88% hydro is a concentration/drought vulnerability → mid diversity score.
B6: =Assumptions!$B$82 -> United States | C6: =MIN(Assumptions!$K$82,100) -> 100 | D6: =ROUND((1-SUMPRODUCT(Assumptions!$C$82:$J$82,Assumptions!$C$82:$J$82)/10000)*100,1) -> 74.3 | E6: =100-Assumptions!$D$82-Assumptions!$E$82 -> 85 | F6: =ROUND(AVERAGE(C6:E6),1) -> 86.4 | G6: =RANK(F6,$F$5:$F$9) -> 1 | H6: United States — most diverse grid (gas 43 / nuclear 18 / coal 15 / wind 10 / hydro 6), self-sufficient, high firm share → highest security.
B7: =Assumptions!$B$83 -> India | C7: =MIN(Assumptions!$K$83,100) -> 60 | D7: =ROUND((1-SUMPRODUCT(Assumptions!$C$83:$J$83,Assumptions!$C$83:$J$83)/10000)*100,1) -> 51.6 | E7: =100-Assumptions!$D$83-Assumptions!$E$83 -> 85 | F7: =ROUND(AVERAGE(C7:E7),1) -> 65.5 | G7: =RANK(F7,$F$5:$F$9) -> 4 | H7: India — high firm (coal 68), improving diversity, but ~60% energy self-sufficient (oil/gas imports).
B8: =Assumptions!$B$84 -> Ireland | C8: =MIN(Assumptions!$K$84,100) -> 21 | D8: =ROUND((1-SUMPRODUCT(Assumptions!$C$84:$J$84,Assumptions!$C$84:$J$84)/10000)*100,1) -> 70 | E8: =100-Assumptions!$D$84-Assumptions!$E$84 -> 63 | F8: =ROUND(AVERAGE(C8:E8),1) -> 51.3 | G8: =RANK(F8,$F$5:$F$9) -> 5 | H8: Ireland — lowest: ~21% self-sufficient (gas-import-dependent) and lower firm share (wind 33 / solar 4).
B9: =Assumptions!$B$85 -> Saudi Arabia | C9: =MIN(Assumptions!$K$85,100) -> 100 | D9: =ROUND((1-SUMPRODUCT(Assumptions!$C$85:$J$85,Assumptions!$C$85:$J$85)/10000)*100,1) -> 48 | E9: =100-Assumptions!$D$85-Assumptions!$E$85 -> 98 | F9: =ROUND(AVERAGE(C9:E9),1) -> 82 | G9: =RANK(F9,$F$5:$F$9) -> 2 | H9: Saudi Arabia — self-sufficient + ~98% firm (gas 63 / oil 35), but concentrated (low diversity).
A11: Method: Energy-Security proxy score = equal-weighted mean of three 0–100 pillars (import independence, generation diversity 1−HHI, firm/dispatchable share). Framework: World Energy Council, World Energy Trilemma. Data: IEA (self-sufficiency), Ember 2024 (electricity mix).
A12: Water note (resource sovereignty): cooling-water availability is a related sovereignty constraint, material in hot climates (India, Saudi). Shown qualitatively — not in the index.
A13: Sources: WEC World Energy Trilemma (framework); IEA / IEEJ (energy self-sufficiency); Ember Global Electricity Review 2024 (electricity mix). See Sources tab.
A15: Check — electricity mix sums to 100% per country (max abs deviation): | C15: =MAX(ABS(SUM(Assumptions!C81:J81)-100),ABS(SUM(Assumptions!C82:J82)-100),ABS(SUM(Assumptions!C83:J83)-100),ABS(SUM(Assumptions!C84:J84)-100),ABS(SUM(Assumptions!C85:J85)-100)) -> 0 | D15: =--(C15>ErrorTolerance) -> 0

Sheet Three-Lens View
A1: Three-Lens View — economics × energy security × carbon | C1: =IF(Checks!$C$4>0,"MODEL IN ERROR","checks OK") -> checks OK
A2: The NPV ranking is one lens. Energy security (WEC Trilemma) and grid carbon are independent lenses — no country leads all three. Active scenario/deal (headline = Base · Contracted).
B4: Country | C4: NPV ($m) | D4: Economics | E4: Energy-security | F4: Energy security | G4: Carbon (gCO₂/kWh) | H4: Carbon
B5: =Comparison!C6 -> Norway | C5: =Comparison!C38 -> 1448.0114 | D5: =RANK(C5,$C$5:$C$9,1) -> 5 | E5: ='Energy Security'!F5 -> 70.5 | F5: =RANK(E5,$E$5:$E$9,0) -> 3 | G5: =Comparison!C42 -> 28 | H5: =RANK(G5,$G$5:$G$9,0) -> 5
B6: =Comparison!D6 -> United States | C6: =Comparison!D38 -> -281.96077 | D6: =RANK(C6,$C$5:$C$9,1) -> 2 | E6: ='Energy Security'!F6 -> 86.4 | F6: =RANK(E6,$E$5:$E$9,0) -> 1 | G6: =Comparison!D42 -> 384 | H6: =RANK(G6,$G$5:$G$9,0) -> 3
B7: =Comparison!E6 -> India | C7: =Comparison!E38 -> 12.417256 | D7: =RANK(C7,$C$5:$C$9,1) -> 3 | E7: ='Energy Security'!F7 -> 65.5 | F7: =RANK(E7,$E$5:$E$9,0) -> 4 | G7: =Comparison!E42 -> 670 | H7: =RANK(G7,$G$5:$G$9,0) -> 1
B8: =Comparison!F6 -> Ireland | C8: =Comparison!F38 -> -460.96698 | D8: =RANK(C8,$C$5:$C$9,1) -> 1 | E8: ='Energy Security'!F8 -> 51.3 | F8: =RANK(E8,$E$5:$E$9,0) -> 5 | G8: =Comparison!F42 -> 290 | H8: =RANK(G8,$G$5:$G$9,0) -> 4
B9: =Comparison!G6 -> Saudi Arabia | C9: =Comparison!G38 -> 1428.7514 | D9: =RANK(C9,$C$5:$C$9,1) -> 4 | E9: ='Energy Security'!F9 -> 82 | F9: =RANK(E9,$E$5:$E$9,0) -> 2 | G9: =Comparison!G42 -> 590 | H9: =RANK(G9,$G$5:$G$9,0) -> 2
A11: Normalized 0–100 for visual comparison (min–max within the five-country set; higher = better). Raw values above.
B12: Country | C12: Economics (NPV) | D12: Energy security (0-100) | E12: Carbon (gCO₂/kWh) (cleaner=high)
B13: =B5 -> Norway | C13: =(C5-MIN($C$5:$C$9))/(MAX($C$5:$C$9)-MIN($C$5:$C$9))*100 -> 100 | D13: =E5 -> 70.5 | E13: =(MAX($G$5:$G$9)-G5)/(MAX($G$5:$G$9)-MIN($G$5:$G$9))*100 -> 100
B14: =B6 -> United States | C14: =(C6-MIN($C$5:$C$9))/(MAX($C$5:$C$9)-MIN($C$5:$C$9))*100 -> 9.3770688 | D14: =E6 -> 86.4 | E14: =(MAX($G$5:$G$9)-G6)/(MAX($G$5:$G$9)-MIN($G$5:$G$9))*100 -> 44.548287
B15: =B7 -> India | C15: =(C7-MIN($C$5:$C$9))/(MAX($C$5:$C$9)-MIN($C$5:$C$9))*100 -> 24.797779 | D15: =E7 -> 65.5 | E15: =(MAX($G$5:$G$9)-G7)/(MAX($G$5:$G$9)-MIN($G$5:$G$9))*100 -> 0
B16: =B8 -> Ireland | C16: =(C8-MIN($C$5:$C$9))/(MAX($C$5:$C$9)-MIN($C$5:$C$9))*100 -> 0 | D16: =E8 -> 51.3 | E16: =(MAX($G$5:$G$9)-G8)/(MAX($G$5:$G$9)-MIN($G$5:$G$9))*100 -> 59.190031
B17: =B9 -> Saudi Arabia | C17: =(C9-MIN($C$5:$C$9))/(MAX($C$5:$C$9)-MIN($C$5:$C$9))*100 -> 98.991084 | D17: =E9 -> 82 | E17: =(MAX($G$5:$G$9)-G9)/(MAX($G$5:$G$9)-MIN($G$5:$G$9))*100 -> 12.461059
A34: Read: no country wins all three. Saudi is strong on economics AND security but poor on carbon; Norway leads economics and carbon but is mid on security (98% hydro concentration); the US is the most energy-secure grid but with long interconnection queue time. Sources: NPV = Comparison (Country Engine); Energy security = WEC Trilemma dimension (Energy Sovereignty tab); Carbon = Comparison (Country Engine).
A36: Check — each lens ranks 1–5 (sum = 15): | C36: =--((SUM(D5:D9)<>15)+(SUM(F5:F9)<>15)+(SUM(H5:H9)<>15)>0) -> 0

Sheet Power Cost
A1: Power Cost — how much of revenue the electricity bill eats, by country × scenario | C1: =IF(Checks!$C$4>0,"MODEL IN ERROR","checks OK") -> checks OK
A2: Materiality = power cost ÷ revenue, both at the entry-price operating point. Entry price = P0·(1−decline)^TTP, floored. The ratio is DEAL-INVARIANT (paid occupancy cancels); $m magnitudes are shown at the active deal. Regime thresholds: “material” ≥ 10% of revenue, “power-heavy” ≥ 20% (Assumptions r76–77). Method identical to the Revenue Mix tab, generalised to all three scenarios.
A4: Materiality summary — power cost as % of revenue at entry (this table feeds the chart)
B5: Country | C5: Bear | D5: Base | E5: Bull | F5: Material line (10%)
B6: =Comparison!C6 -> Norway | C6: =I16 -> 0.090196078 | D6: =I24 -> 0.027320906 | E6: =I32 -> 0.0080327865 | F6: =Assumptions!$C$76 -> 0.1
B7: =Comparison!D6 -> United States | C7: =I17 -> 0.16568627 | D7: =I25 -> 0.052 | E7: =I33 -> 0.018134438 | F7: =Assumptions!$C$76 -> 0.1
B8: =Comparison!E6 -> India | C8: =I18 -> 0.17647059 | D8: =I26 -> 0.081380208 | E8: =I34 -> 0.02741302 | F8: =Assumptions!$C$76 -> 0.1
B9: =Comparison!F6 -> Ireland | C9: =I19 -> 0.21176471 | D9: =I27 -> 0.12 | E9: =I35 -> 0.057418721 | F9: =Assumptions!$C$76 -> 0.1
B10: =Comparison!G6 -> Saudi Arabia | C10: =I20 -> 0.092401961 | D10: =I28 -> 0.031798246 | E10: =I36 -> 0.010128296 | F10: =Assumptions!$C$76 -> 0.1
B11: Check — Base column ties to live engine when Base is active (|Δ|<0.001) | C11: =IF(Assumptions!$B$4<>"Base",0,--(MAX(ABS(D6-'Revenue Mix'!C20),ABS(D7-'Revenue Mix'!D20),ABS(D8-'Revenue Mix'!E20),ABS(D9-'Revenue Mix'!F20),ABS(D10-'Revenue Mix'!G20))>0.001)) -> 0
A13: Working — entry-price build by scenario (transparent; each block reconciles to the summary and to the live engine)
A14: Bear — glut (P0 $4.00 · decline 30%/yr · floor $1.70)
B15: Country | C15: Power $/MWh | D15: PUE (x) | E15: Eff. burden $/MWh | F15: Entry price $/GPU-hr | G15: Power cost $m | H15: Revenue $m | I15: Power % of rev | J15: Regime
B16: =Comparison!C6 -> Norway | C16: =INDEX(Assumptions!$C$50:$E$54,MATCH($B16,Assumptions!$B$50:$B$54,0),1) -> 80 | D16: =INDEX(Assumptions!$M$50:$M$54,MATCH($B16,Assumptions!$B$50:$B$54,0),1) -> 1.15 | E16: =C16*D16 -> 92 | F16: =MAX(Assumptions!$D$66,Assumptions!$D$14*(1-Assumptions!$D$65)^INDEX(Assumptions!$F$50:$H$54,MATCH($B16,Assumptions!$B$50:$B$54,0),1)) -> 1.7 | G16: =IT_load_MW*D16*Hours_per_year*C16*Paid_occupancy/Unit_scale -> 70.92096 | H16: =IT_load_MW*Assumptions!$D$12*Hours_per_year*F16*Paid_occupancy/Unit_scale -> 786.2976 | I16: =G16/H16 -> 0.090196078 | J16: =IF(I16<Assumptions!$C$76,"thin",IF(I16<Assumptions!$C$77,"material","power-heavy")) -> thin
B17: =Comparison!D6 -> United States | C17: =INDEX(Assumptions!$C$50:$E$54,MATCH($B17,Assumptions!$B$50:$B$54,0),1) -> 130 | D17: =INDEX(Assumptions!$M$50:$M$54,MATCH($B17,Assumptions!$B$50:$B$54,0),1) -> 1.3 | E17: =C17*D17 -> 169 | F17: =MAX(Assumptions!$D$66,Assumptions!$D$14*(1-Assumptions!$D$65)^INDEX(Assumptions!$F$50:$H$54,MATCH($B17,Assumptions!$B$50:$B$54,0),1)) -> 1.7 | G17: =IT_load_MW*D17*Hours_per_year*C17*Paid_occupancy/Unit_scale -> 130.27872 | H17: =IT_load_MW*Assumptions!$D$12*Hours_per_year*F17*Paid_occupancy/Unit_scale -> 786.2976 | I17: =G17/H17 -> 0.16568627 | J17: =IF(I17<Assumptions!$C$76,"thin",IF(I17<Assumptions!$C$77,"material","power-heavy")) -> material
B18: =Comparison!E6 -> India | C18: =INDEX(Assumptions!$C$50:$E$54,MATCH($B18,Assumptions!$B$50:$B$54,0),1) -> 120 | D18: =INDEX(Assumptions!$M$50:$M$54,MATCH($B18,Assumptions!$B$50:$B$54,0),1) -> 1.5 | E18: =C18*D18 -> 180 | F18: =MAX(Assumptions!$D$66,Assumptions!$D$14*(1-Assumptions!$D$65)^INDEX(Assumptions!$F$50:$H$54,MATCH($B18,Assumptions!$B$50:$B$54,0),1)) -> 1.7 | G18: =IT_load_MW*D18*Hours_per_year*C18*Paid_occupancy/Unit_scale -> 138.7584 | H18: =IT_load_MW*Assumptions!$D$12*Hours_per_year*F18*Paid_occupancy/Unit_scale -> 786.2976 | I18: =G18/H18 -> 0.17647059 | J18: =IF(I18<Assumptions!$C$76,"thin",IF(I18<Assumptions!$C$77,"material","power-heavy")) -> material
B19: =Comparison!F6 -> Ireland | C19: =INDEX(Assumptions!$C$50:$E$54,MATCH($B19,Assumptions!$B$50:$B$54,0),1) -> 180 | D19: =INDEX(Assumptions!$M$50:$M$54,MATCH($B19,Assumptions!$B$50:$B$54,0),1) -> 1.2 | E19: =C19*D19 -> 216 | F19: =MAX(Assumptions!$D$66,Assumptions!$D$14*(1-Assumptions!$D$65)^INDEX(Assumptions!$F$50:$H$54,MATCH($B19,Assumptions!$B$50:$B$54,0),1)) -> 1.7 | G19: =IT_load_MW*D19*Hours_per_year*C19*Paid_occupancy/Unit_scale -> 166.51008 | H19: =IT_load_MW*Assumptions!$D$12*Hours_per_year*F19*Paid_occupancy/Unit_scale -> 786.2976 | I19: =G19/H19 -> 0.21176471 | J19: =IF(I19<Assumptions!$C$76,"thin",IF(I19<Assumptions!$C$77,"material","power-heavy")) -> power-heavy
B20: =Comparison!G6 -> Saudi Arabia | C20: =INDEX(Assumptions!$C$50:$E$54,MATCH($B20,Assumptions!$B$50:$B$54,0),1) -> 65 | D20: =INDEX(Assumptions!$M$50:$M$54,MATCH($B20,Assumptions!$B$50:$B$54,0),1) -> 1.45 | E20: =C20*D20 -> 94.25 | F20: =MAX(Assumptions!$D$66,Assumptions!$D$14*(1-Assumptions!$D$65)^INDEX(Assumptions!$F$50:$H$54,MATCH($B20,Assumptions!$B$50:$B$54,0),1)) -> 1.7 | G20: =IT_load_MW*D20*Hours_per_year*C20*Paid_occupancy/Unit_scale -> 72.65544 | H20: =IT_load_MW*Assumptions!$D$12*Hours_per_year*F20*Paid_occupancy/Unit_scale -> 786.2976 | I20: =G20/H20 -> 0.092401961 | J20: =IF(I20<Assumptions!$C$76,"thin",IF(I20<Assumptions!$C$77,"material","power-heavy")) -> thin
A22: Base — central (P0 $5.70 · decline 20%/yr · floor $2.50)
B23: Country | C23: Power $/MWh | D23: PUE (x) | E23: Eff. burden $/MWh | F23: Entry price $/GPU-hr | G23: Power cost $m | H23: Revenue $m | I23: Power % of rev | J23: Regime
B24: =Comparison!C6 -> Norway | C24: =INDEX(Assumptions!$C$50:$E$54,MATCH($B24,Assumptions!$B$50:$B$54,0),2) -> 52 | D24: =INDEX(Assumptions!$M$50:$M$54,MATCH($B24,Assumptions!$B$50:$B$54,0),1) -> 1.15 | E24: =C24*D24 -> 59.8 | F24: =MAX(Assumptions!$E$66,Assumptions!$E$14*(1-Assumptions!$E$65)^INDEX(Assumptions!$F$50:$H$54,MATCH($B24,Assumptions!$B$50:$B$54,0),2)) -> 3.648 | G24: =IT_load_MW*D24*Hours_per_year*C24*Paid_occupancy/Unit_scale -> 46.098624 | H24: =IT_load_MW*Assumptions!$E$12*Hours_per_year*F24*Paid_occupancy/Unit_scale -> 1687.3021 | I24: =G24/H24 -> 0.027320906 | J24: =IF(I24<Assumptions!$C$76,"thin",IF(I24<Assumptions!$C$77,"material","power-heavy")) -> thin
B25: =Comparison!D6 -> United States | C25: =INDEX(Assumptions!$C$50:$E$54,MATCH($B25,Assumptions!$B$50:$B$54,0),2) -> 60 | D25: =INDEX(Assumptions!$M$50:$M$54,MATCH($B25,Assumptions!$B$50:$B$54,0),1) -> 1.3 | E25: =C25*D25 -> 78 | F25: =MAX(Assumptions!$E$66,Assumptions!$E$14*(1-Assumptions!$E$65)^INDEX(Assumptions!$F$50:$H$54,MATCH($B25,Assumptions!$B$50:$B$54,0),2)) -> 2.5 | G25: =IT_load_MW*D25*Hours_per_year*C25*Paid_occupancy/Unit_scale -> 60.12864 | H25: =IT_load_MW*Assumptions!$E$12*Hours_per_year*F25*Paid_occupancy/Unit_scale -> 1156.32 | I25: =G25/H25 -> 0.052 | J25: =IF(I25<Assumptions!$C$76,"thin",IF(I25<Assumptions!$C$77,"material","power-heavy")) -> thin
B26: =Comparison!E6 -> India | C26: =INDEX(Assumptions!$C$50:$E$54,MATCH($B26,Assumptions!$B$50:$B$54,0),2) -> 95 | D26: =INDEX(Assumptions!$M$50:$M$54,MATCH($B26,Assumptions!$B$50:$B$54,0),1) -> 1.5 | E26: =C26*D26 -> 142.5 | F26: =MAX(Assumptions!$E$66,Assumptions!$E$14*(1-Assumptions!$E$65)^INDEX(Assumptions!$F$50:$H$54,MATCH($B26,Assumptions!$B$50:$B$54,0),2)) -> 2.9184 | G26: =IT_load_MW*D26*Hours_per_year*C26*Paid_occupancy/Unit_scale -> 109.8504 | H26: =IT_load_MW*Assumptions!$E$12*Hours_per_year*F26*Paid_occupancy/Unit_scale -> 1349.8417 | I26: =G26/H26 -> 0.081380208 | J26: =IF(I26<Assumptions!$C$76,"thin",IF(I26<Assumptions!$C$77,"material","power-heavy")) -> thin
B27: =Comparison!F6 -> Ireland | C27: =INDEX(Assumptions!$C$50:$E$54,MATCH($B27,Assumptions!$B$50:$B$54,0),2) -> 150 | D27: =INDEX(Assumptions!$M$50:$M$54,MATCH($B27,Assumptions!$B$50:$B$54,0),1) -> 1.2 | E27: =C27*D27 -> 180 | F27: =MAX(Assumptions!$E$66,Assumptions!$E$14*(1-Assumptions!$E$65)^INDEX(Assumptions!$F$50:$H$54,MATCH($B27,Assumptions!$B$50:$B$54,0),2)) -> 2.5 | G27: =IT_load_MW*D27*Hours_per_year*C27*Paid_occupancy/Unit_scale -> 138.7584 | H27: =IT_load_MW*Assumptions!$E$12*Hours_per_year*F27*Paid_occupancy/Unit_scale -> 1156.32 | I27: =G27/H27 -> 0.12 | J27: =IF(I27<Assumptions!$C$76,"thin",IF(I27<Assumptions!$C$77,"material","power-heavy")) -> material
B28: =Comparison!G6 -> Saudi Arabia | C28: =INDEX(Assumptions!$C$50:$E$54,MATCH($B28,Assumptions!$B$50:$B$54,0),2) -> 48 | D28: =INDEX(Assumptions!$M$50:$M$54,MATCH($B28,Assumptions!$B$50:$B$54,0),1) -> 1.45 | E28: =C28*D28 -> 69.6 | F28: =MAX(Assumptions!$E$66,Assumptions!$E$14*(1-Assumptions!$E$65)^INDEX(Assumptions!$F$50:$H$54,MATCH($B28,Assumptions!$B$50:$B$54,0),2)) -> 3.648 | G28: =IT_load_MW*D28*Hours_per_year*C28*Paid_occupancy/Unit_scale -> 53.653248 | H28: =IT_load_MW*Assumptions!$E$12*Hours_per_year*F28*Paid_occupancy/Unit_scale -> 1687.3021 | I28: =G28/H28 -> 0.031798246 | J28: =IF(I28<Assumptions!$C$76,"thin",IF(I28<Assumptions!$C$77,"material","power-heavy")) -> thin
A30: Bull — tight (P0 $9.00 · decline 15%/yr · floor $2.50)
B31: Country | C31: Power $/MWh | D31: PUE (x) | E31: Eff. burden $/MWh | F31: Entry price $/GPU-hr | G31: Power cost $m | H31: Revenue $m | I31: Power % of rev | J31: Regime
B32: =Comparison!C6 -> Norway | C32: =INDEX(Assumptions!$C$50:$E$54,MATCH($B32,Assumptions!$B$50:$B$54,0),3) -> 30 | D32: =INDEX(Assumptions!$M$50:$M$54,MATCH($B32,Assumptions!$B$50:$B$54,0),1) -> 1.15 | E32: =C32*D32 -> 34.5 | F32: =MAX(Assumptions!$F$66,Assumptions!$F$14*(1-Assumptions!$F$65)^INDEX(Assumptions!$F$50:$H$54,MATCH($B32,Assumptions!$B$50:$B$54,0),3)) -> 7.1581636 | G32: =IT_load_MW*D32*Hours_per_year*C32*Paid_occupancy/Unit_scale -> 26.59536 | H32: =IT_load_MW*Assumptions!$F$12*Hours_per_year*F32*Paid_occupancy/Unit_scale -> 3310.8511 | I32: =G32/H32 -> 0.0080327865 | J32: =IF(I32<Assumptions!$C$76,"thin",IF(I32<Assumptions!$C$77,"material","power-heavy")) -> thin
B33: =Comparison!D6 -> United States | C33: =INDEX(Assumptions!$C$50:$E$54,MATCH($B33,Assumptions!$B$50:$B$54,0),3) -> 45 | D33: =INDEX(Assumptions!$M$50:$M$54,MATCH($B33,Assumptions!$B$50:$B$54,0),1) -> 1.3 | E33: =C33*D33 -> 58.5 | F33: =MAX(Assumptions!$F$66,Assumptions!$F$14*(1-Assumptions!$F$65)^INDEX(Assumptions!$F$50:$H$54,MATCH($B33,Assumptions!$B$50:$B$54,0),3)) -> 5.3765106 | G33: =IT_load_MW*D33*Hours_per_year*C33*Paid_occupancy/Unit_scale -> 45.09648 | H33: =IT_load_MW*Assumptions!$F$12*Hours_per_year*F33*Paid_occupancy/Unit_scale -> 2486.7867 | I33: =G33/H33 -> 0.018134438 | J33: =IF(I33<Assumptions!$C$76,"thin",IF(I33<Assumptions!$C$77,"material","power-heavy")) -> thin
B34: =Comparison!E6 -> India | C34: =INDEX(Assumptions!$C$50:$E$54,MATCH($B34,Assumptions!$B$50:$B$54,0),3) -> 70 | D34: =INDEX(Assumptions!$M$50:$M$54,MATCH($B34,Assumptions!$B$50:$B$54,0),1) -> 1.5 | E34: =C34*D34 -> 105 | F34: =MAX(Assumptions!$F$66,Assumptions!$F$14*(1-Assumptions!$F$65)^INDEX(Assumptions!$F$50:$H$54,MATCH($B34,Assumptions!$B$50:$B$54,0),3)) -> 6.3838279 | G34: =IT_load_MW*D34*Hours_per_year*C34*Paid_occupancy/Unit_scale -> 80.9424 | H34: =IT_load_MW*Assumptions!$F$12*Hours_per_year*F34*Paid_occupancy/Unit_scale -> 2952.6992 | I34: =G34/H34 -> 0.02741302 | J34: =IF(I34<Assumptions!$C$76,"thin",IF(I34<Assumptions!$C$77,"material","power-heavy")) -> thin
B35: =Comparison!F6 -> Ireland | C35: =INDEX(Assumptions!$C$50:$E$54,MATCH($B35,Assumptions!$B$50:$B$54,0),3) -> 130 | D35: =INDEX(Assumptions!$M$50:$M$54,MATCH($B35,Assumptions!$B$50:$B$54,0),1) -> 1.2 | E35: =C35*D35 -> 156 | F35: =MAX(Assumptions!$F$66,Assumptions!$F$14*(1-Assumptions!$F$65)^INDEX(Assumptions!$F$50:$H$54,MATCH($B35,Assumptions!$B$50:$B$54,0),3)) -> 4.5281399 | G35: =IT_load_MW*D35*Hours_per_year*C35*Paid_occupancy/Unit_scale -> 120.25728 | H35: =IT_load_MW*Assumptions!$F$12*Hours_per_year*F35*Paid_occupancy/Unit_scale -> 2094.3915 | I35: =G35/H35 -> 0.057418721 | J35: =IF(I35<Assumptions!$C$76,"thin",IF(I35<Assumptions!$C$77,"material","power-heavy")) -> thin
B36: =Comparison!G6 -> Saudi Arabia | C36: =INDEX(Assumptions!$C$50:$E$54,MATCH($B36,Assumptions!$B$50:$B$54,0),3) -> 30 | D36: =INDEX(Assumptions!$M$50:$M$54,MATCH($B36,Assumptions!$B$50:$B$54,0),1) -> 1.45 | E36: =C36*D36 -> 43.5 | F36: =MAX(Assumptions!$F$66,Assumptions!$F$14*(1-Assumptions!$F$65)^INDEX(Assumptions!$F$50:$H$54,MATCH($B36,Assumptions!$B$50:$B$54,0),3)) -> 7.1581636 | G36: =IT_load_MW*D36*Hours_per_year*C36*Paid_occupancy/Unit_scale -> 33.53328 | H36: =IT_load_MW*Assumptions!$F$12*Hours_per_year*F36*Paid_occupancy/Unit_scale -> 3310.8511 | I36: =G36/H36 -> 0.010128296 | J36: =IF(I36<Assumptions!$C$76,"thin",IF(I36<Assumptions!$C$77,"material","power-heavy")) -> thin
A38: Read: power is a thin slice at today’s tight prices (Bull < 3% almost everywhere) but crosses to MATERIAL under glut, when a long grid queue floors the entry price while local power stays dear. In Bear every country sits at the price floor, so materiality is set purely by PUE × local power: Ireland ~21% and the US/India ~16–18% breach the 10% “material” line, while cheap-power Norway/Saudi stay ~9%. Base: only Ireland (12%) is material. The queue is necessary; the local power price decides. This is the revenue-side mirror of the Holding Cost tab’s cost-side of “queue is destiny.”
A40: Sources: delivered power, time-to-power, PUE and the compute-price path all link from Assumptions (country levers r50–54; price path r14/r65/r66; sources [22][23][37] power, [24]–[28][46] TTP, [4] PUE, [5][30][34][35][36] price/floor). Materiality thresholds are analyst-derived presentation cut-offs (Assumptions r76–77). Method mirrors the Revenue Mix tab, generalised across scenarios.

Sheet Revenue Mix
A1: Revenue Mix — power is a thin slice at today’s price, but a long grid queue can flip it: power share rises as the eroded entry price falls, crossing to “material” where the queue floors the price AND local power is dear. | C1: =IF(Checks!$C$4>0,"MODEL IN ERROR","checks OK") -> checks OK
A2: Annual steady-state P&L as a share of revenue for the selected country/scenario/deal (Assumptions). Blue = linked from Calculations. Power is ~2% — the tornado confirms it barely moves NPV.
A4: Share of revenue
B5: =Assumptions!$B$5&" "&Assumptions!$B$4&" / "&Assumptions!$B$7 -> Norway Base / Contracted | C5: Power | D5: Other opex | E5: EBITDA
B6: Share of revenue (%) | C6: =Calculations!$C$10/Calculations!$C$9 -> 0.01748538 | D6: =(Calculations!$C$9-Calculations!$C$10-Calculations!$C$14)/Calculations!$C$9 -> 0.032798394 | E6: =Calculations!$C$14/Calculations!$C$9 -> 0.94971623
B8: Power cost ($m) | C8: =Calculations!$C$10 -> 46.098624
B9: Revenue ($m) | C9: =Calculations!$C$9 -> 2636.4096
B10: Annual EBITDA ($m) | C10: =Calculations!$C$14 -> 2503.841
B12: Check: shares sum to 100% | C12: =--(ABS(C6+D6+E6-1)>0.001) -> 0
A15: Power Regime — where power crosses from a thin slice to a material cost. Power cost is fixed per period; revenue scales with the entry price, so power share rises as P_e falls. Flip price is analytic.
B16: Metric | C16: =Comparison!C6 -> Norway | D16: =Comparison!D6 -> United States | E16: =Comparison!E6 -> India | F16: =Comparison!F6 -> Ireland | G16: =Comparison!G6 -> Saudi Arabia
B17: Entry price P_e ($/GPU-hr) | C17: =Comparison!C17 -> 3.648 | D17: =Comparison!D17 -> 2.5 | E17: =Comparison!E17 -> 2.9184 | F17: =Comparison!F17 -> 2.5 | G17: =Comparison!G17 -> 3.648
B18: Power cost ($m/yr) | C18: =Comparison!C19 -> 46.098624 | D18: =Comparison!D19 -> 60.12864 | E18: =Comparison!E19 -> 109.8504 | F18: =Comparison!F19 -> 138.7584 | G18: =Comparison!G19 -> 53.653248
B19: Revenue at entry ($m/yr) | C19: =Comparison!C18 -> 1687.3021 | D19: =Comparison!D18 -> 1156.32 | E19: =Comparison!E18 -> 1349.8417 | F19: =Comparison!F18 -> 1156.32 | G19: =Comparison!G18 -> 1687.3021
B20: Power % of revenue at entry | C20: =Comparison!C19/Comparison!C18 -> 0.027320906 | D20: =Comparison!D19/Comparison!D18 -> 0.052 | E20: =Comparison!E19/Comparison!E18 -> 0.081380208 | F20: =Comparison!F19/Comparison!F18 -> 0.12 | G20: =Comparison!G19/Comparison!G18 -> 0.031798246
B21: EBITDA % at entry | C21: =Comparison!C23/Comparison!C18 -> 0.9214316 | D21: =Comparison!D23/Comparison!D18 -> 0.86023883 | E21: =Comparison!E23/Comparison!E18 -> 0.85138598 | F21: =Comparison!F23/Comparison!F18 -> 0.80888647 | G21: =Comparison!G23/Comparison!G18 -> 0.92011167
B22: 1 - Power (% of revenue at entry) | C22: =1-C20 -> 0.97267909 | D22: =1-D20 -> 0.948 | E22: =1-E20 -> 0.91861979 | F22: =1-F20 -> 0.88 | G22: =1-G20 -> 0.96820175
B23: Regime (thin < material threshold · material · power-heavy above heavy threshold) | C23: =IF(C20<Assumptions!$C$76,"thin",IF(C20<Assumptions!$C$77,"material","power-heavy")) -> thin | D23: =IF(D20<Assumptions!$C$76,"thin",IF(D20<Assumptions!$C$77,"material","power-heavy")) -> thin | E23: =IF(E20<Assumptions!$C$76,"thin",IF(E20<Assumptions!$C$77,"material","power-heavy")) -> thin | F23: =IF(F20<Assumptions!$C$76,"thin",IF(F20<Assumptions!$C$77,"material","power-heavy")) -> material | G23: =IF(G20<Assumptions!$C$76,"thin",IF(G20<Assumptions!$C$77,"material","power-heavy")) -> thin
B24: Flip price → power = material threshold ($/GPU-hr) [analytic] | C24: =Comparison!C19*Compute_P0/(Assumptions!$C$76*Calculations!$C$9) -> 0.99666667 | D24: =Comparison!D19*Compute_P0/(Assumptions!$C$76*Calculations!$C$9) -> 1.3 | E24: =Comparison!E19*Compute_P0/(Assumptions!$C$76*Calculations!$C$9) -> 2.375 | F24: =Comparison!F19*Compute_P0/(Assumptions!$C$76*Calculations!$C$9) -> 3 | G24: =Comparison!G19*Compute_P0/(Assumptions!$C$76*Calculations!$C$9) -> 1.16
B25: Flip price → power = heavy threshold ($/GPU-hr) [analytic] | C25: =Comparison!C19*Compute_P0/(Assumptions!$C$77*Calculations!$C$9) -> 0.49833333 | D25: =Comparison!D19*Compute_P0/(Assumptions!$C$77*Calculations!$C$9) -> 0.65 | E25: =Comparison!E19*Compute_P0/(Assumptions!$C$77*Calculations!$C$9) -> 1.1875 | F25: =Comparison!F19*Compute_P0/(Assumptions!$C$77*Calculations!$C$9) -> 1.5 | G25: =Comparison!G19*Compute_P0/(Assumptions!$C$77*Calculations!$C$9) -> 0.58
B26: Already past its material flip at entry? (the queue has made power material) | C26: =IF(C17<=C24,"YES","no") -> no | D26: =IF(D17<=D24,"YES","no") -> no | E26: =IF(E17<=E24,"YES","no") -> no | F26: =IF(F17<=F24,"YES","no") -> YES | G26: =IF(G17<=G24,"YES","no") -> no
A27: Read (Base/Contracted): power is ~2.4–2.6% of revenue for the cheap-power leaders (Norway, Saudi) at entry, and crosses the 10% material line only for Ireland (12.5%) — its .40 floored entry price sits below its ~.00 flip price — while the US stays thin (5.4%) despite the same price floor because its power is cheap; the queue is necessary, the power price decides.
A30: (Compute-price erosion path moved to the dedicated Price Path tab.)

Sheet ▸ CHECKS
A1: ▸ CHECKS & REVIEW

Sheet Checks
A1: Checks | C1: =IF(Checks!$C$4>0,"MODEL IN ERROR","checks OK") -> checks OK
A2: Error tolerance ($m) | C2: 0.5
A4: ERROR total (must be 0) | C4: =SUM(C7:C10)+SUM(C17:C19)+SUM(C21:C25)+C27+C30+C20 -> 0
A5: SENSE total (review if >0) | C5: =SUM(C12:C16)+C26+C29 -> 0
A6: Check | B6: Value | C6: Flag (1=triggered)
A7: Error: single-country NPV ties to dashboard | B7: =Calculations!C61-INDEX(Comparison!$C$38:$G$38,MATCH(Assumptions!$B$5,Comparison!$C$6:$G$6,0)) -> 0 | C7: =--(ABS($B7)>ErrorTolerance) -> 0
A8: Error: single-hold exit fits the horizon (≤19) | B8: =Calculations!$C$20+GPU_life-1 -> 6 | C8: =--((Calculations!$C$20+GPU_life)>19) -> 0
A9: Error: outputs free of Excel errors | B9: =--OR(ISERROR(Calculations!C61),ISERROR(Calculations!C64)) -> 0 | C9: =--OR(ISERROR(Calculations!C61),ISERROR(Calculations!C64)) -> 0
A10: Error: Calculations row-checks | B10: =Calculations!C58 -> 0 | C10: =--(Calculations!C58>0) -> 0
A11: Sense checks
A12: Sense: power 1–40% of revenue | B12: =Calculations!$C$10/Calculations!$C$9 -> 0.01748538 | C12: =--OR(Calculations!$C$10/Calculations!$C$9<0.01,Calculations!$C$10/Calculations!$C$9>0.4) -> 0
A13: Sense: IRR within -20% to 40% | B13: =Calculations!C62 -> 0.18467513 | C13: =IF(ISNUMBER(Calculations!C62),--OR(Calculations!C62<-0.2,Calculations!C62>0.4),0) -> 0
A14: Sense: break-even util <= 100% (n/a when all-loss) | B14: =Calculations!C64 -> 0.59483429 | C14: =IF(ISNUMBER(Calculations!C64),--(Calculations!C64>1),0) -> 0
A15: Sense: facility life >= GPU life | B15: =Assumptions!$F$34-Assumptions!$G$16 -> 10 | C15: =--(Assumptions!$F$34<Assumptions!$G$16) -> 0
A16: Power delivered vs observed industrial all-in | B16: ='Power Build-up'!$C$13 -> 0.054545455 | C16: ='Power Build-up'!$D$13 -> 0
A17: Error: BASE capex/MW within sourced band $30–50m/MW | B17: ='Unit Economics'!$C$15 -> 42.6 | C17: =--OR('Unit Economics'!$C$15<'Unit Economics'!$D$15,'Unit Economics'!$C$15>'Unit Economics'!$E$15) -> 0
A18: Error: BASE revenue/MW/yr within sourced band $15–40m/MW | B18: ='Unit Economics'!$C$16 -> 26.364096 | C18: =--OR('Unit Economics'!$C$16<'Unit Economics'!$D$16,'Unit Economics'!$C$16>'Unit Economics'!$E$16) -> 0
A19: Error: buildout schedule + roll-up reconcile to IT load & capex | B19: ='Buildout Schedule'!$H$3 -> 0 | C19: =--OR('Buildout Schedule'!$H$3>ErrorTolerance,ABS('Unit Economics'!$C$21)>ErrorTolerance) -> 0
A20: WETI electricity mix sums to 100% per country | B20: ='Energy Security'!$C$15 -> 0 | C20: ='Energy Security'!$D$15 -> 0
A21: Error: GPU density (NVIDIA datasheet) ties to Assumptions | B21: ='GPU Specs'!$F$7-Assumptions!$G$12 -> 0 | C21: =--(ABS($B21)>0) -> 0
A22: Error: compute-price P0 — ALL 3 scenarios within their sourced bands (unified control, table rows 33–37) | B22: =$E$36 -> 0 | C22: =--($E$36>0) -> 0
A23: Error: power build-up ties to country table (all 5) | B23: =SUMPRODUCT(ABS('Power Build-up'!$E$5:$E$9-Assumptions!$D$50:$D$54)) -> 0 | C23: =--(ABS($B23)>ErrorTolerance) -> 0
A24: Error: WACC build-up ties to country table (all 5) | B24: =SUMPRODUCT(ABS('WACC Build-up'!$F$6:$F$10-Assumptions!$J$50:$J$54)) -> 0.0002 | C24: =--(ABS($B24)>0.001) -> 0
A25: Error: capex stack ties to Unit Economics per-MW | B25: ='Capex Stack'!$C$11 -> 0 | C25: =--(ABS($B25)>ErrorTolerance) -> 0
A26: Sense: tornado base ≈ engine NPV (contracted closed-form; exact at Base, approximate when the tax-loss kink binds) | B26: =Sensitivity!C44-Sensitivity!C15 -> -2.2737368e-12 | C26: =--((Sensitivity!C48+Sensitivity!C76)>0) -> 0
A27: Error: Deal Comparison active-deal NPV ties to Comparison (all 5) | B27: ='Deal Comparison'!$C$43 -> 0 | C27: =--('Deal Comparison'!$C$43>ErrorTolerance) -> 0
A29: Sense: n/a (single-hold, no re-tenant) | B29: ='Price Floor'!$B$32 -> External-coherence flag (0=ok: band-low ≤ model floor ≤ band-high) | C29: ='Price Floor'!$C$32 -> 0
B30: ='Price Floor'!$B$31 -> Internal-consistency flag (0=ok; |Base floor − model floor|, enforced at Base·Contracted) | C30: ='Price Floor'!$C$31 -> 0
A31: Compute-price P0 input validation — one control, every scenario within its sourced range
A32: Scenario | B32: P0 $/GPU-hr (B200 committed) | C32: Low | D32: High | E32: Out?
A33: Bear | B33: =Assumptions!$D$14 -> 4 | C33: 3.4 | D33: =Assumptions!$E$14 -> 5.7 | E33: =--OR(B33<C33,B33>D33) -> 0 | F33: Bear ∈ [custom-contract low $3.40 (getDeploying) → Base]
A34: Base | B34: =Assumptions!$E$14 -> 5.7 | C34: ='Compute Price Data'!$C$20 -> 3.35 | D34: ='Compute Price Data'!$C$21 -> 8.2 | E34: =--OR(B34<C34,B34>D34) -> 0 | F34: Base ∈ [B200 spot/committed floor $3.35 → on-demand ceiling $8.20] (observed B200 envelope)
A35: Bull | B35: =Assumptions!$F$14 -> 9 | C35: ='Compute Price Data'!$C$21 -> 8.2 | D35: 10 | E35: =--OR(B35<C35,B35>D35) -> 0 | F35: Bull ∈ [on-demand ceiling $8.20 → tight-market/supply-peak $10]; B200 on-demand reaches $8.19, AWS $12.36
A36: All scenarios in band (0 = pass) → feeds error C23 | E36: =SUM(E33:E35) -> 0

Sheet Review
A1: Review | C1: =IF(Checks!$C$4>0,"MODEL IN ERROR","checks OK") -> checks OK
A2: Independent review per PwC guidelines. Reviewer must not be the builder. Status via dropdown (Pass/Concern/Fail).
A4: Section | B4: Review step | C4: Status | D4: Reviewer / note
A5: Inputs | B5: All inputs sourced, dated, confidence-flagged (D6 fairness) | C5: Pass | D5: HD 17 Aug, 2026 (self reviewed by builder, Claude Opus 4.8, and ChatGPT 5.6 Sol)
A6: Inputs | B6: No hard-codes in formulas; scenario switch drives Active column | C6: Pass | D6: HD
A7: Data foundation | B7: Unit Economics per-MW rolls up; Buildout & Scenario Grid Tables reconcile | C7: Pass | D7: HD
A8: Calculations | B8: One formula per row copied across; timing flags correct | C8: Pass | D8: HD
A9: Calculations | B9: No banned functions (OFFSET/INDIRECT/circular/array/nested IF) | C9: Pass | D9: HD
A10: External anchors | B10: capex/MW & revenue/MW/yr inside sourced bands | C10: Pass | D10: HD
A11: Checks | B11: All error flags = 0 under Bear/Base/Bull & Contracted/Merchant | C11: Pass | D11: HD
A12: Compliance | B12: Run Model_Compliance_Checklist.md end-to-end | C12: Pass | D12: HD
